Workbook

Sheet README
A1: IntelCost Equipment Catalog - review draft
A2: Built 2026-10-21 from the research notes in 'Construction equipment catalog and rates' (no new research). For review by the Director of Estimating, then for building the Equipment List library and the equipment picker in the Equipment cost component.
A4: How a row is used in the app
A5: 1. Pick | B5: User picks Equipment type -> size class (one Equipment row, Equip_ID).
A6: 2. Activity | B6: User picks an Activity the machine serves (Equipment.Activities lists the Activity_IDs; Production holds the Equip_ID x Activity_ID rates). Production auto-fills Prod_typical (low/high shown for judgement).
A7: 3. Hours | B7: Hours = Quantity / Production (convert BCY/LCY/CCY with Factors section 1). For crew/DOT daily rates: days = Quantity / daily rate; equipment hours = days x shift hours. Duration-based equipment (lifts, cranes, telehandlers, compressors, generators, lights, pumps, shoring, site) has no production rate: duration = the served crew/activity duration (Duration_Norms).
A8: 4. Cost | B8: Cost = equipment basis + fuel + operator + mob/demob: - Rental basis: Rent_day/week/4wk (bare, no operator, no fuel), chosen by duration (cheapest combination), x equipment location factor (Settings B8). - Owned basis: Owned_rate_hr_excl_fuel x hours x location factor. - Fuel: Fuel_gal_hr_med (low/high by duty) x hours x user fuel price (Settings B4). Do NOT add fuel to Owned_rate_hr_incl_fuel. - Operator: hours x the project's wage set for Typical_operator_craft (labor). NEVER from this workbook. - Operated rows (Rent_basis = operated: cranes, concrete pumps, dump trucks with driver) already include the operator; do not add labor. - Mob + demob: one-time per move, counted once per resource per project (Mob_Demob; Default_mob_one_way / Default_demob_one_way at Settings B6 miles).
A10: Sheets
A11: README | B11: This page: workflow, column dictionary, confidence legend, rate dates, caveats.
A12: Equipment | B12: One row per equipment size class (628 rows). Rates, fuel, transport, default mob/demob, activities, notes and flags.
A13: Activities | B13: Activity master: unit, norm basis (per hour at 50-min hour vs per 8-hr / working day), method formula, inputs, sources, type (Production / Duration / Quantity).
A14: Production | B14: Equip_ID x Activity_ID (592 rows): Prod_low / typical / high with unit, basis, default conditions, calculation shown, sources, confidence. Calculated rows are live formulas driven by Input_capacity (yellow) and Settings (efficiency, speeds).
A15: Duration_Norms | B15: How duration is derived for duration-based equipment; minimum hours/rental periods; shift/overtime; standby; Caltrans delay/OT factors.
A16: Factors | B16: Soil conversions, fill factors, efficiency, operator, dozer corrections, rolling resistance, cycle components, compaction (16.3), water, grader, fuel factors.
A17: Mob_Demob | B17: Transport classes with $/loaded mile, minimums, permits, escorts; calculator; legal limits; rental delivery norms.
A18: Rental_Terms | B18: Hour limits (8/40/160 vs 176), overtime, multipliers observed, damage waiver, environmental fee, refuel, shift multipliers.
A19: Location | B19: Method (equipment factor / local fuel / wage-set operator) and evidence (RSMeans IL, Blue Book, EIA PADD diesel).
A20: Sources | B20: Source_ID register: title, publisher, edition/date, URL, what it supports.
A21: Gaps | B21: Every missing or weak item with impact and the recommended way to close it; live counts.
A22: Settings | B22: All assumptions referenced by formulas: fuel prices, FEMA back-out diesel price, default mob distance, job efficiency, location factor, fuel factors, multipliers, production speeds. Blue = editable.
A24: Confidence legend (Rent_confidence, Owned_confidence, Production.Confidence)
A25: A (green) | B25: Sourced from 2+ sources that are not derived from each other; median used (per-source values in Notes). ScaffoldExchange (cites Sunbelt/URI/BigRentz) does not count as independent of COSTARS or BigRentz; broad DOZR bands (60-120, 120-180 ft) are not counted as class sources.
A26: B (blue) | B26: Single source, or several sources that are not independent (value as published; FEMA rows are B).
A27: C (amber) | B27: Derived by a stated method: interpolation between adjacent sourced classes (never extrapolated), week/4-week from day by the Settings multipliers, fuel back-out, HP x 0.0486 x load factor, or production calculated from documented formulas. Method is written in Notes / Calc_shown.
A28: D (grey) | B28: No basis. Rate cell left blank; Flags says 'Needs rate' (or 'Needs fuel gal/hr' / input needed). Production rows become D whenever their driving input is blank.
A30: Column dictionary - Equipment
A31: Equip_ID | B31: Stable readable key (TYPE-SUBTYPE-SIZE). Never reuse a retired ID.
A32: Category / Type / Sub_type / Size_class | B32: Picker hierarchy.
A33: Defining_spec / Spec_value / Spec_unit | B33: The spec that defines the class (operating weight, net HP, bucket, ROC, drum width, platform height, capacity...).
A34: Example_models | B34: Representative models from the sources (not an endorsement).
A35: Operating_weight_lb / Net_HP | B35: Representative values from notes (blank = not in notes).
A36: Capacity / Platform_or_lift_height_ft | B36: Bucket/payload/lift capacity; platform height (lifts), lift height (telehandlers).
A37: Fuel_type | B37: diesel / gas / electric / dual / hybrid / propane / none.
A38: Typical_operator_craft | B38: Craft label only - wages come from the project wage set.
A39: Default_billing_basis | B39: day/wk/4wk (bare rental), hr (operated or owned), 4wk/month, LF etc.
A40: Rent_day / Rent_week / Rent_4wk | B40: Bare rental (no operator, no fuel), USD. 4-week = 28 days (Wheeler 176 hr, others 160 hr).
A41: Rent_low_4wk / Rent_high_4wk | B41: Lowest/highest 4-week value across the sources used. For a single source they are blank, EXCEPT where that one source publishes its own range (office trailers, containers, fence, tower crane, rentd compressors) - then they hold that range (see Notes).
A42: Rent_basis | B42: bare or operated.
... A55: Notes / Flags | B55: Every derivation is described in Notes; Flags list Needs rate / Needs fuel / FEMA ⚠ / label corrections.
A57: Rate dates
A58: Rental (earthwork, support) | B58: Dealer sheets 2025 (Wheeler UT Mar 2025; Columbus OH Jun 2025; Burris IL Mar 2025; RTL MN Spring 2025; Nu-Way MO Jan 2025) and Ahearn MA (read Oct 2026); DOZR Mar 2026; rentd Jul 2026.
A59: Rental (aerial) | B59: Mixed: Sunbelt PA COSTARS contract caps 3/2023-3/2024; BigRentz Dec 2022 data; DOZR Mar 2026; ScaffoldExchange Sep 2026. Older figures likely understate 2026.
A60: Operated | B60: Cranes NTX 2025, Dependable Oct 2025, CFCS Jun 2026; pumps Ohio (read Oct 2026), CCE Mar 2026; dump trucks MN DLI May 1 2026, dumptruckrates Sep 2026.
A61: Owned | B61: FEMA 2025 schedule (declarations on/after Jul 1 2025). Fuel: Cat VisionLink Dec 2022. Back-out diesel: EIA 2025 average.
A62: Fuel price default | B62: EIA US on-highway diesel week of Oct 19 2026 = $6.276/gal (Settings B4).
A64: Key caveats
A65: Rental sample | B65: Leans Midwest / Mountain West (UT, OH, IL, MN, MO, MA). No TX/CA/FL bare earthwork sheets. Wheeler (Cat dealer) is consistently the high end; medians used.
A66: Aerial rates | B66: Partly 2022-2024; COSTARS day rates are contract ceilings. Spider/track lifts use COSTARS 'atrium' classes.
A67: FEMA ⚠ | B67: Suspect FEMA values are kept as published and flagged (generators 17-45 kW, pickups, BW120, 13 CY mixer, small pumps, 125 ft boom, V120 trencher, 19 in chipper, 130 CFM compressor). Verify against the PDF. FEMA 8636 'Scraper, Wirtgen WR2400' corrected to stabilizer/recycler.
A68: Fuel back-out | B68: FEMA's embedded diesel price is not published; EIA 2025 average assumed. Gas/LPG FEMA rows have no ex-fuel value (no gasoline basis in notes).
A69: Production | B69: Cat dozer push curves were not obtained: dozer rows use the Peurifoy blade/cycle method with Cat SAE J1265 blade capacities (specs_fill) and Settings dozing speeds (D9-D11 use their published gear speeds). Excavator buckets: typical = midpoint of the GP range from Deere/Komatsu/Cat specs (C); minis 1-2 t and 5-6 t, 45-50 t long-reach etc. stay D (no bucket published). Haul and scraper rows stay D until Settings B22-B27 average speeds are entered (specs give only top speeds and one rimpull worked example, not average haul speeds). DOT daily rates are crew/spread outcomes (include delays), not single-machine output.
A70: Location | B70: Equipment location factor 0.85-1.15 is an inference from RSMeans IL and Blue Book. Never apply the labor factor to equipment.
A71: Mob/demob | B71: Haul $/mile from one trade publisher (2026, high-diesel period). Load/unload hours not sourced (excluded).
A72: Interpolation | B72: C-rated interpolations are linear between adjacent sourced classes and never extrapolated.
A73: Non-monotonic steps | B73: Where a smaller class costs more than the next larger one (or fuel/ex-fuel inverts), the source data is kept and the row is flagged 'Non-monotonic vs <ID> - source data'.
A74: Rounding | B74: All hard-coded medians use half-up rounding (Excel ROUND). A few values differ by 1 from the research-notes tables, which used banker's rounding; those rows say so in Notes.
A75: Out of scope | B75: Snow & ice equipment (FEMA 8450-8458, 8549-8565), aircraft/helicopters/drones (8900-8916), marine (barges, tow/push/tug boats, airboats), fire apparatus, ambulances, buses, police and garbage vehicles are intentionally excluded. Log skidders, blowers, grizzly feeders, leaf vac and vans also have no rows (FEMA rates not captured).
A76: IDs | B76: A few IDs contain lowercase 'x' (box sizes, e.g. TB-STL-8x12) or '_' (GEN-5_5). Kept unchanged because IDs are stable keys.
A78: Colours
A79: Blue font | B79: Sourced hard-coded value / editable input
A80: Black font | B80: Formula or text
A81: Yellow fill | B81: Input cell (Settings, Production Input_capacity)
A82: Grey/white bands | B82: Alternate categories on Equipment columns A-E
A83: Red bold flag | B83: FEMA ⚠ value

Sheet Equipment
A1: Equip_ID | B1: Category | C1: Type | D1: Sub_type | E1: Size_class | F1: Defining_spec | G1: Spec_value | H1: Spec_unit | I1: Example_models | J1: Operating_weight_lb | K1: Net_HP | L1: Capacity | M1: Platform_or_lift_height_ft | N1: Fuel_type | O1: Typical_operator_craft | P1: Default_billing_basis | Q1: Rent_day | R1: Rent_week | S1: Rent_4wk | T1: Rent_low_4wk | U1: Rent_high_4wk | V1: Rent_basis | W1: Rent_hr_operated | X1: Operated_min_hr | Y1: Rent_source_ids | Z1: Rent_date | AA1: Rent_confidence | AB1: FEMA_code | AC1: Owned_rate_hr_incl_fuel | AD1: Owned_rate_year | AE1: Fuel_gal_hr_low | AF1: Fuel_gal_hr_med | AG1: Fuel_gal_hr_high | AH1: Fuel_source | AI1: Owned_rate_hr_excl_fuel | AJ1: Owned_confidence | AK1: Owned_excl_fuel_confidence | AL1: Standby_rule | AM1: Transport_class | AN1: Transport_weight_lb | AO1: Transport_width_ft | AP1: Permit_likely | AQ1: Default_mob_one_way | AR1: Default_demob_one_way | AS1: Activities | AT1: Notes | AU1: Flags
A2: DZ-CRAWL-D1 | B2: Earthwork | C2: Crawler dozer | D2: Small (Cat D1-D3) | E2: D1 class (~80 hp) | F2: Net HP | G2: 80 | H2: hp | I2: Cat D1 (formerly D3K2) | J2: 17855 | K2: 80 | L2: Blade Cat D1 std blade 1.99 yd3 (LGP 2.17) | N2: diesel | O2: Operating Engineer - heavy equip. group (per WD) | P2: day/wk/4wk | V2: bare | AA2: D | AB2: 8250 | AC2: 47.73 | AD2: FEMA 2025 | AE2: =ROUND(K2*Settings!$B$11*Settings!$B$13,2) -> 1.36 | AF2: =ROUND(K2*Settings!$B$11*Settings!$B$14,2) -> 1.79 | AG2: =ROUND(K2*Settings!$B$11*Settings!$B$15,2) -> 2.33 | AH2: Derived (C): Net_HP x 0.0486 diesel gal/bhp-hr x load factor 0.35/0.46/0.60 [USACE-EP] | AI2: =IF(OR(AC2="",AF2="",Settings!$B$5=""),"",ROUND(AC2-AF2*Settings!$B$5,2)) -> 41.18 | AJ2: B | AK2: C | AL2: Owned: USACE standby = 0.5 x DEPR + FCCM, max 40 hr/wk [USACE-EP]; with only an all-in rate use Caltrans delay factor x rate, max 8 hr/day & 40 hr/wk [CALT-2627]: no class factor captured, use 0.10-0.22 band (inference). Rental: accrues by calendar period. FEMA: not eligible unless intermittent use [FEMA-PG]. | AM2: tilt-trailer | AN2: 17855 | AP2: N | AQ2: =IFERROR(IF(AND(INDEX(Mob_Demob!$D$6:$D$14,MATCH(AM2,Mob_Demob!$A$6:$A$14,0))="",INDEX(Mob_Demob!$G$6:$G$14,MATCH(AM2,Mob_Demob!$A$6:$A$14,0))=""),"",ROUND(MAX(N(INDEX(Mob_Demob!$G$6:$G$14,MATCH(AM2,Mob_Demob!$A$6:$A$14,0))),N(INDEX(Mob_Demob!$D$6:$D$14,MATCH(AM2,Mob_Demob!$A$6:$A$14,0)))*Settings!$B$6)+IF(AP2="Y",N(INDEX(Mob_Demob!$I$6:$I$14,MATCH(AM2,Mob_Demob!$A$6:$A$14,0)))*Settings!$B$19,0)+N(INDEX(Mob_Demob!$L$6:$L$14,MATCH(AM2,Mob_Demob!$A$6:$A$14,0)))*N(INDEX(Mob_Demob!$K$6:$K$14,MATCH(AM2,Mob_Demob!$A$6:$A$14,0)))*Settings!$B$6+N(INDEX(Mob_Demob!$M$6:$M$14,MATCH(AM2,Mob_Demob!$A$6:$A$14,0)))*N(INDEX(Mob_Demob!$N$6:$N$14,MATCH(AM2,Mob_Demob!$A$6:$A$14,0))),0)),"") -> 500 | AR2: =IF(AQ2="","",ROUND(AQ2*Settings!$B$18,0)) -> 500 | AS2: EW-STRIP,EW-PUSH-100,EW-SPREAD,EW-RGRADE | AT2: Weight/HP Ziegler. Max speeds F 5.6 / R 6.2 mph (hydrostatic) [CAT-DOZ-PG]; production uses Settings dozing speeds because no working-speed reduction is sourced. Fuel gal/hr derived (C): Net_HP x USACE fuel factor x load factor (Settings B11-B15). Ex-fuel (C) = FEMA incl-fuel rate - Fuel_gal_hr_med x diesel back-out price (Settings B5). | AU2: Needs rate (rental)
A3: DZ-CRAWL-D2 | B3: Earthwork | C3: Crawler dozer | D3: Small (Cat D1-D3) | E3: D2 class (85+ hp) | F3: Net HP (min) | G3: 85 | H3: hp | I3: Cat D2 (formerly D4K2; 92 hp, 18,382 lb) | J3: 18382 | K3: 92 | L3: Blade Cat D2 std 2.59 yd3 (LGP 2.42) | N3: diesel | O3: Operating Engineer - heavy equip. group (per WD) | P3: day/wk/4wk | V3: bare | AA3: D | AC3: =ROUND(AC2+(AC4-AC2)*(K3-K2)/(K4-K2),2) -> 55.96 | AD3: FEMA 2025 (interpolated) | AE3: =ROUND(K3*Settings!$B$11*Settings!$B$13,2) -> 1.56 | AF3: =ROUND(K3*Settings!$B$11*Settings!$B$14,2) -> 2.06 | AG3: =ROUND(K3*Settings!$B$11*Settings!$B$15,2) -> 2.68 | AH3: Derived (C): Net_HP x 0.0486 diesel gal/bhp-hr x load factor 0.35/0.46/0.60 [USACE-EP] | AI3: =IF(OR(AC3="",AF3="",Settings!$B$5=""),"",ROUND(AC3-AF3*Settings!$B$5,2)) -> 48.42 | AJ3: C | AK3: C | AL3: Owned: USACE standby = 0.5 x DEPR + FCCM, max 40 hr/wk [USACE-EP]; with only an all-in rate use Caltrans delay factor x rate, max 8 hr/day & 40 hr/wk [CALT-2627]: no class factor captured, use 0.10-0.22 band (inference). Rental: accrues by calendar period. FEMA: not eligible unless intermittent use [FEMA-PG]. | AM3: tilt-trailer | AN3: 18382 | AP3: N | AQ3: =IFERROR(IF(AND(INDEX(Mob_Demob!$D$6:$D$14,MATCH(AM3,Mob_Demob!$A$6:$A$14,0))="",INDEX(Mob_Demob!$G$6:$G$14,MATCH(AM3,Mob_Demob!$A$6:$A$14,0))=""),"",ROUND(MAX(N(INDEX(Mob_Demob!$G$6:$G$14,MATCH(AM3,Mob_Demob!$A$6:$A$14,0))),N(INDEX(Mob_Demob!$D$6:$D$14,MATCH(AM3,Mob_Demob!$A$6:$A$14,0)))*Settings!$B$6)+IF(AP3="Y",N(INDEX(Mob_Demob!$I$6:$I$14,MATCH(AM3,Mob_Demob!$A$6:$A$14,0)))*Settings!$B$19,0)+N(INDEX(Mob_Demob!$L$6:$L$14,MATCH(AM3,Mob_Demob!$A$6:$A$14,0)))*N(INDEX(Mob_Demob!$K$6:$K$14,MATCH(AM3,Mob_Demob!$A$6:$A$14,0)))*Settings!$B$6+N(INDEX(Mob_Demob!$M$6:$M$14,MATCH(AM3,Mob_Demob!$A$6:$A$14,0)))*N(INDEX(Mob_Demob!$N$6:$N$14,MATCH(AM3,Mob_Demob!$A$6:$A$14,0))),0)),"") -> 500 | AR3: =IF(AQ3="","",ROUND(AQ3*Settings!$B$18,0)) -> 500 | AS3: EW-STRIP,EW-PUSH-100,EW-SPREAD,EW-RGRADE | AT3: Only the Cat minimum HP (85+) is sourced (Carter); no weight, HP, fuel or rates. Specs from Western States Cat D2 page [CAT-DOZ-PG]. Owned_rate_hr_incl_fuel interpolated (C) between DZ-CRAWL-D1 and DZ-CRAWL-D3 by Net HP (FEMA 2025 endpoints). Fuel gal/hr derived (C): Net_HP x USACE fuel factor x load factor (Settings B11-B15). Ex-fuel (C) = FEMA incl-fuel rate - Fuel_gal_hr_med x diesel back-out price (Settings B5). | AU3: Needs rate (rental)
A4: DZ-CRAWL-D3 | B4: Earthwork | C4: Crawler dozer | D4: Small (Cat D1-D3) | E4: D3 class (~100-104 hp, 20-24k lb) | F4: Net HP | G4: 104 | H4: hp | I4: Cat D3; Komatsu D39EX/PX; Develon DD100/130 | J4: 20640 | K4: 104 | L4: Blade Cat D3 std 2.86 yd3 (LGP 3.06) | N4: diesel | O4: Operating Engineer - heavy equip. group (per WD) | P4: day/wk/4wk | Q4: 875 | R4: 2629 | S4: 6900 | T4: 5413 | U4: 7623 | V4: bare | Y4: W25;C25;R25 | Z4: 2025-2026 | AA4: A | AB4: 8251 | AC4: 64.18 | AD4: FEMA 2025 | AE4: 1.51 | AF4: 1.93 | AG4: 2.36 | AH4: Cat VisionLink Dec 2022, model D3-12 [CATFUEL22] | AI4: =IF(OR(AC4="",AF4="",Settings!$B$5=""),"",ROUND(AC4-AF4*Settings!$B$5,2)) -> 57.12 | AJ4: B | AK4: C | AL4: Owned: USACE standby = 0.5 x DEPR + FCCM, max 40 hr/wk [USACE-EP]; with only an all-in rate use Caltrans delay factor x rate, max 8 hr/day & 40 hr/wk [CALT-2627]: no class factor captured, use 0.10-0.22 band (inference). Rental: accrues by calendar period. FEMA: not eligible unless intermittent use [FEMA-PG]. | AM4: lowboy-legal | AN4: 20640 | AP4: N | AQ4: =IFERROR(IF(AND(INDEX(Mob_Demob!$D$6:$D$14,MATCH(AM4,Mob_Demob!$A$6:$A$14,0))="",INDEX(Mob_Demob!$G$6:$G$14,MATCH(AM4,Mob_Demob!$A$6:$A$14,0))=""),"",ROUND(MAX(N(INDEX(Mob_Demob!$G$6:$G$14,MATCH(AM4,Mob_Demob!$A$6:$A$14,0))),N(INDEX(Mob_Demob!$D$6:$D$14,MATCH(AM4,Mob_Demob!$A$6:$A$14,0)))*Settings!$B$6)+IF(AP4="Y",N(INDEX(Mob_Demob!$I$6:$I$14,MATCH(AM4,Mob_Demob!$A$6:$A$14,0)))*Settings!$B$19,0)+N(INDEX(Mob_Demob!$L$6:$L$14,MATCH(AM4,Mob_Demob!$A$6:$A$14,0)))*N(INDEX(Mob_Demob!$K$6:$K$14,MATCH(AM4,Mob_Demob!$A$6:$A$14,0)))*Settings!$B$6+N(INDEX(Mob_Demob!$M$6:$M$14,MATCH(AM4,Mob_Demob!$A$6:$A$14,0)))*N(INDEX(Mob_Demob!$N$6:$N$14,MATCH(AM4,Mob_Demob!$A$6:$A$14,0))),0)),"") -> 550 | AR4: =IF(AQ4="","",ROUND(AQ4*Settings!$B$18,0)) -> 550 | AS4: EW-STRIP,EW-PUSH-100,EW-PUSH-200,EW-SPREAD,EW-RGRADE | AT4: Operating weight given only as 20,000-24,000 lb class band (rental notes); transport class set manually. Rounded half-up (Excel rule) in revision; may differ by 1 from the notes table, which used banker's rounding. Rent: Median of 3 sources (W 906/2629/7623; C 875/2175/5412; R 850/2850/6900). Class mapping D39->D3, DD100/130->D3 per notes. Ex-fuel (C) = FEMA incl-fuel rate - Fuel_gal_hr_med x diesel back-out price (Settings B5).
A5: DZ-CRAWL-D4 | B5: Earthwork | C5: Crawler dozer | D5: Medium (Cat D4-D7) | E5: D4 class (~130 hp, ~30k lb) | F5: Net HP | G5: 130 | H5: hp | I5: Cat D4 (formerly D6K2); Komatsu D51EX/PX | J5: 29259 | K5: 130 | N5: diesel | O5: Operating Engineer - heavy equip. group (per WD) | P5: day/wk/4wk | Q5: 1142 | R5: 3062 | S5: 8302 | T5: 7075 | U5: 9529 | V5: bare | Y5: W25;C25 | Z5: 2025-2026 | AA5: A | AB5: 8252 | AC5: 86.7 | AD5: FEMA 2025 | AE5: 2.19 | AF5: 2.85 | AG5: 3.5 | AH5: Cat VisionLink Dec 2022, model D4-16 [CATFUEL22] | AI5: =IF(OR(AC5="",AF5="",Settings!$B$5=""),"",ROUND(AC5-AF5*Settings!$B$5,2)) -> 76.27 | AJ5: B | AK5: C | AL5: Owned: USACE standby = 0.5 x DEPR + FCCM, max 40 hr/wk [USACE-EP]; with only an all-in rate use Caltrans delay factor x rate, max 8 hr/day & 40 hr/wk [CALT-2627]: no class factor captured, use 0.10-0.22 band (inference). Rental: accrues by calendar period. FEMA: not eligible unless intermittent use [FEMA-PG]. | AM5: lowboy-legal | AN5: 29259 | AP5: N | AQ5: =IFERROR(IF(AND(INDEX(Mob_Demob!$D$6:$D$14,MATCH(AM5,Mob_Demob!$A$6:$A$14,0))="",INDEX(Mob_Demob!$G$6:$G$14,MATCH(AM5,Mob_Demob!$A$6:$A$14,0))=""),"",ROUND(MAX(N(INDEX(Mob_Demob!$G$6:$G$14,MATCH(AM5,Mob_Demob!$A$6:$A$14,0))),N(INDEX(Mob_Demob!$D$6:$D$14,MATCH(AM5,Mob_Demob!$A$6:$A$14,0)))*Settings!$B$6)+IF(AP5="Y",N(INDEX(Mob_Demob!$I$6:$I$14,MATCH(AM5,Mob_Demob!$A$6:$A$14,0)))*Settings!$B$19,0)+N(INDEX(Mob_Demob!$L$6:$L$14,MATCH(AM5,Mob_Demob!$A$6:$A$14,0)))*N(INDEX(Mob_Demob!$K$6:$K$14,MATCH(AM5,Mob_Demob!$A$6:$A$14,0)))*Settings!$B$6+N(INDEX(Mob_Demob!$M$6:$M$14,MATCH(AM5,Mob_Demob!$A$6:$A$14,0)))*N(INDEX(Mob_Demob!$N$6:$N$14,MATCH(AM5,Mob_Demob!$A$6:$A$14,0))),0)),"") -> 550 | AR5: =IF(AQ5="","",ROUND(AQ5*Settings!$B$18,0)) -> 550 | AS5: EW-CLR-MED,EW-STRIP,EW-PUSH-100,EW-PUSH-200,EW-SPREAD,EW-RGRADE | AT5: Rent: Median (=mean) of 2 sources: W 1133/3286/9529; C 1150/2838/7075. Ex-fuel (C) = FEMA incl-fuel rate - Fuel_gal_hr_med x diesel back-out price (Settings B5).
A6: DZ-CRAWL-D5 | B6: Earthwork | C6: Crawler dozer | D6: Medium (Cat D4-D7) | E6: D5 class (~170 hp, ~40k lb) | F6: Net HP | G6: 170 | H6: hp | I6: Cat D5 LGP VPAT; Komatsu D61EX/PX | J6: 42263 | K6: 170 | L6: Blade Cat D5 VPAT 4.6 yd3 (LGP VPAT 5.5; push-arm SU 5.6) | N6: diesel | O6: Operating Engineer - heavy equip. group (per WD) | P6: day/wk/4wk | Q6: 1554 | R6: 4210 | S6: 11461 | T6: 9200 | U6: 13721 | V6: bare | Y6: W25;C25 | Z6: 2025-2026 | AA6: A | AC6: =ROUND(AC5+(AC7-AC5)*(K6-K5)/(K7-K5),2) -> 109.5 | AD6: FEMA 2025 (interpolated) | AE6: 3.18 | AF6: 4.12 | AG6: 5.06 | AH6: Cat VisionLink Dec 2022, model D5-17 [CATFUEL22] | AI6: =IF(OR(AC6="",AF6="",Settings!$B$5=""),"",ROUND(AC6-AF6*Settings!$B$5,2)) -> 94.42 | AJ6: C | AK6: C | AL6: Owned: USACE standby = 0.5 x DEPR + FCCM, max 40 hr/wk [USACE-EP]; with only an all-in rate use Caltrans delay factor x rate, max 8 hr/day & 40 hr/wk [CALT-2627]: no class factor captured, use 0.10-0.22 band (inference). Rental: accrues by calendar period. FEMA: not eligible unless intermittent use [FEMA-PG]. | AM6: lowboy-legal | AN6: 42263 | AP6: N | AQ6: =IFERROR(IF(AND(INDEX(Mob_Demob!$D$6:$D$14,MATCH(AM6,Mob_Demob!$A$6:$A$14,0))="",INDEX(Mob_Demob!$G$6:$G$14,MATCH(AM6,Mob_Demob!$A$6:$A$14,0))=""),"",ROUND(MAX(N(INDEX(Mob_Demob!$G$6:$G$14,MATCH(AM6,Mob_Demob!$A$6:$A$14,0))),N(INDEX(Mob_Demob!$D$6:$D$14,MATCH(AM6,Mob_Demob!$A$6:$A$14,0)))*Settings!$B$6)+IF(AP6="Y",N(INDEX(Mob_Demob!$I$6:$I$14,MATCH(AM6,Mob_Demob!$A$6:$A$14,0)))*Settings!$B$19,0)+N(INDEX(Mob_Demob!$L$6:$L$14,MATCH(AM6,Mob_Demob!$A$6:$A$14,0)))*N(INDEX(Mob_Demob!$K$6:$K$14,MATCH(AM6,Mob_Demob!$A$6:$A$14,0)))*Settings!$B$6+N(INDEX(Mob_Demob!$M$6:$M$14,MATCH(AM6,Mob_Demob!$A$6:$A$14,0)))*N(INDEX(Mob_Demob!$N$6:$N$14,MATCH(AM6,Mob_Demob!$A$6:$A$14,0))),0)),"") -> 550 | AR6: =IF(AQ6="","",ROUND(AQ6*Settings!$B$18,0)) -> 550 | AS6: EW-CLR-MED,EW-STRIP,EW-PUSH-100,EW-PUSH-200,EW-PUSH-300,EW-SPREAD,EW-RGRADE | AT6: Rounded half-up (Excel rule) in revision; may differ by 1 from the notes table, which used banker's rounding. Rent: Median (=mean) of 2 sources: W 1632/4732/13721; C 1475/3688/9200. Owned_rate_hr_incl_fuel interpolated (C) between DZ-CRAWL-D4 and DZ-CRAWL-D6 by Net HP (FEMA 2025 endpoints). Ex-fuel (C) = FEMA incl-fuel rate - Fuel_gal_hr_med x diesel back-out price (Settings B5).
A7: DZ-CRAWL-D6 | B7: Earthwork | C7: Crawler dozer | D7: Medium (Cat D4-D7) | E7: D6 class (~215-240 hp, ~50k lb) | F7: Net HP | G7: 215 | H7: hp | I7: Cat D6; Komatsu D71PX | J7: 50733 | K7: 215 | L7: Blade Cat D6 SU 7.5 yd3 (VPAT 5.4; angle 5.5; LGP-36 S 5.0) | N7: diesel | O7: Operating Engineer - heavy equip. group (per WD) | P7: day/wk/4wk | Q7: 2111 | R7: 5730 | S7: 15656 | T7: 12000 | U7: 19312 | V7: bare | Y7: W25;C25 | Z7: 2025-2026 | AA7: A | AB7: 8253 | AC7: 135.15 | AD7: FEMA 2025 | AE7: 3.74 | AF7: 4.82 | AG7: 5.9 | AH7: Cat VisionLink Dec 2022, model D6-20 [CATFUEL22] | AI7: =IF(OR(AC7="",AF7="",Settings!$B$5=""),"",ROUND(AC7-AF7*Settings!$B$5,2)) -> 117.51 | AJ7: B | AK7: C | AL7: Owned: USACE standby = 0.5 x DEPR + FCCM, max 40 hr/wk [USACE-EP]; with only an all-in rate use Caltrans delay factor x rate, max 8 hr/day & 40 hr/wk [CALT-2627]: no class factor captured, use 0.10-0.22 band (inference). Rental: accrues by calendar period. FEMA: not eligible unless intermittent use [FEMA-PG]. | AM7: lowboy-legal | AN7: 50733 | AP7: maybe | AQ7: =IFERROR(IF(AND(INDEX(Mob_Demob!$D$6:$D$14,MATCH(AM7,Mob_Demob!$A$6:$A$14,0))="",INDEX(Mob_Demob!$G$6:$G$14,MATCH(AM7,Mob_Demob!$A$6:$A$14,0))=""),"",ROUND(MAX(N(INDEX(Mob_Demob!$G$6:$G$14,MATCH(AM7,Mob_Demob!$A$6:$A$14,0))),N(INDEX(Mob_Demob!$D$6:$D$14,MATCH(AM7,Mob_Demob!$A$6:$A$14,0)))*Settings!$B$6)+IF(AP7="Y",N(INDEX(Mob_Demob!$I$6:$I$14,MATCH(AM7,Mob_Demob!$A$6:$A$14,0)))*Settings!$B$19,0)+N(INDEX(Mob_Demob!$L$6:$L$14,MATCH(AM7,Mob_Demob!$A$6:$A$14,0)))*N(INDEX(Mob_Demob!$K$6:$K$14,MATCH(AM7,Mob_Demob!$A$6:$A$14,0)))*Settings!$B$6+N(INDEX(Mob_Demob!$M$6:$M$14,MATCH(AM7,Mob_Demob!$A$6:$A$14,0)))*N(INDEX(Mob_Demob!$N$6:$N$14,MATCH(AM7,Mob_Demob!$A$6:$A$14,0))),0)),"") -> 550 | AR7: =IF(AQ7="","",ROUND(AQ7*Settings!$B$18,0)) -> 550 | AS7: EW-CLR-MED,EW-STRIP,EW-PUSH-100,EW-PUSH-200,EW-PUSH-300,EW-SPREAD,EW-RGRADE | AT7: Rent: Median (=mean) of 2 sources: W D6/D6 LGP avg 2296/6659/19312; C D71PX 1925/4800/12000. Ex-fuel (C) = FEMA incl-fuel rate - Fuel_gal_hr_med x diesel back-out price (Settings B5).
A8: DZ-CRAWL-D6-XE | B8: Earthwork | C8: Crawler dozer | D8: Medium - electric drive (XE) | E8: D6 XE (215 hp) | F8: Net HP | G8: 215 | H8: hp | I8: Cat D6 XE | J8: 51333 | K8: 215 | N8: hybrid | O8: Operating Engineer - heavy equip. group (per WD) | P8: day/wk/4wk | V8: bare | AA8: D | AE8: 3.59 | AF8: 4.6 | AG8: 5.61 | AH8: Cat VisionLink Dec 2022, model D6-20 XE [CATFUEL22] | AJ8: D | AK8: D | AL8: Owned: USACE standby = 0.5 x DEPR + FCCM, max 40 hr/wk [USACE-EP]; with only an all-in rate use Caltrans delay factor x rate, max 8 hr/day & 40 hr/wk [CALT-2627]: no class factor captured, use 0.10-0.22 band (inference). Rental: accrues by calendar period. FEMA: not eligible unless intermittent use [FEMA-PG]. | AM8: lowboy-legal | AN8: 51333 | AP8: maybe | AQ8: =IFERROR(IF(AND(INDEX(Mob_Demob!$D$6:$D$14,MATCH(AM8,Mob_Demob!$A$6:$A$14,0))="",INDEX(Mob_Demob!$G$6:$G$14,MATCH(AM8,Mob_Demob!$A$6:$A$14,0))=""),"",ROUND(MAX(N(INDEX(Mob_Demob!$G$6:$G$14,MATCH(AM8,Mob_Demob!$A$6:$A$14,0))),N(INDEX(Mob_Demob!$D$6:$D$14,MATCH(AM8,Mob_Demob!$A$6:$A$14,0)))*Settings!$B$6)+IF(AP8="Y",N(INDEX(Mob_Demob!$I$6:$I$14,MATCH(AM8,Mob_Demob!$A$6:$A$14,0)))*Settings!$B$19,0)+N(INDEX(Mob_Demob!$L$6:$L$14,MATCH(AM8,Mob_Demob!$A$6:$A$14,0)))*N(INDEX(Mob_Demob!$K$6:$K$14,MATCH(AM8,Mob_Demob!$A$6:$A$14,0)))*Settings!$B$6+N(INDEX(Mob_Demob!$M$6:$M$14,MATCH(AM8,Mob_Demob!$A$6:$A$14,0)))*N(INDEX(Mob_Demob!$N$6:$N$14,MATCH(AM8,Mob_Demob!$A$6:$A$14,0))),0)),"") -> 550 | AR8: =IF(AQ8="","",ROUND(AQ8*Settings!$B$18,0)) -> 550 | AS8: EW-STRIP,EW-PUSH-100,EW-PUSH-200,EW-PUSH-300,EW-SPREAD,EW-RGRADE | AT8: Diesel-electric drive. No rate source; D6 class row is the nearest priced class. | AU8: Needs rate; Needs rate (rental); Needs rate (owned)
A9: DZ-CRAWL-D6-LGP | B9: Earthwork | C9: Crawler dozer | D9: Medium - LGP (low ground pressure) | E9: D6 LGP | F9: Track variant | G9: LGP | I9: Cat D6 LGP | L9: Blade Cat D6 LGP SU 7.6 yd3 (LGP VPAT 5.9-6.5) | N9: diesel | O9: Operating Engineer - heavy equip. group (per WD) | P9: day/wk/4wk | Q9: 2372 | R9: 6878 | S9: 19947 | V9: bare | Y9: W25 | Z9: 2025 | AA9: B | AJ9: D | AK9: D | AL9: Owned: USACE standby = 0.5 x DEPR + FCCM, max 40 hr/wk [USACE-EP]; with only an all-in rate use Caltrans delay factor x rate, max 8 hr/day & 40 hr/wk [CALT-2627]: no class factor captured, use 0.10-0.22 band (inference). Rental: accrues by calendar period. FEMA: not eligible unless intermittent use [FEMA-PG]. | AM9: lowboy-legal | AP9: maybe | AQ9: =IFERROR(IF(AND(INDEX(Mob_Demob!$D$6:$D$14,MATCH(AM9,Mob_Demob!$A$6:$A$14,0))="",INDEX(Mob_Demob!$G$6:$G$14,MATCH(AM9,Mob_Demob!$A$6:$A$14,0))=""),"",ROUND(MAX(N(INDEX(Mob_Demob!$G$6:$G$14,MATCH(AM9,Mob_Demob!$A$6:$A$14,0))),N(INDEX(Mob_Demob!$D$6:$D$14,MATCH(AM9,Mob_Demob!$A$6:$A$14,0)))*Settings!$B$6)+IF(AP9="Y",N(INDEX(Mob_Demob!$I$6:$I$14,MATCH(AM9,Mob_Demob!$A$6:$A$14,0)))*Settings!$B$19,0)+N(INDEX(Mob_Demob!$L$6:$L$14,MATCH(AM9,Mob_Demob!$A$6:$A$14,0)))*N(INDEX(Mob_Demob!$K$6:$K$14,MATCH(AM9,Mob_Demob!$A$6:$A$14,0)))*Settings!$B$6+N(INDEX(Mob_Demob!$M$6:$M$14,MATCH(AM9,Mob_Demob!$A$6:$A$14,0)))*N(INDEX(Mob_Demob!$N$6:$N$14,MATCH(AM9,Mob_Demob!$A$6:$A$14,0))),0)),"") -> 550 | AR9: =IF(AQ9="","",ROUND(AQ9*Settings!$B$18,0)) -> 550 | AS9: EW-STRIP,EW-PUSH-100,EW-SPREAD,EW-RGRADE | AT9: HP/weight for LGP not in notes. Rent: Wheeler only. | AU9: Needs fuel gal/hr; Needs rate (owned)
A10: DZ-CRAWL-D7 | B10: Earthwork | C10: Crawler dozer | D10: Medium (Cat D4-D7) | E10: D7 class (~265 hp) | F10: Net HP | G10: 265 | H10: hp | I10: Cat D7 (formerly D7E) | J10: 65644 | K10: 265 | L10: Blade Cat D7 (Tier 3, MX page) SU 9.7 yd3 (S 8.1) | N10: diesel | O10: Operating Engineer - heavy equip. group (per WD) | P10: day/wk/4wk | Q10: 2973 | R10: 8623 | S10: 25006 | V10: bare | Y10: W25 | Z10: 2025 | AA10: B | AC10: =ROUND(AC7+(AC11-AC7)*(K10-K7)/(K11-K7),2) -> 161.61 | AD10: FEMA 2025 (interpolated) | AE10: 4.4 | AF10: 5.71 | AG10: 7.02 | AH10: Cat VisionLink Dec 2022, model D7-17 [CATFUEL22] | AI10: =IF(OR(AC10="",AF10="",Settings!$B$5=""),"",ROUND(AC10-AF10*Settings!$B$5,2)) -> 140.71 | AJ10: C | AK10: C | AL10: Owned: USACE standby = 0.5 x DEPR + FCCM, max 40 hr/wk [USACE-EP]; with only an all-in rate use Caltrans delay factor x rate, max 8 hr/day & 40 hr/wk [CALT-2627]: no class factor captured, use 0.10-0.22 band (inference). Rental: accrues by calendar period. FEMA: not eligible unless intermittent use [FEMA-PG]. | AM10: lowboy-permitted | AN10: 65644 | AP10: Y | AQ10: =IFERROR(IF(AND(INDEX(Mob_Demob!$D$6:$D$14,MATCH(AM10,Mob_Demob!$A$6:$A$14,0))="",INDEX(Mob_Demob!$G$6:$G$14,MATCH(AM10,Mob_Demob!$A$6:$A$14,0))=""),"",ROUND(MAX(N(INDEX(Mob_Demob!$G$6:$G$14,MATCH(AM10,Mob_Demob!$A$6:$A$14,0))),N(INDEX(Mob_Demob!$D$6:$D$14,MATCH(AM10,Mob_Demob!$A$6:$A$14,0)))*Settings!$B$6)+IF(AP10="Y",N(INDEX(Mob_Demob!$I$6:$I$14,MATCH(AM10,Mob_Demob!$A$6:$A$14,0)))*Settings!$B$19,0)+N(INDEX(Mob_Demob!$L$6:$L$14,MATCH(AM10,Mob_Demob!$A$6:$A$14,0)))*N(INDEX(Mob_Demob!$K$6:$K$14,MATCH(AM10,Mob_Demob!$A$6:$A$14,0)))*Settings!$B$6+N(INDEX(Mob_Demob!$M$6:$M$14,MATCH(AM10,Mob_Demob!$A$6:$A$14,0)))*N(INDEX(Mob_Demob!$N$6:$N$14,MATCH(AM10,Mob_Demob!$A$6:$A$14,0))),0)),"") -> 1800 | AR10: =IF(AQ10="","",ROUND(AQ10*Settings!$B$18,0)) -> 1800 | AS10: EW-CLR-MED,EW-STRIP,EW-PUSH-100,EW-PUSH-200,EW-PUSH-300,EW-SPREAD,EW-RGRADE | AT10: Transport set to lowboy-permitted: ~65,600 lb machine + tractor/lowboy exceeds 80,000 lb gross (notes' 36 t excavator reasoning). Rent: Wheeler only. Owned_rate_hr_incl_fuel interpolated (C) between DZ-CRAWL-D6 and DZ-CRAWL-D8 by Net HP (FEMA 2025 endpoints). Ex-fuel (C) = FEMA incl-fuel rate - Fuel_gal_hr_med x diesel back-out price (Settings B5).
A11: DZ-CRAWL-D8 | B11: Earthwork | C11: Crawler dozer | D11: Large (Cat D8-D11) | E11: D8 class (~363 hp) | F11: Net HP | G11: 363 | H11: hp | I11: Cat D8 (D8T) | J11: 87083 | K11: 363 | L11: Blade Cat D8 SU 13.47 yd3 (LGP SU 12.9) | N11: diesel | O11: Operating Engineer - heavy equip. group (per WD) | P11: day/wk/4wk | Q11: 4170 | R11: 12092 | S11: 35066 | V11: bare | Y11: W25 | Z11: 2025 | AA11: B | AB11: 8254 | AC11: 213.48 | AD11: FEMA 2025 | AE11: 6.54 | AF11: 8.59 | AG11: 10.64 | AH11: Cat VisionLink Dec 2022, model D8-21 / D8T [CATFUEL22] | AI11: =IF(OR(AC11="",AF11="",Settings!$B$5=""),"",ROUND(AC11-AF11*Settings!$B$5,2)) -> 182.04 | AJ11: B | AK11: C | AL11: Owned: USACE standby = 0.5 x DEPR + FCCM, max 40 hr/wk [USACE-EP]; with only an all-in rate use Caltrans delay factor x rate, max 8 hr/day & 40 hr/wk [CALT-2627]: no class factor captured, use 0.10-0.22 band (inference). Rental: accrues by calendar period. FEMA: not eligible unless intermittent use [FEMA-PG]. | AM11: lowboy-permitted | AN11: 87083 | AP11: Y | AQ11: =IFERROR(IF(AND(INDEX(Mob_Demob!$D$6:$D$14,MATCH(AM11,Mob_Demob!$A$6:$A$14,0))="",INDEX(Mob_Demob!$G$6:$G$14,MATCH(AM11,Mob_Demob!$A$6:$A$14,0))=""),"",ROUND(MAX(N(INDEX(Mob_Demob!$G$6:$G$14,MATCH(AM11,Mob_Demob!$A$6:$A$14,0))),N(INDEX(Mob_Demob!$D$6:$D$14,MATCH(AM11,Mob_Demob!$A$6:$A$14,0)))*Settings!$B$6)+IF(AP11="Y",N(INDEX(Mob_Demob!$I$6:$I$14,MATCH(AM11,Mob_Demob!$A$6:$A$14,0)))*Settings!$B$19,0)+N(INDEX(Mob_Demob!$L$6:$L$14,MATCH(AM11,Mob_Demob!$A$6:$A$14,0)))*N(INDEX(Mob_Demob!$K$6:$K$14,MATCH(AM11,Mob_Demob!$A$6:$A$14,0)))*Settings!$B$6+N(INDEX(Mob_Demob!$M$6:$M$14,MATCH(AM11,Mob_Demob!$A$6:$A$14,0)))*N(INDEX(Mob_Demob!$N$6:$N$14,MATCH(AM11,Mob_Demob!$A$6:$A$14,0))),0)),"") -> 1800 | AR11: =IF(AQ11="","",ROUND(AQ11*Settings!$B$18,0)) -> 1800 | AS11: EW-CLR-HVY,EW-PUSH-100,EW-PUSH-200,EW-PUSH-300,EW-SPREAD,EW-RIP | AT11: Ziegler lists D8 as Medium, Carter as Large; Large used (Carter rename grouping). Rent: Wheeler only. Ex-fuel (C) = FEMA incl-fuel rate - Fuel_gal_hr_med x diesel back-out price (Settings B5).
A12: DZ-CRAWL-D9 | B12: Earthwork | C12: Crawler dozer | D12: Large (Cat D8-D11) | E12: D9 class (~452 hp) | F12: Net HP | G12: 452 | H12: hp | I12: Cat D9 | J12: 110205 | K12: 452 | L12: Blade Cat D9 SU 17.8 yd3 (U 21.7) | N12: diesel | O12: Operating Engineer - heavy equip. group (per WD) | P12: day/wk/4wk | V12: bare | AA12: D | AB12: 8255 | AC12: 360.3 | AD12: FEMA 2025 | AE12: 7.93 | AF12: 10.38 | AG12: 12.82 | AH12: Cat VisionLink Dec 2022, model D9-07 [CATFUEL22] | AI12: =IF(OR(AC12="",AF12="",Settings!$B$5=""),"",ROUND(AC12-AF12*Settings!$B$5,2)) -> 322.31 | AJ12: B | AK12: C | AL12: Owned: USACE standby = 0.5 x DEPR + FCCM, max 40 hr/wk [USACE-EP]; with only an all-in rate use Caltrans delay factor x rate, max 8 hr/day & 40 hr/wk [CALT-2627]: no class factor captured, use 0.10-0.22 band (inference). Rental: accrues by calendar period. FEMA: not eligible unless intermittent use [FEMA-PG]. | AM12: multi-axle-heavy | AN12: 110205 | AP12: Y | AQ12: =IFERROR(IF(AND(INDEX(Mob_Demob!$D$6:$D$14,MATCH(AM12,Mob_Demob!$A$6:$A$14,0))="",INDEX(Mob_Demob!$G$6:$G$14,MATCH(AM12,Mob_Demob!$A$6:$A$14,0))=""),"",ROUND(MAX(N(INDEX(Mob_Demob!$G$6:$G$14,MATCH(AM12,Mob_Demob!$A$6:$A$14,0))),N(INDEX(Mob_Demob!$D$6:$D$14,MATCH(AM12,Mob_Demob!$A$6:$A$14,0)))*Settings!$B$6)+IF(AP12="Y",N(INDEX(Mob_Demob!$I$6:$I$14,MATCH(AM12,Mob_Demob!$A$6:$A$14,0)))*Settings!$B$19,0)+N(INDEX(Mob_Demob!$L$6:$L$14,MATCH(AM12,Mob_Demob!$A$6:$A$14,0)))*N(INDEX(Mob_Demob!$K$6:$K$14,MATCH(AM12,Mob_Demob!$A$6:$A$14,0)))*Settings!$B$6+N(INDEX(Mob_Demob!$M$6:$M$14,MATCH(AM12,Mob_Demob!$A$6:$A$14,0)))*N(INDEX(Mob_Demob!$N$6:$N$14,MATCH(AM12,Mob_Demob!$A$6:$A$14,0))),0)),"") -> 1913 | AR12: =IF(AQ12="","",ROUND(AQ12*Settings!$B$18,0)) -> 1913 | AS12: EW-CLR-HVY,EW-PUSH-100,EW-PUSH-200,EW-PUSH-300,EW-RIP | AT12: Weight not in notes; transport set per mob notes ('D9+' multi-axle). Weight from cat.com (D9 110,205-111,362 lb) [CAT-DOZ-PG]. Ex-fuel (C) = FEMA incl-fuel rate - Fuel_gal_hr_med x diesel back-out price (Settings B5). | AU12: Needs rate (rental)
A13: DZ-CRAWL-D10 | B13: Earthwork | C13: Crawler dozer | D13: Large (Cat D8-D11) | E13: D10 class (~602 hp) | F13: Net HP | G13: 602 | H13: hp | I13: Cat D10 (D10T2) | J13: 154888 | K13: 602 | L13: Blade Cat D10 10SU 24.2 yd3 (10U 28.7) | N13: diesel | O13: Operating Engineer - heavy equip. group (per WD) | P13: day/wk/4wk | V13: bare | AA13: D | AC13: =ROUND(AC12+(AC14-AC12)*(K13-K12)/(K14-K12),2) -> 431.85 | AD13: FEMA 2025 (interpolated) | AE13: 11.46 | AF13: 15.09 | AG13: 18.73 | AH13: Cat VisionLink Dec 2022, model D10T2 [CATFUEL22] | AI13: =IF(OR(AC13="",AF13="",Settings!$B$5=""),"",ROUND(AC13-AF13*Settings!$B$5,2)) -> 376.62 | AJ13: C | AK13: C | AL13: Owned: USACE standby = 0.5 x DEPR + FCCM, max 40 hr/wk [USACE-EP]; with only an all-in rate use Caltrans delay factor x rate, max 8 hr/day & 40 hr/wk [CALT-2627]: no class factor captured, use 0.10-0.22 band (inference). Rental: accrues by calendar period. FEMA: not eligible unless intermittent use [FEMA-PG]. | AM13: multi-axle-heavy | AN13: 154888 | AP13: Y | AQ13: =IFERROR(IF(AND(INDEX(Mob_Demob!$D$6:$D$14,MATCH(AM13,Mob_Demob!$A$6:$A$14,0))="",INDEX(Mob_Demob!$G$6:$G$14,MATCH(AM13,Mob_Demob!$A$6:$A$14,0))=""),"",ROUND(MAX(N(INDEX(Mob_Demob!$G$6:$G$14,MATCH(AM13,Mob_Demob!$A$6:$A$14,0))),N(INDEX(Mob_Demob!$D$6:$D$14,MATCH(AM13,Mob_Demob!$A$6:$A$14,0)))*Settings!$B$6)+IF(AP13="Y",N(INDEX(Mob_Demob!$I$6:$I$14,MATCH(AM13,Mob_Demob!$A$6:$A$14,0)))*Settings!$B$19,0)+N(INDEX(Mob_Demob!$L$6:$L$14,MATCH(AM13,Mob_Demob!$A$6:$A$14,0)))*N(INDEX(Mob_Demob!$K$6:$K$14,MATCH(AM13,Mob_Demob!$A$6:$A$14,0)))*Settings!$B$6+N(INDEX(Mob_Demob!$M$6:$M$14,MATCH(AM13,Mob_Demob!$A$6:$A$14,0)))*N(INDEX(Mob_Demob!$N$6:$N$14,MATCH(AM13,Mob_Demob!$A$6:$A$14,0))),0)),"") -> 1913 | AR13: =IF(AQ13="","",ROUND(AQ13*Settings!$B$18,0)) -> 1913 | AS13: EW-PUSH-100,EW-PUSH-200,EW-PUSH-300,EW-RIP | AT13: Rental quoted on request only (Wheeler). Weight from cat.com (D9 110,205-111,362 lb) [CAT-DOZ-PG]. Owned_rate_hr_incl_fuel interpolated (C) between DZ-CRAWL-D9 and DZ-CRAWL-D11 by Net HP (FEMA 2025 endpoints). Ex-fuel (C) = FEMA incl-fuel rate - Fuel_gal_hr_med x diesel back-out price (Settings B5). | AU13: Needs rate (rental)
A14: DZ-CRAWL-D11 | B14: Earthwork | C14: Crawler dozer | D14: Large (Cat D8-D11) | E14: D11 class (~850 hp) | F14: Net HP | G14: 850 | H14: hp | I14: Cat D11 | J14: 235507 | K14: 850 | L14: Blade Cat D11 SU 35.6 yd3 (U 45; reclamation U 55; carrydozer 57) | N14: diesel | O14: Operating Engineer - heavy equip. group (per WD) | P14: day/wk/4wk | V14: bare | AA14: D | AB14: 8256 | AC14: 550.14 | AD14: FEMA 2025 | AE14: 15.45 | AF14: 20.52 | AG14: 25.59 | AH14: Cat VisionLink Dec 2022, model D11-07 [CATFUEL22] | AI14: =IF(OR(AC14="",AF14="",Settings!$B$5=""),"",ROUND(AC14-AF14*Settings!$B$5,2)) -> 475.04 | AJ14: B | AK14: C | AL14: Owned: USACE standby = 0.5 x DEPR + FCCM, max 40 hr/wk [USACE-EP]; with only an all-in rate use Caltrans delay factor x rate, max 8 hr/day & 40 hr/wk [CALT-2627]: no class factor captured, use 0.10-0.22 band (inference). Rental: accrues by calendar period. FEMA: not eligible unless intermittent use [FEMA-PG]. | AM14: multi-axle-heavy | AN14: 235507 | AP14: Y | AQ14: =IFERROR(IF(AND(INDEX(Mob_Demob!$D$6:$D$14,MATCH(AM14,Mob_Demob!$A$6:$A$14,0))="",INDEX(Mob_Demob!$G$6:$G$14,MATCH(AM14,Mob_Demob!$A$6:$A$14,0))=""),"",ROUND(MAX(N(INDEX(Mob_Demob!$G$6:$G$14,MATCH(AM14,Mob_Demob!$A$6:$A$14,0))),N(INDEX(Mob_Demob!$D$6:$D$14,MATCH(AM14,Mob_Demob!$A$6:$A$14,0)))*Settings!$B$6)+IF(AP14="Y",N(INDEX(Mob_Demob!$I$6:$I$14,MATCH(AM14,Mob_Demob!$A$6:$A$14,0)))*Settings!$B$19,0)+N(INDEX(Mob_Demob!$L$6:$L$14,MATCH(AM14,Mob_Demob!$A$6:$A$14,0)))*N(INDEX(Mob_Demob!$K$6:$K$14,MATCH(AM14,Mob_Demob!$A$6:$A$14,0)))*Settings!$B$6+N(INDEX(Mob_Demob!$M$6:$M$14,MATCH(AM14,Mob_Demob!$A$6:$A$14,0)))*N(INDEX(Mob_Demob!$N$6:$N$14,MATCH(AM14,Mob_Demob!$A$6:$A$14,0))),0)),"") -> 1913 | AR14: =IF(AQ14="","",ROUND(AQ14*Settings!$B$18,0)) -> 1913 | AS14: EW-PUSH-100,EW-PUSH-200,EW-PUSH-300,EW-RIP | AT14: Rental quoted on request only (Wheeler). Weight from cat.com (D9 110,205-111,362 lb) [CAT-DOZ-PG]. Ex-fuel (C) = FEMA incl-fuel rate - Fuel_gal_hr_med x diesel back-out price (Settings B5). | AU14: Needs rate (rental)
A15: DZ-WHEEL-814 | B15: Earthwork | C15: Wheel dozer | D15: Rubber-tired dozer | E15: Cat 814 class (~249 hp) | F15: Net HP | G15: 249 | H15: hp | I15: Cat 814 | K15: 249 | N15: diesel | O15: Operating Engineer - heavy equip. group (per WD) | P15: day/wk/4wk | V15: bare | AA15: D | AB15: 8260 | AC15: 101.21 | AD15: FEMA 2025 | AE15: =ROUND(K15*Settings!$B$11*Settings!$B$13,2) -> 4.24 | AF15: =ROUND(K15*Settings!$B$11*Settings!$B$14,2) -> 5.57 | AG15: =ROUND(K15*Settings!$B$11*Settings!$B$15,2) -> 7.26 | AH15: Derived (C): Net_HP x 0.0486 diesel gal/bhp-hr x load factor 0.35/0.46/0.60 [USACE-EP] | AI15: =IF(OR(AC15="",AF15="",Settings!$B$5=""),"",ROUND(AC15-AF15*Settings!$B$5,2)) -> 80.82 | AJ15: B | AK15: C | AL15: Owned: USACE standby = 0.5 x DEPR + FCCM, max 40 hr/wk [USACE-EP]; with only an all-in rate use Caltrans delay factor x rate, max 8 hr/day & 40 hr/wk [CALT-2627]: no class factor captured, use 0.10-0.22 band (inference). Rental: accrues by calendar period. FEMA: not eligible unless intermittent use [FEMA-PG]. | AM15: lowboy-permitted | AP15: Y | AQ15: =IFERROR(IF(AND(INDEX(Mob_Demob!$D$6:$D$14,MATCH(AM15,Mob_Demob!$A$6:$A$14,0))="",INDEX(Mob_Demob!$G$6:$G$14,MATCH(AM15,Mob_Demob!$A$6:$A$14,0))=""),"",ROUND(MAX(N(INDEX(Mob_Demob!$G$6:$G$14,MATCH(AM15,Mob_Demob!$A$6:$A$14,0))),N(INDEX(Mob_Demob!$D$6:$D$14,MATCH(AM15,Mob_Demob!$A$6:$A$14,0)))*Settings!$B$6)+IF(AP15="Y",N(INDEX(Mob_Demob!$I$6:$I$14,MATCH(AM15,Mob_Demob!$A$6:$A$14,0)))*Settings!$B$19,0)+N(INDEX(Mob_Demob!$L$6:$L$14,MATCH(AM15,Mob_Demob!$A$6:$A$14,0)))*N(INDEX(Mob_Demob!$K$6:$K$14,MATCH(AM15,Mob_Demob!$A$6:$A$14,0)))*Settings!$B$6+N(INDEX(Mob_Demob!$M$6:$M$14,MATCH(AM15,Mob_Demob!$A$6:$A$14,0)))*N(INDEX(Mob_Demob!$N$6:$N$14,MATCH(AM15,Mob_Demob!$A$6:$A$14,0))),0)),"") -> 1800 | AR15: =IF(AQ15="","",ROUND(AQ15*Settings!$B$18,0)) -> 1800 | AS15: EW-PUSH-100,EW-PUSH-200,EW-SPREAD | AT15: Weight not in notes; transport class assumed permitted (verify). Fuel gal/hr derived (C): Net_HP x USACE fuel factor x load factor (Settings B11-B15). Ex-fuel (C) = FEMA incl-fuel rate - Fuel_gal_hr_med x diesel back-out price (Settings B5). | AU15: Needs rate (rental)
A16: DZ-WHEEL-824 | B16: Earthwork | C16: Wheel dozer | D16: Rubber-tired dozer | E16: Cat 824 class (~405 hp) | F16: Net HP | G16: 405 | H16: hp | I16: Cat 824 | J16: 74966 | K16: 405 | N16: diesel | O16: Operating Engineer - heavy equip. group (per WD) | P16: day/wk/4wk | V16: bare | AA16: D | AB16: 8261 | AC16: 170.28 | AD16: FEMA 2025 | AE16: =ROUND(K16*Settings!$B$11*Settings!$B$13,2) -> 6.89 | AF16: =ROUND(K16*Settings!$B$11*Settings!$B$14,2) -> 9.05 | AG16: =ROUND(K16*Settings!$B$11*Settings!$B$15,2) -> 11.81 | AH16: Derived (C): Net_HP x 0.0486 diesel gal/bhp-hr x load factor 0.35/0.46/0.60 [USACE-EP] | AI16: =IF(OR(AC16="",AF16="",Settings!$B$5=""),"",ROUND(AC16-AF16*Settings!$B$5,2)) -> 137.16 | AJ16: B | AK16: C | AL16: Owned: USACE standby = 0.5 x DEPR + FCCM, max 40 hr/wk [USACE-EP]; with only an all-in rate use Caltrans delay factor x rate, max 8 hr/day & 40 hr/wk [CALT-2627]: no class factor captured, use 0.10-0.22 band (inference). Rental: accrues by calendar period. FEMA: not eligible unless intermittent use [FEMA-PG]. | AM16: lowboy-permitted | AN16: 74966 | AP16: Y | AQ16: =IFERROR(IF(AND(INDEX(Mob_Demob!$D$6:$D$14,MATCH(AM16,Mob_Demob!$A$6:$A$14,0))="",INDEX(Mob_Demob!$G$6:$G$14,MATCH(AM16,Mob_Demob!$A$6:$A$14,0))=""),"",ROUND(MAX(N(INDEX(Mob_Demob!$G$6:$G$14,MATCH(AM16,Mob_Demob!$A$6:$A$14,0))),N(INDEX(Mob_Demob!$D$6:$D$14,MATCH(AM16,Mob_Demob!$A$6:$A$14,0)))*Settings!$B$6)+IF(AP16="Y",N(INDEX(Mob_Demob!$I$6:$I$14,MATCH(AM16,Mob_Demob!$A$6:$A$14,0)))*Settings!$B$19,0)+N(INDEX(Mob_Demob!$L$6:$L$14,MATCH(AM16,Mob_Demob!$A$6:$A$14,0)))*N(INDEX(Mob_Demob!$K$6:$K$14,MATCH(AM16,Mob_Demob!$A$6:$A$14,0)))*Settings!$B$6+N(INDEX(Mob_Demob!$M$6:$M$14,MATCH(AM16,Mob_Demob!$A$6:$A$14,0)))*N(INDEX(Mob_Demob!$N$6:$N$14,MATCH(AM16,Mob_Demob!$A$6:$A$14,0))),0)),"") -> 1800 | AR16: =IF(AQ16="","",ROUND(AQ16*Settings!$B$18,0)) -> 1800 | AS16: EW-PUSH-100,EW-PUSH-200,EW-SPREAD | AT16: Fuel gal/hr derived (C): Net_HP x USACE fuel factor x load factor (Settings B11-B15). Ex-fuel (C) = FEMA incl-fuel rate - Fuel_gal_hr_med x diesel back-out price (Settings B5). | AU16: Needs rate (rental)
A17: DZ-WHEEL-834 | B17: Earthwork | C17: Wheel dozer | D17: Rubber-tired dozer | E17: Cat 834 class (~496 hp) | F17: Net HP | G17: 496 | H17: hp | I17: Cat 834 | J17: 105271 | K17: 496 | N17: diesel | O17: Operating Engineer - heavy equip. group (per WD) | P17: day/wk/4wk | V17: bare | AA17: D | AB17: 8262 | AC17: 308.97 | AD17: FEMA 2025 | AE17: =ROUND(K17*Settings!$B$11*Settings!$B$13,2) -> 8.44 | AF17: =ROUND(K17*Settings!$B$11*Settings!$B$14,2) -> 11.09 | AG17: =ROUND(K17*Settings!$B$11*Settings!$B$15,2) -> 14.46 | AH17: Derived (C): Net_HP x 0.0486 diesel gal/bhp-hr x load factor 0.35/0.46/0.60 [USACE-EP] | AI17: =IF(OR(AC17="",AF17="",Settings!$B$5=""),"",ROUND(AC17-AF17*Settings!$B$5,2)) -> 268.38 | AJ17: B | AK17: C | AL17: Owned: USACE standby = 0.5 x DEPR + FCCM, max 40 hr/wk [USACE-EP]; with only an all-in rate use Caltrans delay factor x rate, max 8 hr/day & 40 hr/wk [CALT-2627]: no class factor captured, use 0.10-0.22 band (inference). Rental: accrues by calendar period. FEMA: not eligible unless intermittent use [FEMA-PG]. | AM17: multi-axle-heavy | AN17: 105271 | AP17: Y | AQ17: =IFERROR(IF(AND(INDEX(Mob_Demob!$D$6:$D$14,MATCH(AM17,Mob_Demob!$A$6:$A$14,0))="",INDEX(Mob_Demob!$G$6:$G$14,MATCH(AM17,Mob_Demob!$A$6:$A$14,0))=""),"",ROUND(MAX(N(INDEX(Mob_Demob!$G$6:$G$14,MATCH(AM17,Mob_Demob!$A$6:$A$14,0))),N(INDEX(Mob_Demob!$D$6:$D$14,MATCH(AM17,Mob_Demob!$A$6:$A$14,0)))*Settings!$B$6)+IF(AP17="Y",N(INDEX(Mob_Demob!$I$6:$I$14,MATCH(AM17,Mob_Demob!$A$6:$A$14,0)))*Settings!$B$19,0)+N(INDEX(Mob_Demob!$L$6:$L$14,MATCH(AM17,Mob_Demob!$A$6:$A$14,0)))*N(INDEX(Mob_Demob!$K$6:$K$14,MATCH(AM17,Mob_Demob!$A$6:$A$14,0)))*Settings!$B$6+N(INDEX(Mob_Demob!$M$6:$M$14,MATCH(AM17,Mob_Demob!$A$6:$A$14,0)))*N(INDEX(Mob_Demob!$N$6:$N$14,MATCH(AM17,Mob_Demob!$A$6:$A$14,0))),0)),"") -> 1913 | AR17: =IF(AQ17="","",ROUND(AQ17*Settings!$B$18,0)) -> 1913 | AS17: EW-PUSH-100,EW-PUSH-200,EW-SPREAD | AT17: Fuel gal/hr derived (C): Net_HP x USACE fuel factor x load factor (Settings B11-B15). Ex-fuel (C) = FEMA incl-fuel rate - Fuel_gal_hr_med x diesel back-out price (Settings B5). | AU17: Needs rate (rental)
A18: DZ-WHEEL-844 | B18: Earthwork | C18: Wheel dozer | D18: Rubber-tired dozer | E18: Cat 844 class (~732 hp) | F18: Net HP | G18: 732 | H18: hp | I18: Cat 844 | K18: 732 | N18: diesel | O18: Operating Engineer - heavy equip. group (per WD) | P18: day/wk/4wk | V18: bare | AA18: D | AB18: 8263 | AC18: 402.76 | AD18: FEMA 2025 | AE18: =ROUND(K18*Settings!$B$11*Settings!$B$13,2) -> 12.45 | AF18: =ROUND(K18*Settings!$B$11*Settings!$B$14,2) -> 16.36 | AG18: =ROUND(K18*Settings!$B$11*Settings!$B$15,2) -> 21.35 | AH18: Derived (C): Net_HP x 0.0486 diesel gal/bhp-hr x load factor 0.35/0.46/0.60 [USACE-EP] | AI18: =IF(OR(AC18="",AF18="",Settings!$B$5=""),"",ROUND(AC18-AF18*Settings!$B$5,2)) -> 342.88 | AJ18: B | AK18: C | AL18: Owned: USACE standby = 0.5 x DEPR + FCCM, max 40 hr/wk [USACE-EP]; with only an all-in rate use Caltrans delay factor x rate, max 8 hr/day & 40 hr/wk [CALT-2627]: no class factor captured, use 0.10-0.22 band (inference). Rental: accrues by calendar period. FEMA: not eligible unless intermittent use [FEMA-PG]. | AM18: multi-axle-heavy | AP18: Y | AQ18: =IFERROR(IF(AND(INDEX(Mob_Demob!$D$6:$D$14,MATCH(AM18,Mob_Demob!$A$6:$A$14,0))="",INDEX(Mob_Demob!$G$6:$G$14,MATCH(AM18,Mob_Demob!$A$6:$A$14,0))=""),"",ROUND(MAX(N(INDEX(Mob_Demob!$G$6:$G$14,MATCH(AM18,Mob_Demob!$A$6:$A$14,0))),N(INDEX(Mob_Demob!$D$6:$D$14,MATCH(AM18,Mob_Demob!$A$6:$A$14,0)))*Settings!$B$6)+IF(AP18="Y",N(INDEX(Mob_Demob!$I$6:$I$14,MATCH(AM18,Mob_Demob!$A$6:$A$14,0)))*Settings!$B$19,0)+N(INDEX(Mob_Demob!$L$6:$L$14,MATCH(AM18,Mob_Demob!$A$6:$A$14,0)))*N(INDEX(Mob_Demob!$K$6:$K$14,MATCH(AM18,Mob_Demob!$A$6:$A$14,0)))*Settings!$B$6+N(INDEX(Mob_Demob!$M$6:$M$14,MATCH(AM18,Mob_Demob!$A$6:$A$14,0)))*N(INDEX(Mob_Demob!$N$6:$N$14,MATCH(AM18,Mob_Demob!$A$6:$A$14,0))),0)),"") -> 1913 | AR18: =IF(AQ18="","",ROUND(AQ18*Settings!$B$18,0)) -> 1913 | AS18: EW-PUSH-100,EW-PUSH-200,EW-SPREAD | AT18: Weight not in notes; transport class assumed permitted (verify). Transport set to multi-axle-heavy for consistency with the lighter 834 (105,271 lb); 844 weight not in notes. Fuel gal/hr derived (C): Net_HP x USACE fuel factor x load factor (Settings B11-B15). Ex-fuel (C) = FEMA incl-fuel rate - Fuel_gal_hr_med x diesel back-out price (Settings B5). | AU18: Needs rate (rental)
A19: DZ-WHEEL-854 | B19: Earthwork | C19: Wheel dozer | D19: Rubber-tired dozer | E19: Cat 854 class (~814 hp) | F19: Net HP | G19: 814 | H19: hp | I19: Cat 854 | J19: 224647 | K19: 814 | N19: diesel | O19: Operating Engineer - heavy equip. group (per WD) | P19: day/wk/4wk | V19: bare | AA19: D | AE19: =ROUND(K19*Settings!$B$11*Settings!$B$13,2) -> 13.85 | AF19: =ROUND(K19*Settings!$B$11*Settings!$B$14,2) -> 18.2 | AG19: =ROUND(K19*Settings!$B$11*Settings!$B$15,2) -> 23.74 | AH19: Derived (C): Net_HP x 0.0486 diesel gal/bhp-hr x load factor 0.35/0.46/0.60 [USACE-EP] | AJ19: D | AK19: D | AL19: Owned: USACE standby = 0.5 x DEPR + FCCM, max 40 hr/wk [USACE-EP]; with only an all-in rate use Caltrans delay factor x rate, max 8 hr/day & 40 hr/wk [CALT-2627]: no class factor captured, use 0.10-0.22 band (inference). Rental: accrues by calendar period. FEMA: not eligible unless intermittent use [FEMA-PG]. | AM19: multi-axle-heavy | AN19: 224647 | AP19: Y | AQ19: =IFERROR(IF(AND(INDEX(Mob_Demob!$D$6:$D$14,MATCH(AM19,Mob_Demob!$A$6:$A$14,0))="",INDEX(Mob_Demob!$G$6:$G$14,MATCH(AM19,Mob_Demob!$A$6:$A$14,0))=""),"",ROUND(MAX(N(INDEX(Mob_Demob!$G$6:$G$14,MATCH(AM19,Mob_Demob!$A$6:$A$14,0))),N(INDEX(Mob_Demob!$D$6:$D$14,MATCH(AM19,Mob_Demob!$A$6:$A$14,0)))*Settings!$B$6)+IF(AP19="Y",N(INDEX(Mob_Demob!$I$6:$I$14,MATCH(AM19,Mob_Demob!$A$6:$A$14,0)))*Settings!$B$19,0)+N(INDEX(Mob_Demob!$L$6:$L$14,MATCH(AM19,Mob_Demob!$A$6:$A$14,0)))*N(INDEX(Mob_Demob!$K$6:$K$14,MATCH(AM19,Mob_Demob!$A$6:$A$14,0)))*Settings!$B$6+N(INDEX(Mob_Demob!$M$6:$M$14,MATCH(AM19,Mob_Demob!$A$6:$A$14,0)))*N(INDEX(Mob_Demob!$N$6:$N$14,MATCH(AM19,Mob_Demob!$A$6:$A$14,0))),0)),"") -> 1913 | AR19: =IF(AQ19="","",ROUND(AQ19*Settings!$B$18,0)) -> 1913 | AS19: EW-PUSH-100,EW-PUSH-200,EW-SPREAD | AT19: Fuel gal/hr derived (C): Net_HP x USACE fuel factor x load factor (Settings B11-B15). | AU19: Needs rate; Needs rate (rental); Needs rate (owned)
A20: EX-MINI-1T | B20: Earthwork | C20: Hydraulic excavator | D20: Mini/compact 1-2 t | E20: 1-2 t (<=5,000 lb) | F20: Operating weight | G20: 3913 | H20: lb | I20: Cat 300.9D (2,061 lb, 13 hp), 301.5 (3,913 lb, 21 hp), 301.7 CR, 301.8, 302 CR; Kubota K008; Bobcat E10/E20 | J20: 3913 | K20: 21 | N20: diesel | O20: Operating Engineer - light/compact group (per WD) | P20: day/wk/4wk | Q20: 237 | R20: 748 | S20: 2200 | T20: 1665 | U20: 2913 | V20: bare | Y20: W25;B25;R25;N25;A26;DOZR-EX | Z20: 2025-2026 | AA20: A | AE20: =ROUND(K20*Settings!$B$11*Settings!$B$13,2) -> 0.36 | AF20: =ROUND(K20*Settings!$B$11*Settings!$B$14,2) -> 0.47 | AG20: =ROUND(K20*Settings!$B$11*Settings!$B$15,2) -> 0.61 | AH20: Derived (C): Net_HP x 0.0486 diesel gal/bhp-hr x load factor 0.35/0.46/0.60 [USACE-EP] | AJ20: D | AK20: D | AL20: Owned: USACE standby = 0.5 x DEPR + FCCM, max 40 hr/wk [USACE-EP]; with only an all-in rate use Caltrans delay factor x rate, max 8 hr/day & 40 hr/wk [CALT-2627]: HCECL factor 0.17 (book) / 0.16 (Sep 2026 interim). Rental: accrues by calendar period (no idle discount). FEMA: not eligible unless intermittent use [FEMA-PG]. | AM20: tilt-trailer | AN20: 3913 | AP20: N | AQ20: =IFERROR(IF(AND(INDEX(Mob_Demob!$D$6:$D$14,MATCH(AM20,Mob_Demob!$A$6:$A$14,0))="",INDEX(Mob_Demob!$G$6:$G$14,MATCH(AM20,Mob_Demob!$A$6:$A$14,0))=""),"",ROUND(MAX(N(INDEX(Mob_Demob!$G$6:$G$14,MATCH(AM20,Mob_Demob!$A$6:$A$14,0))),N(INDEX(Mob_Demob!$D$6:$D$14,MATCH(AM20,Mob_Demob!$A$6:$A$14,0)))*Settings!$B$6)+IF(AP20="Y",N(INDEX(Mob_Demob!$I$6:$I$14,MATCH(AM20,Mob_Demob!$A$6:$A$14,0)))*Settings!$B$19,0)+N(INDEX(Mob_Demob!$L$6:$L$14,MATCH(AM20,Mob_Demob!$A$6:$A$14,0)))*N(INDEX(Mob_Demob!$K$6:$K$14,MATCH(AM20,Mob_Demob!$A$6:$A$14,0)))*Settings!$B$6+N(INDEX(Mob_Demob!$M$6:$M$14,MATCH(AM20,Mob_Demob!$A$6:$A$14,0)))*N(INDEX(Mob_Demob!$N$6:$N$14,MATCH(AM20,Mob_Demob!$A$6:$A$14,0))),0)),"") -> 500 | AR20: =IF(AQ20="","",ROUND(AQ20*Settings!$B$18,0)) -> 500 | AS20: EW-TRENCH-5,EW-STRUCT,EW-BACKFILL | AT20: Representative model 301.5 (3,913 lb, 21 hp) used for weight/HP. Tail swing (zero/reduced/conventional) does not change the rate class. No FEMA code below 45 hp; not extrapolated. Tail swing: zero / minimal (<10% overhang) / conventional variants exist [BOBCAT-EX]; not priced separately by the rental sources. Max dig depth: Deere 17 P 7'2" [DEERE-RENT; CAT-EXC-PG]. Rent: Median of 6 sources (W 346/1004/2913; B 248/745/2235; R 200/750/2200; N 190/665/1665; A 300/900/2200; D 225/675/1775). Fuel gal/hr derived (C): Net_HP x USACE fuel factor x load factor (Settings B11-B15). | AU20: Needs rate (owned)
A21: EX-MINI-3T | B21: Earthwork | C21: Hydraulic excavator | D21: Mini/compact 3-4 t | E21: 3-4 t (5,000-10,000 lb) | F21: Operating weight | G21: 9867 | H21: lb | I21: Cat 302.7 CR, 303 CR, 303.5 CR, 304 (9,867 lb, 45 hp); Kubota KX033/KX040; Bobcat E26/E35/E42 | J21: 9867 | K21: 45 | L21: GP bucket 0.15 yd3 (typ; Deere 35G spec-basis bucket 0.11 m3 (0.15 yd3); single value, not a range) | N21: diesel | O21: Operating Engineer - light/compact group (per WD) | P21: day/wk/4wk | Q21: 325 | R21: 1013 | S21: 2788 | T21: 2250 | U21: 4438 | V21: bare | Y21: W25;C25;B25;R25;N25;A26;DOZR-EX | Z21: 2025-2026 | AA21: A | AE21: =ROUND(K21*Settings!$B$11*Settings!$B$13,2) -> 0.77 | AF21: =ROUND(K21*Settings!$B$11*Settings!$B$14,2) -> 1.01 | AG21: =ROUND(K21*Settings!$B$11*Settings!$B$15,2) -> 1.31 | AH21: Derived (C): Net_HP x 0.0486 diesel gal/bhp-hr x load factor 0.35/0.46/0.60 [USACE-EP] | AJ21: D | AK21: D | AL21: Owned: USACE standby = 0.5 x DEPR + FCCM, max 40 hr/wk [USACE-EP]; with only an all-in rate use Caltrans delay factor x rate, max 8 hr/day & 40 hr/wk [CALT-2627]: HCECL factor 0.17 (book) / 0.16 (Sep 2026 interim). Rental: accrues by calendar period (no idle discount). FEMA: not eligible unless intermittent use [FEMA-PG]. | AM21: tilt-trailer | AN21: 9867 | AP21: N | AQ21: =IFERROR(IF(AND(INDEX(Mob_Demob!$D$6:$D$14,MATCH(AM21,Mob_Demob!$A$6:$A$14,0))="",INDEX(Mob_Demob!$G$6:$G$14,MATCH(AM21,Mob_Demob!$A$6:$A$14,0))=""),"",ROUND(MAX(N(INDEX(Mob_Demob!$G$6:$G$14,MATCH(AM21,Mob_Demob!$A$6:$A$14,0))),N(INDEX(Mob_Demob!$D$6:$D$14,MATCH(AM21,Mob_Demob!$A$6:$A$14,0)))*Settings!$B$6)+IF(AP21="Y",N(INDEX(Mob_Demob!$I$6:$I$14,MATCH(AM21,Mob_Demob!$A$6:$A$14,0)))*Settings!$B$19,0)+N(INDEX(Mob_Demob!$L$6:$L$14,MATCH(AM21,Mob_Demob!$A$6:$A$14,0)))*N(INDEX(Mob_Demob!$K$6:$K$14,MATCH(AM21,Mob_Demob!$A$6:$A$14,0)))*Settings!$B$6+N(INDEX(Mob_Demob!$M$6:$M$14,MATCH(AM21,Mob_Demob!$A$6:$A$14,0)))*N(INDEX(Mob_Demob!$N$6:$N$14,MATCH(AM21,Mob_Demob!$A$6:$A$14,0))),0)),"") -> 500 | AR21: =IF(AQ21="","",ROUND(AQ21*Settings!$B$18,0)) -> 500 | AS21: EW-TRENCH-5,EW-STRUCT,EW-BACKFILL,UT-PIPE-WATER | AT21: Representative model Cat 304 (9,867 lb, 45 hp). FEMA 8280 (305 CR) caps at 45 hp but is mapped to the 5-6 t class; not reused here. Rounded half-up (Excel rule) in revision; may differ by 1 from the notes table, which used banker's rounding. Tail swing: zero / minimal (<10% overhang) / conventional variants exist [BOBCAT-EX]; not priced separately by the rental sources. Max dig depth: Cat 303.5 CR 110.6-122.4 in; Deere 35G 10'0"; Kubota KX040-4 11.23 ft [DEERE-RENT; CAT-EXC-PG]. Rent: Median of 7 sources (W 528/1530/4438; C 375/912/2250; B 310/930/2790; R 307/1215/3190; N 290/1012/2788; A 375/1075/2625; D 325/975/2550). Fuel gal/hr derived (C): Net_HP x USACE fuel factor x load factor (Settings B11-B15). | AU21: Needs rate (owned)
A22: EX-MINI-5T | B22: Earthwork | C22: Hydraulic excavator | D22: Mini/compact 5-6 t | E22: 5-6 t (10,000-14,000 lb) | F22: Operating weight | G22: 12688 | H22: lb | I22: Cat 305 CR (12,688 lb, 45 hp, 12 ft dig), 306 CR; Kubota KX057; Case CX55; Bobcat E50/E60 | J22: 12688 | K22: 45 | N22: diesel | O22: Operating Engineer - light/compact group (per WD) | P22: day/wk/4wk | Q22: 443 | R22: 1319 | S22: 3228 | T22: 2950 | U22: 6226 | V22: bare | Y22: W25;C25;B25;R25;N25;A26 | Z22: 2025-2026 | AA22: A | AB22: 8280 | AC22: 57.14 | AD22: FEMA 2025 | AE22: 1.15 | AF22: 1.55 | AG22: 1.94 | AH22: Cat VisionLink Dec 2022, model 305-07 CR [CATFUEL22] | AI22: =IF(OR(AC22="",AF22="",Settings!$B$5=""),"",ROUND(AC22-AF22*Settings!$B$5,2)) -> 51.47 | AJ22: B | AK22: C | AL22: Owned: USACE standby = 0.5 x DEPR + FCCM, max 40 hr/wk [USACE-EP]; with only an all-in rate use Caltrans delay factor x rate, max 8 hr/day & 40 hr/wk [CALT-2627]: HCECL factor 0.17 (book) / 0.16 (Sep 2026 interim). Rental: accrues by calendar period (no idle discount). FEMA: not eligible unless intermittent use [FEMA-PG]. | AM22: tilt-trailer | AN22: 12688 | AP22: N | AQ22: =IFERROR(IF(AND(INDEX(Mob_Demob!$D$6:$D$14,MATCH(AM22,Mob_Demob!$A$6:$A$14,0))="",INDEX(Mob_Demob!$G$6:$G$14,MATCH(AM22,Mob_Demob!$A$6:$A$14,0))=""),"",ROUND(MAX(N(INDEX(Mob_Demob!$G$6:$G$14,MATCH(AM22,Mob_Demob!$A$6:$A$14,0))),N(INDEX(Mob_Demob!$D$6:$D$14,MATCH(AM22,Mob_Demob!$A$6:$A$14,0)))*Settings!$B$6)+IF(AP22="Y",N(INDEX(Mob_Demob!$I$6:$I$14,MATCH(AM22,Mob_Demob!$A$6:$A$14,0)))*Settings!$B$19,0)+N(INDEX(Mob_Demob!$L$6:$L$14,MATCH(AM22,Mob_Demob!$A$6:$A$14,0)))*N(INDEX(Mob_Demob!$K$6:$K$14,MATCH(AM22,Mob_Demob!$A$6:$A$14,0)))*Settings!$B$6+N(INDEX(Mob_Demob!$M$6:$M$14,MATCH(AM22,Mob_Demob!$A$6:$A$14,0)))*N(INDEX(Mob_Demob!$N$6:$N$14,MATCH(AM22,Mob_Demob!$A$6:$A$14,0))),0)),"") -> 500 | AR22: =IF(AQ22="","",ROUND(AQ22*Settings!$B$18,0)) -> 500 | AS22: EW-TRENCH-5,EW-TRENCH-10,EW-STRUCT,EW-BACKFILL,UT-PIPE-WATER | AT22: Rounded half-up (Excel rule) in revision; may differ by 1 from the notes table, which used banker's rounding. Tail swing: zero / minimal (<10% overhang) / conventional variants exist [BOBCAT-EX]; not priced separately by the rental sources. Max dig depth: Cat 305 CR 134.6-144.5 in; Deere 50 P 11'7"; Bobcat E50 11.4 ft [DEERE-RENT; CAT-EXC-PG]. Rent: Median of 6 sources (W 740/2147/6226; C 488/1212/3000; B 370/1110/3330; R 410/1672/3798; N 335/1175/2950; A 475/1425/3125). Ex-fuel (C) = FEMA incl-fuel rate - Fuel_gal_hr_med x diesel back-out price (Settings B5).
A23: EX-MIDI-8T | B23: Earthwork | C23: Hydraulic excavator | D23: Midi 7-8 t (nominal 8 t) | E23: 7-8 t nominal (~15,400-19,800 lb) | F23: Operating weight | G23: 18493 | H23: lb | I23: Cat 307.5 (17,905 lb), 308 CR (18,493 lb, 69.5 hp); Komatsu PC88MR (19,225 lb); Kubota KX080; Bobcat E88 | J23: 18493 | K23: 69.5 | L23: GP bucket 0.26 yd3 (typ; Komatsu PC88MR-11 single listed bucket 0.26 yd3 (aggregator)) | N23: diesel | O23: Operating Engineer - light/compact group (per WD) | P23: day/wk/4wk | Q23: 600 | R23: 1798 | S23: 4498 | T23: 3780 | U23: 6924 | V23: bare | Y23: W25;C25;B25;R25 | Z23: 2025 | AA23: A | AC23: =ROUND(AC22+(AC25-AC22)*(K23-K22)/(K25-K22),2) -> 77.76 | AD23: FEMA 2025 (interpolated) | AE23: 0.68 | AF23: 0.95 | AG23: 1.22 | AH23: Cat VisionLink Dec 2022, model 308-07 CR [CATFUEL22] | AI23: =IF(OR(AC23="",AF23="",Settings!$B$5=""),"",ROUND(AC23-AF23*Settings!$B$5,2)) -> 74.28 | AJ23: C | AK23: C | AL23: Owned: USACE standby = 0.5 x DEPR + FCCM, max 40 hr/wk [USACE-EP]; with only an all-in rate use Caltrans delay factor x rate, max 8 hr/day & 40 hr/wk [CALT-2627]: HCECL factor 0.17 (book) / 0.16 (Sep 2026 interim). Rental: accrues by calendar period (no idle discount). FEMA: not eligible unless intermittent use [FEMA-PG]. | AM23: tilt-trailer | AN23: 18493 | AP23: N | AQ23: =IFERROR(IF(AND(INDEX(Mob_Demob!$D$6:$D$14,MATCH(AM23,Mob_Demob!$A$6:$A$14,0))="",INDEX(Mob_Demob!$G$6:$G$14,MATCH(AM23,Mob_Demob!$A$6:$A$14,0))=""),"",ROUND(MAX(N(INDEX(Mob_Demob!$G$6:$G$14,MATCH(AM23,Mob_Demob!$A$6:$A$14,0))),N(INDEX(Mob_Demob!$D$6:$D$14,MATCH(AM23,Mob_Demob!$A$6:$A$14,0)))*Settings!$B$6)+IF(AP23="Y",N(INDEX(Mob_Demob!$I$6:$I$14,MATCH(AM23,Mob_Demob!$A$6:$A$14,0)))*Settings!$B$19,0)+N(INDEX(Mob_Demob!$L$6:$L$14,MATCH(AM23,Mob_Demob!$A$6:$A$14,0)))*N(INDEX(Mob_Demob!$K$6:$K$14,MATCH(AM23,Mob_Demob!$A$6:$A$14,0)))*Settings!$B$6+N(INDEX(Mob_Demob!$M$6:$M$14,MATCH(AM23,Mob_Demob!$A$6:$A$14,0)))*N(INDEX(Mob_Demob!$N$6:$N$14,MATCH(AM23,Mob_Demob!$A$6:$A$14,0))),0)),"") -> 500 | AR23: =IF(AQ23="","",ROUND(AQ23*Settings!$B$18,0)) -> 500 | AS23: EW-CUTLOAD,EW-MASS,EW-TRENCH-5,EW-TRENCH-10,EW-STRUCT,EW-BACKFILL,UT-PIPE-STORM,DM-PAVE-CONC | AT23: Cat 308-07 CR fuel (0.95 med) is below the 305 CR (1.55) in the source; reproduced as published. Split in revision from the notes' 8-10 t class (Bobcat 7-8 / 9-10 t classes). Tail swing: zero / minimal (<10% overhang) / conventional variants exist in compact classes [BOBCAT-EX]; rental sources do not price them separately. Max dig depth: Deere 85 P 14'10"; PC88MR 15 ft [DEERE-RENT; CAT-EXC-PG]. Rent: Median of 4 sources after split (W 308 823/2388/6924; C PC88MR 650/1600/4000; B KX080/ET90 420/1260/3780; R E88 550/1995/4995). 8.4-8.8 t models assigned to the 7-8 t (nominal 8 t) class. Owned_rate_hr_incl_fuel interpolated (C) between EX-MINI-5T and EX-CRAWL-13T by Net HP (FEMA 2025 endpoints). Ex-fuel (C) = FEMA incl-fuel rate - Fuel_gal_hr_med x diesel back-out price (Settings B5). | AU23: Fuel value looks low vs smaller class
A24: EX-MIDI-10T | B24: Earthwork | C24: Hydraulic excavator | D24: Midi 9-10 t | E24: 9-10 t (~19,800-23,000 lb) | F24: Operating weight | G24: 23002 | H24: lb | I24: Cat 309 CR (21,091 lb), 310 (23,002 lb, 69.5 hp, 205.2 in dig) | J24: 23002 | K24: 69.5 | N24: diesel | O24: Operating Engineer - light/compact group (per WD) | P24: day/wk/4wk | Q24: 717 | R24: 2182 | S24: 5843 | T24: 4250 | U24: 7437 | V24: bare | Y24: W25;A26 | Z24: 2025-2026 | AA24: A | AC24: =ROUND(AC22+(AC25-AC22)*(K24-K22)/(K25-K22),2) -> 77.76 | AD24: FEMA 2025 (interpolated) | AE24: =ROUND(K24*Settings!$B$11*Settings!$B$13,2) -> 1.18 | AF24: =ROUND(K24*Settings!$B$11*Settings!$B$14,2) -> 1.55 | AG24: =ROUND(K24*Settings!$B$11*Settings!$B$15,2) -> 2.03 | AH24: Derived (C): Net_HP x 0.0486 diesel gal/bhp-hr x load factor 0.35/0.46/0.60 [USACE-EP] | AI24: =IF(OR(AC24="",AF24="",Settings!$B$5=""),"",ROUND(AC24-AF24*Settings!$B$5,2)) -> 72.09 | AJ24: C | AK24: C | AL24: Owned: USACE standby = 0.5 x DEPR + FCCM, max 40 hr/wk [USACE-EP]; with only an all-in rate use Caltrans delay factor x rate, max 8 hr/day & 40 hr/wk [CALT-2627]: HCECL factor 0.17 (book) / 0.16 (Sep 2026 interim). Rental: accrues by calendar period (no idle discount). FEMA: not eligible unless intermittent use [FEMA-PG]. | AM24: lowboy-legal | AN24: 23002 | AP24: N | AQ24: =IFERROR(IF(AND(INDEX(Mob_Demob!$D$6:$D$14,MATCH(AM24,Mob_Demob!$A$6:$A$14,0))="",INDEX(Mob_Demob!$G$6:$G$14,MATCH(AM24,Mob_Demob!$A$6:$A$14,0))=""),"",ROUND(MAX(N(INDEX(Mob_Demob!$G$6:$G$14,MATCH(AM24,Mob_Demob!$A$6:$A$14,0))),N(INDEX(Mob_Demob!$D$6:$D$14,MATCH(AM24,Mob_Demob!$A$6:$A$14,0)))*Settings!$B$6)+IF(AP24="Y",N(INDEX(Mob_Demob!$I$6:$I$14,MATCH(AM24,Mob_Demob!$A$6:$A$14,0)))*Settings!$B$19,0)+N(INDEX(Mob_Demob!$L$6:$L$14,MATCH(AM24,Mob_Demob!$A$6:$A$14,0)))*N(INDEX(Mob_Demob!$K$6:$K$14,MATCH(AM24,Mob_Demob!$A$6:$A$14,0)))*Settings!$B$6+N(INDEX(Mob_Demob!$M$6:$M$14,MATCH(AM24,Mob_Demob!$A$6:$A$14,0)))*N(INDEX(Mob_Demob!$N$6:$N$14,MATCH(AM24,Mob_Demob!$A$6:$A$14,0))),0)),"") -> 550 | AR24: =IF(AQ24="","",ROUND(AQ24*Settings!$B$18,0)) -> 550 | AS24: EW-CUTLOAD,EW-MASS,EW-TRENCH-5,EW-TRENCH-10,EW-STRUCT,EW-BACKFILL,UT-PIPE-STORM | AT24: Split from the 8-10 t class in revision. Rent: Mean of 2 sources after split (W 309/310 avg 884.5/2564/7436.5; A 18-25K lb 550/1800/4250). Ahearn 18-25K lb class straddles both midi rows; assigned here. Half-up rounding. Owned_rate_hr_incl_fuel interpolated (C) between EX-MINI-5T and EX-CRAWL-13T by Net HP (FEMA 2025 endpoints). Fuel gal/hr derived (C): Net_HP x USACE fuel factor x load factor (Settings B11-B15). Ex-fuel (C) = FEMA incl-fuel rate - Fuel_gal_hr_med x diesel back-out price (Settings B5).
A25: EX-CRAWL-13T | B25: Earthwork | C25: Hydraulic excavator | D25: Small 13-15 t | E25: 13-15 t (~30,000-34,000 lb) | F25: Operating weight | G25: 30400 | H25: lb | I25: Cat 313 GC (30,400 lb, 73 hp), 313 (108 hp), 315 GC (34,000 lb); Komatsu PC138USLC; Develon DX140 | J25: 30400 | K25: 90 | L25: GP bucket 0.75 yd3 (typ; midpoint of typical GP 0.5-1.0 yd3 (Deere 135 P HD 0.47-0.99)) | N25: diesel | O25: Operating Engineer - heavy equip. group (per WD) | P25: day/wk/4wk | Q25: 700 | R25: 2100 | S25: 5250 | T25: 4635 | U25: 8703 | V25: bare | Y25: W25;C25;B25;R25;A26 | Z25: 2025-2026 | AA25: A | AB25: 8281 | AC25: 95.01 | AD25: FEMA 2025 | AE25: 1.49 | AF25: 1.9 | AG25: 2.31 | AH25: Cat VisionLink Dec 2022, model 313-07 GC [CATFUEL22] | AI25: =IF(OR(AC25="",AF25="",Settings!$B$5=""),"",ROUND(AC25-AF25*Settings!$B$5,2)) -> 88.06 | AJ25: B | AK25: C | AL25: Owned: USACE standby = 0.5 x DEPR + FCCM, max 40 hr/wk [USACE-EP]; with only an all-in rate use Caltrans delay factor x rate, max 8 hr/day & 40 hr/wk [CALT-2627]: HCECL factor 0.17 (book) / 0.16 (Sep 2026 interim). Rental: accrues by calendar period (no idle discount). FEMA: not eligible unless intermittent use [FEMA-PG]. | AM25: lowboy-legal | AN25: 30400 | AP25: N | AQ25: =IFERROR(IF(AND(INDEX(Mob_Demob!$D$6:$D$14,MATCH(AM25,Mob_Demob!$A$6:$A$14,0))="",INDEX(Mob_Demob!$G$6:$G$14,MATCH(AM25,Mob_Demob!$A$6:$A$14,0))=""),"",ROUND(MAX(N(INDEX(Mob_Demob!$G$6:$G$14,MATCH(AM25,Mob_Demob!$A$6:$A$14,0))),N(INDEX(Mob_Demob!$D$6:$D$14,MATCH(AM25,Mob_Demob!$A$6:$A$14,0)))*Settings!$B$6)+IF(AP25="Y",N(INDEX(Mob_Demob!$I$6:$I$14,MATCH(AM25,Mob_Demob!$A$6:$A$14,0)))*Settings!$B$19,0)+N(INDEX(Mob_Demob!$L$6:$L$14,MATCH(AM25,Mob_Demob!$A$6:$A$14,0)))*N(INDEX(Mob_Demob!$K$6:$K$14,MATCH(AM25,Mob_Demob!$A$6:$A$14,0)))*Settings!$B$6+N(INDEX(Mob_Demob!$M$6:$M$14,MATCH(AM25,Mob_Demob!$A$6:$A$14,0)))*N(INDEX(Mob_Demob!$N$6:$N$14,MATCH(AM25,Mob_Demob!$A$6:$A$14,0))),0)),"") -> 550 | AR25: =IF(AQ25="","",ROUND(AQ25*Settings!$B$18,0)) -> 550 | AS25: EW-CUTLOAD,EW-MASS,EW-TRENCH-5,EW-TRENCH-10,EW-STRUCT,EW-BACKFILL,UT-PIPE-STORM,DM-PAVE-CONC | AT25: Net_HP = FEMA HP cap (90); Ziegler lists 313 GC at 73 hp. Max dig depth: Deere 135 P 20'0" [DEERE-RENT; CAT-EXC-PG]. Rent: Median of 5 sources (W 1034/3001/8703; C 850/2100/5200; B 515/1545/4635; R 650/2200/5600; A 700/2000/5250). Ex-fuel (C) = FEMA incl-fuel rate - Fuel_gal_hr_med x diesel back-out price (Settings B5).
A26: EX-CRAWL-17T | B26: Earthwork | C26: Hydraulic excavator | D26: Small 16-18 t | E26: 16-18 t (~38,000-40,000 lb) | F26: Operating weight | G26: 40200 | H26: lb | I26: Cat 317 GC (38,000 lb), 317 (40,200 lb, 133 hp); Komatsu PC170LC; Develon DX170/180 | J26: 40200 | K26: 133 | L26: GP bucket 0.899 yd3 (typ; interpolated by operating weight between EX-CRAWL-13T (30,400 lb, 0.75) and EX-CRAWL-20T (48,500 lb, 1.025)) | N26: diesel | O26: Operating Engineer - heavy equip. group (per WD) | P26: day/wk/4wk | Q26: 855 | R26: 2463 | S26: 6513 | T26: 5750 | U26: 8766 | V26: bare | Y26: W25;C25;R25;A26 | Z26: 2025-2026 | AA26: A | AC26: =ROUND(AC25+(AC27-AC25)*(J26-J25)/(J27-J25),2) -> 102.01 | AD26: FEMA 2025 (interpolated) | AE26: =ROUND(K26*Settings!$B$11*Settings!$B$13,2) -> 2.26 | AF26: =ROUND(K26*Settings!$B$11*Settings!$B$14,2) -> 2.97 | AG26: =ROUND(K26*Settings!$B$11*Settings!$B$15,2) -> 3.88 | AH26: Derived (C): Net_HP x 0.0486 diesel gal/bhp-hr x load factor 0.35/0.46/0.60 [USACE-EP] | AI26: =IF(OR(AC26="",AF26="",Settings!$B$5=""),"",ROUND(AC26-AF26*Settings!$B$5,2)) -> 91.14 | AJ26: C | AK26: C | AL26: Owned: USACE standby = 0.5 x DEPR + FCCM, max 40 hr/wk [USACE-EP]; with only an all-in rate use Caltrans delay factor x rate, max 8 hr/day & 40 hr/wk [CALT-2627]: HCECL factor 0.17 (book) / 0.16 (Sep 2026 interim). Rental: accrues by calendar period (no idle discount). FEMA: not eligible unless intermittent use [FEMA-PG]. | AM26: lowboy-legal | AN26: 40200 | AP26: N | AQ26: =IFERROR(IF(AND(INDEX(Mob_Demob!$D$6:$D$14,MATCH(AM26,Mob_Demob!$A$6:$A$14,0))="",INDEX(Mob_Demob!$G$6:$G$14,MATCH(AM26,Mob_Demob!$A$6:$A$14,0))=""),"",ROUND(MAX(N(INDEX(Mob_Demob!$G$6:$G$14,MATCH(AM26,Mob_Demob!$A$6:$A$14,0))),N(INDEX(Mob_Demob!$D$6:$D$14,MATCH(AM26,Mob_Demob!$A$6:$A$14,0)))*Settings!$B$6)+IF(AP26="Y",N(INDEX(Mob_Demob!$I$6:$I$14,MATCH(AM26,Mob_Demob!$A$6:$A$14,0)))*Settings!$B$19,0)+N(INDEX(Mob_Demob!$L$6:$L$14,MATCH(AM26,Mob_Demob!$A$6:$A$14,0)))*N(INDEX(Mob_Demob!$K$6:$K$14,MATCH(AM26,Mob_Demob!$A$6:$A$14,0)))*Settings!$B$6+N(INDEX(Mob_Demob!$M$6:$M$14,MATCH(AM26,Mob_Demob!$A$6:$A$14,0)))*N(INDEX(Mob_Demob!$N$6:$N$14,MATCH(AM26,Mob_Demob!$A$6:$A$14,0))),0)),"") -> 550 | AR26: =IF(AQ26="","",ROUND(AQ26*Settings!$B$18,0)) -> 550 | AS26: EW-CUTLOAD,EW-MASS,EW-TRENCH-5,EW-TRENCH-10,EW-STRUCT,EW-BACKFILL,UT-PIPE-STORM,DM-PAVE-CONC | AT26: Rounded half-up (Excel rule) in revision; may differ by 1 from the notes table, which used banker's rounding. Rent: Median of 4 sources (W 1042/3023/8766; C 950/2375/5900; R 760/2550/7125; A 750/2250/5750). Owned_rate_hr_incl_fuel interpolated (C) between EX-CRAWL-13T and EX-CRAWL-20T by operating weight (FEMA 2025 endpoints). Fuel gal/hr derived (C): Net_HP x USACE fuel factor x load factor (Settings B11-B15). Ex-fuel (C) = FEMA incl-fuel rate - Fuel_gal_hr_med x diesel back-out price (Settings B5). | AU26: Non-monotonic vs EX-CRAWL-20T - source data
A27: EX-CRAWL-20T | B27: Earthwork | C27: Hydraulic excavator | D27: Medium 20-25 t | E27: 20-25 t (~48,500-62,800 lb) | F27: Operating weight | G27: 48500 | H27: lb | I27: Cat 320 GC (48,500 lb, 146 hp), 320 (172 hp), 323, 325, 326; Komatsu PC210LC/PC238; Develon DX225/235/255 | J27: 48500 | K27: 150 | L27: GP bucket 1.025 yd3 (typ; midpoint of typical GP 0.75-1.3 yd3 (Deere 210 P 0.56-1.29)) | N27: diesel | O27: Operating Engineer - heavy equip. group (per WD) | P27: day/wk/4wk | Q27: 1040 | R27: 2927 | S27: 7950 | T27: 6500 | U27: 10259 | V27: bare | Y27: W25;C25;R25;A26 | Z27: 2025-2026 | AA27: A | AB27: 8282 | AC27: 107.93 | AD27: FEMA 2025 | AE27: 2.18 | AF27: 2.78 | AG27: 3.37 | AH27: Cat VisionLink Dec 2022, model 320-07 GC [CATFUEL22] | AI27: =IF(OR(AC27="",AF27="",Settings!$B$5=""),"",ROUND(AC27-AF27*Settings!$B$5,2)) -> 97.76 | AJ27: B | AK27: C | AL27: Owned: USACE standby = 0.5 x DEPR + FCCM, max 40 hr/wk [USACE-EP]; with only an all-in rate use Caltrans delay factor x rate, max 8 hr/day & 40 hr/wk [CALT-2627]: HCECL factor 0.17 (book) / 0.16 (Sep 2026 interim). Rental: accrues by calendar period (no idle discount). FEMA: not eligible unless intermittent use [FEMA-PG]. | AM27: lowboy-legal | AN27: 48500 | AP27: maybe | AQ27: =IFERROR(IF(AND(INDEX(Mob_Demob!$D$6:$D$14,MATCH(AM27,Mob_Demob!$A$6:$A$14,0))="",INDEX(Mob_Demob!$G$6:$G$14,MATCH(AM27,Mob_Demob!$A$6:$A$14,0))=""),"",ROUND(MAX(N(INDEX(Mob_Demob!$G$6:$G$14,MATCH(AM27,Mob_Demob!$A$6:$A$14,0))),N(INDEX(Mob_Demob!$D$6:$D$14,MATCH(AM27,Mob_Demob!$A$6:$A$14,0)))*Settings!$B$6)+IF(AP27="Y",N(INDEX(Mob_Demob!$I$6:$I$14,MATCH(AM27,Mob_Demob!$A$6:$A$14,0)))*Settings!$B$19,0)+N(INDEX(Mob_Demob!$L$6:$L$14,MATCH(AM27,Mob_Demob!$A$6:$A$14,0)))*N(INDEX(Mob_Demob!$K$6:$K$14,MATCH(AM27,Mob_Demob!$A$6:$A$14,0)))*Settings!$B$6+N(INDEX(Mob_Demob!$M$6:$M$14,MATCH(AM27,Mob_Demob!$A$6:$A$14,0)))*N(INDEX(Mob_Demob!$N$6:$N$14,MATCH(AM27,Mob_Demob!$A$6:$A$14,0))),0)),"") -> 550 | AR27: =IF(AQ27="","",ROUND(AQ27*Settings!$B$18,0)) -> 550 | AS27: EW-CUTLOAD,EW-MASS,EW-TRENCH-5,EW-TRENCH-10,EW-STRUCT,EW-BACKFILL,UT-PIPE-STORM,DM-PAVE-CONC,UT-PIPE-SAN,EW-TRENCH-15 | AT27: Max dig depth: Deere 210 P 21'11"; Cat 320 22 ft [DEERE-RENT; CAT-EXC-PG]. Rent: Median of 4 sources (W 1220/3538/10259; C 1162/2888/7200; R 917/2967/8700; A 800/2500/6500). Machine-control 'i' models cost 25-75% more (Columbus PC210LCi 1400/4150/12400). Ex-fuel (C) = FEMA incl-fuel rate - Fuel_gal_hr_med x diesel back-out price (Settings B5).
A28: EX-CRAWL-30T | B28: Earthwork | C28: Hydraulic excavator | D28: Medium 30-36 t | E28: 30-36 t (~68,000-81,000 lb) | F28: Operating weight | G28: 69200 | H28: lb | I28: Cat 330 (69,200 lb, 273 hp), 330 GC, 335, 336 (81,100 lb, 300 hp); Komatsu PC290/PC360; Develon DX300/350 | J28: 69200 | K28: 201 | L28: GP bucket 1.95 yd3 (typ; midpoint of typical GP 1.4-2.5 yd3 (Deere 345/350 P, Komatsu PC360LC-11)) | N28: diesel | O28: Operating Engineer - heavy equip. group (per WD) | P28: day/wk/4wk | Q28: 1424 | R28: 4019 | S28: 10850 | T28: 9000 | U28: 14177 | V28: bare | Y28: W25;C25;R25;A26 | Z28: 2025-2026 | AA28: A | AB28: 8283 | AC28: 150.99 | AD28: FEMA 2025 | AE28: 3.51 | AF28: 4.5 | AG28: 5.49 | AH28: Cat VisionLink Dec 2022, model 330-07 GC [CATFUEL22] | AI28: =IF(OR(AC28="",AF28="",Settings!$B$5=""),"",ROUND(AC28-AF28*Settings!$B$5,2)) -> 134.52 | AJ28: B | AK28: C | AL28: Owned: USACE standby = 0.5 x DEPR + FCCM, max 40 hr/wk [USACE-EP]; with only an all-in rate use Caltrans delay factor x rate, max 8 hr/day & 40 hr/wk [CALT-2627]: HCECL factor 0.17 (book) / 0.16 (Sep 2026 interim). Rental: accrues by calendar period (no idle discount). FEMA: not eligible unless intermittent use [FEMA-PG]. | AM28: lowboy-permitted | AN28: 69200 | AO28: 11.1 | AP28: Y | AQ28: =IFERROR(IF(AND(INDEX(Mob_Demob!$D$6:$D$14,MATCH(AM28,Mob_Demob!$A$6:$A$14,0))="",INDEX(Mob_Demob!$G$6:$G$14,MATCH(AM28,Mob_Demob!$A$6:$A$14,0))=""),"",ROUND(MAX(N(INDEX(Mob_Demob!$G$6:$G$14,MATCH(AM28,Mob_Demob!$A$6:$A$14,0))),N(INDEX(Mob_Demob!$D$6:$D$14,MATCH(AM28,Mob_Demob!$A$6:$A$14,0)))*Settings!$B$6)+IF(AP28="Y",N(INDEX(Mob_Demob!$I$6:$I$14,MATCH(AM28,Mob_Demob!$A$6:$A$14,0)))*Settings!$B$19,0)+N(INDEX(Mob_Demob!$L$6:$L$14,MATCH(AM28,Mob_Demob!$A$6:$A$14,0)))*N(INDEX(Mob_Demob!$K$6:$K$14,MATCH(AM28,Mob_Demob!$A$6:$A$14,0)))*Settings!$B$6+N(INDEX(Mob_Demob!$M$6:$M$14,MATCH(AM28,Mob_Demob!$A$6:$A$14,0)))*N(INDEX(Mob_Demob!$N$6:$N$14,MATCH(AM28,Mob_Demob!$A$6:$A$14,0))),0)),"") -> 1800 | AR28: =IF(AQ28="","",ROUND(AQ28*Settings!$B$18,0)) -> 1800 | AS28: EW-CUTLOAD,EW-MASS,EW-TRENCH-5,EW-TRENCH-10,EW-STRUCT,EW-BACKFILL,UT-PIPE-STORM,DM-PAVE-CONC,UT-PIPE-SAN,UT-PIPE-STORM-L,EW-TRENCH-15 | AT28: Transport width 11.1 ft = Cat 336D L (133.5 in) per RitchieSpecs; >8.5 ft so oversize. Net_HP = FEMA cap (201). Rounded half-up (Excel rule) in revision; may differ by 1 from the notes table, which used banker's rounding. Max dig depth: Deere 350 P 24'3"-26'10"; Cat 336 26.11 ft [DEERE-RENT; CAT-EXC-PG]. Rent: Median of 4 sources (W 1686/4888/14176; C 1650/4088/10200; R 1198/3950/11500; A 1075/3475/9000). Ex-fuel (C) = FEMA incl-fuel rate - Fuel_gal_hr_med x diesel back-out price (Settings B5).
A29: EX-CRAWL-40T | B29: Earthwork | C29: Hydraulic excavator | D29: Large 36-45 t | E29: ~40 t (83,000 lb) | F29: Operating weight | G29: 83100 | H29: lb | I29: Cat 340 (83,100 lb, 346 hp) | J29: 83100 | K29: 350 | L29: GP bucket 2.402 yd3 (typ; interpolated by operating weight between EX-CRAWL-30T (69,200 lb, 1.95) and EX-CRAWL-70T (162,900 lb, 5.0)) | N29: diesel | O29: Operating Engineer - heavy equip. group (per WD) | P29: day/wk/4wk | Q29: 1903 | R29: 5520 | S29: 16008 | V29: bare | Y29: W25 | Z29: 2025 | AA29: B | AB29: 8284 | AC29: 183.84 | AD29: FEMA 2025 | AE29: 5.32 | AF29: 6.96 | AG29: 8.61 | AH29: Cat VisionLink Dec 2022, model 340-08 [CATFUEL22] | AI29: =IF(OR(AC29="",AF29="",Settings!$B$5=""),"",ROUND(AC29-AF29*Settings!$B$5,2)) -> 158.37 | AJ29: B | AK29: C | AL29: Owned: USACE standby = 0.5 x DEPR + FCCM, max 40 hr/wk [USACE-EP]; with only an all-in rate use Caltrans delay factor x rate, max 8 hr/day & 40 hr/wk [CALT-2627]: HCECL factor 0.17 (book) / 0.16 (Sep 2026 interim). Rental: accrues by calendar period (no idle discount). FEMA: not eligible unless intermittent use [FEMA-PG]. | AM29: lowboy-permitted | AN29: 83100 | AP29: Y | AQ29: =IFERROR(IF(AND(INDEX(Mob_Demob!$D$6:$D$14,MATCH(AM29,Mob_Demob!$A$6:$A$14,0))="",INDEX(Mob_Demob!$G$6:$G$14,MATCH(AM29,Mob_Demob!$A$6:$A$14,0))=""),"",ROUND(MAX(N(INDEX(Mob_Demob!$G$6:$G$14,MATCH(AM29,Mob_Demob!$A$6:$A$14,0))),N(INDEX(Mob_Demob!$D$6:$D$14,MATCH(AM29,Mob_Demob!$A$6:$A$14,0)))*Settings!$B$6)+IF(AP29="Y",N(INDEX(Mob_Demob!$I$6:$I$14,MATCH(AM29,Mob_Demob!$A$6:$A$14,0)))*Settings!$B$19,0)+N(INDEX(Mob_Demob!$L$6:$L$14,MATCH(AM29,Mob_Demob!$A$6:$A$14,0)))*N(INDEX(Mob_Demob!$K$6:$K$14,MATCH(AM29,Mob_Demob!$A$6:$A$14,0)))*Settings!$B$6+N(INDEX(Mob_Demob!$M$6:$M$14,MATCH(AM29,Mob_Demob!$A$6:$A$14,0)))*N(INDEX(Mob_Demob!$N$6:$N$14,MATCH(AM29,Mob_Demob!$A$6:$A$14,0))),0)),"") -> 1800 | AR29: =IF(AQ29="","",ROUND(AQ29*Settings!$B$18,0)) -> 1800 | AS29: EW-CUTLOAD,EW-MASS,EW-TRENCH-10,EW-STRUCT,UT-PIPE-STORM-L,EW-TRENCH-15 | AT29: Rent: Wheeler 340 only. Ex-fuel (C) = FEMA incl-fuel rate - Fuel_gal_hr_med x diesel back-out price (Settings B5). | AU29: Non-monotonic vs EX-CRAWL-50T - source data
A30: EX-CRAWL-50T | B30: Earthwork | C30: Hydraulic excavator | D30: Large 45-55 t | E30: 45-55 t (~105,000-108,000 lb) | F30: Operating weight | G30: 107800 | H30: lb | I30: Cat 349/350/352 (105,100-107,800 lb, 413-443 hp); Komatsu PC490LC | J30: 107800 | K30: 443 | L30: GP bucket 3.206 yd3 (typ; interpolated by operating weight between EX-CRAWL-30T (69,200 lb, 1.95) and EX-CRAWL-70T (162,900 lb, 5.0)) | N30: diesel | O30: Operating Engineer - heavy equip. group (per WD) | P30: day/wk/4wk | Q30: 2250 | R30: 5600 | S30: 14000 | T30: 13500 | U30: 22488 | V30: bare | Y30: W25;C25;A26 | Z30: 2025-2026 | AA30: A | AC30: =ROUND(AC29+(AC32-AC29)*(J30-J29)/(J32-J29),2) -> 203.85 | AD30: FEMA 2025 (interpolated) | AE30: 6.19 | AF30: 8.02 | AG30: 9.85 | AH30: Cat VisionLink Dec 2022, model 352-07 [CATFUEL22] | AI30: =IF(OR(AC30="",AF30="",Settings!$B$5=""),"",ROUND(AC30-AF30*Settings!$B$5,2)) -> 174.5 | AJ30: C | AK30: C | AL30: Owned: USACE standby = 0.5 x DEPR + FCCM, max 40 hr/wk [USACE-EP]; with only an all-in rate use Caltrans delay factor x rate, max 8 hr/day & 40 hr/wk [CALT-2627]: HCECL factor 0.17 (book) / 0.16 (Sep 2026 interim). Rental: accrues by calendar period (no idle discount). FEMA: not eligible unless intermittent use [FEMA-PG]. | AM30: multi-axle-heavy | AN30: 107800 | AP30: Y | AQ30: =IFERROR(IF(AND(INDEX(Mob_Demob!$D$6:$D$14,MATCH(AM30,Mob_Demob!$A$6:$A$14,0))="",INDEX(Mob_Demob!$G$6:$G$14,MATCH(AM30,Mob_Demob!$A$6:$A$14,0))=""),"",ROUND(MAX(N(INDEX(Mob_Demob!$G$6:$G$14,MATCH(AM30,Mob_Demob!$A$6:$A$14,0))),N(INDEX(Mob_Demob!$D$6:$D$14,MATCH(AM30,Mob_Demob!$A$6:$A$14,0)))*Settings!$B$6)+IF(AP30="Y",N(INDEX(Mob_Demob!$I$6:$I$14,MATCH(AM30,Mob_Demob!$A$6:$A$14,0)))*Settings!$B$19,0)+N(INDEX(Mob_Demob!$L$6:$L$14,MATCH(AM30,Mob_Demob!$A$6:$A$14,0)))*N(INDEX(Mob_Demob!$K$6:$K$14,MATCH(AM30,Mob_Demob!$A$6:$A$14,0)))*Settings!$B$6+N(INDEX(Mob_Demob!$M$6:$M$14,MATCH(AM30,Mob_Demob!$A$6:$A$14,0)))*N(INDEX(Mob_Demob!$N$6:$N$14,MATCH(AM30,Mob_Demob!$A$6:$A$14,0))),0)),"") -> 1913 | AR30: =IF(AQ30="","",ROUND(AQ30*Settings!$B$18,0)) -> 1913 | AS30: EW-CUTLOAD,EW-MASS,EW-STRUCT | AT30: Max dig depth: Cat 352 26.11 ft [DEERE-RENT; CAT-EXC-PG]. Rent: Median of 3 sources (W 2674/7754/22488; C 2250/5600/14000; A 2000/4500/13500). PC490+ may bill set-up/dismantle separately (Columbus). Owned_rate_hr_incl_fuel interpolated (C) between EX-CRAWL-40T and EX-CRAWL-90T by operating weight (FEMA 2025 endpoints). Ex-fuel (C) = FEMA incl-fuel rate - Fuel_gal_hr_med x diesel back-out price (Settings B5).
A31: EX-CRAWL-70T | B31: Earthwork | C31: Hydraulic excavator | D31: Mass excavation 65-75 t | E31: 65-75 t (~145,000-163,000 lb) | F31: Operating weight | G31: 162900 | H31: lb | I31: Cat 374 (162,900 lb, 484 hp); Komatsu PC650LC (145,000 lb) | J31: 162900 | K31: 484 | L31: GP bucket 5 yd3 (typ; midpoint of typical production bucket 4-6 yd3 (Cat 374 SD 4.32; Deere 870 P 4.56 spec bucket)) | N31: diesel | O31: Operating Engineer - heavy equip. group (per WD) | P31: day/wk/4wk | Q31: 3950 | R31: 10690 | S31: 29160 | T31: 23000 | U31: 35320 | V31: bare | Y31: W25;C25 | Z31: 2025-2026 | AA31: A | AC31: =ROUND(AC29+(AC32-AC29)*(J31-J29)/(J32-J29),2) -> 248.49 | AD31: FEMA 2025 (interpolated) | AE31: 7.74 | AF31: 9.95 | AG31: 12.17 | AH31: Cat VisionLink Dec 2022, model 374-07 [CATFUEL22] | AI31: =IF(OR(AC31="",AF31="",Settings!$B$5=""),"",ROUND(AC31-AF31*Settings!$B$5,2)) -> 212.07 | AJ31: C | AK31: C | AL31: Owned: USACE standby = 0.5 x DEPR + FCCM, max 40 hr/wk [USACE-EP]; with only an all-in rate use Caltrans delay factor x rate, max 8 hr/day & 40 hr/wk [CALT-2627]: HCECL factor 0.17 (book) / 0.16 (Sep 2026 interim). Rental: accrues by calendar period (no idle discount). FEMA: not eligible unless intermittent use [FEMA-PG]. | AM31: multi-axle-heavy | AN31: 162900 | AP31: Y | AQ31: =IFERROR(IF(AND(INDEX(Mob_Demob!$D$6:$D$14,MATCH(AM31,Mob_Demob!$A$6:$A$14,0))="",INDEX(Mob_Demob!$G$6:$G$14,MATCH(AM31,Mob_Demob!$A$6:$A$14,0))=""),"",ROUND(MAX(N(INDEX(Mob_Demob!$G$6:$G$14,MATCH(AM31,Mob_Demob!$A$6:$A$14,0))),N(INDEX(Mob_Demob!$D$6:$D$14,MATCH(AM31,Mob_Demob!$A$6:$A$14,0)))*Settings!$B$6)+IF(AP31="Y",N(INDEX(Mob_Demob!$I$6:$I$14,MATCH(AM31,Mob_Demob!$A$6:$A$14,0)))*Settings!$B$19,0)+N(INDEX(Mob_Demob!$L$6:$L$14,MATCH(AM31,Mob_Demob!$A$6:$A$14,0)))*N(INDEX(Mob_Demob!$K$6:$K$14,MATCH(AM31,Mob_Demob!$A$6:$A$14,0)))*Settings!$B$6+N(INDEX(Mob_Demob!$M$6:$M$14,MATCH(AM31,Mob_Demob!$A$6:$A$14,0)))*N(INDEX(Mob_Demob!$N$6:$N$14,MATCH(AM31,Mob_Demob!$A$6:$A$14,0))),0)),"") -> 1913 | AR31: =IF(AQ31="","",ROUND(AQ31*Settings!$B$18,0)) -> 1913 | AS31: EW-CUTLOAD,EW-MASS | AT31: Max dig depth: Cat 374 28.1 ft [DEERE-RENT; CAT-EXC-PG]. Rent: Median (=mean) of 2 sources: W 374 4200/12179/35320; C PC650 3700/9200/23000. (Notes' 65-95 t class split into 65-75 and 90-95 t.) Owned_rate_hr_incl_fuel interpolated (C) between EX-CRAWL-40T and EX-CRAWL-90T by operating weight (FEMA 2025 endpoints). Ex-fuel (C) = FEMA incl-fuel rate - Fuel_gal_hr_med x diesel back-out price (Settings B5).
A32: EX-CRAWL-90T | B32: Earthwork | C32: Hydraulic excavator | D32: Mass excavation 90-95 t | E32: 90-95 t (~205,000-207,000 lb) | F32: Operating weight | G32: 207400 | H32: lb | I32: Cat 395 (207,400 lb, 542 hp); Komatsu PC900LC (205,000 lb) | J32: 207400 | K32: 550 | L32: GP bucket 6 yd3 (typ; midpoint of typical 5-7 yd3 (Cat 395 SD 6.8)) | N32: diesel | O32: Operating Engineer - heavy equip. group (per WD) | P32: day/wk/4wk | Q32: 4999 | R32: 13555 | S32: 36988 | T32: 29000 | U32: 44976 | V32: bare | Y32: W25;C25 | Z32: 2025-2026 | AA32: A | AB32: 8285 | AC32: 284.54 | AD32: FEMA 2025 | AE32: 9.6 | AF32: 12.45 | AG32: 15.3 | AH32: Cat VisionLink Dec 2022, model 395-07 [CATFUEL22] | AI32: =IF(OR(AC32="",AF32="",Settings!$B$5=""),"",ROUND(AC32-AF32*Settings!$B$5,2)) -> 238.97 | AJ32: B | AK32: C | AL32: Owned: USACE standby = 0.5 x DEPR + FCCM, max 40 hr/wk [USACE-EP]; with only an all-in rate use Caltrans delay factor x rate, max 8 hr/day & 40 hr/wk [CALT-2627]: HCECL factor 0.17 (book) / 0.16 (Sep 2026 interim). Rental: accrues by calendar period (no idle discount). FEMA: not eligible unless intermittent use [FEMA-PG]. | AM32: multi-axle-heavy | AN32: 207400 | AP32: Y | AQ32: =IFERROR(IF(AND(INDEX(Mob_Demob!$D$6:$D$14,MATCH(AM32,Mob_Demob!$A$6:$A$14,0))="",INDEX(Mob_Demob!$G$6:$G$14,MATCH(AM32,Mob_Demob!$A$6:$A$14,0))=""),"",ROUND(MAX(N(INDEX(Mob_Demob!$G$6:$G$14,MATCH(AM32,Mob_Demob!$A$6:$A$14,0))),N(INDEX(Mob_Demob!$D$6:$D$14,MATCH(AM32,Mob_Demob!$A$6:$A$14,0)))*Settings!$B$6)+IF(AP32="Y",N(INDEX(Mob_Demob!$I$6:$I$14,MATCH(AM32,Mob_Demob!$A$6:$A$14,0)))*Settings!$B$19,0)+N(INDEX(Mob_Demob!$L$6:$L$14,MATCH(AM32,Mob_Demob!$A$6:$A$14,0)))*N(INDEX(Mob_Demob!$K$6:$K$14,MATCH(AM32,Mob_Demob!$A$6:$A$14,0)))*Settings!$B$6+N(INDEX(Mob_Demob!$M$6:$M$14,MATCH(AM32,Mob_Demob!$A$6:$A$14,0)))*N(INDEX(Mob_Demob!$N$6:$N$14,MATCH(AM32,Mob_Demob!$A$6:$A$14,0))),0)),"") -> 1913 | AR32: =IF(AQ32="","",ROUND(AQ32*Settings!$B$18,0)) -> 1913 | AS32: EW-CUTLOAD,EW-MASS | AT32: Max dig depth: Cat 395 31.9 ft [DEERE-RENT; CAT-EXC-PG]. Rent: Median (=mean) of 2 sources: W 395 5348/15509/44976; C PC900 4650/11600/29000. Ex-fuel (C) = FEMA incl-fuel rate - Fuel_gal_hr_med x diesel back-out price (Settings B5).
A33: EX-WHEEL-11T | B33: Earthwork | C33: Hydraulic excavator | D33: Wheeled excavator | E33: Wheeled ~25,000 lb | F33: Operating weight | G33: 25000 | H33: lb | I33: Wheeled excavator 25K lb class (Ahearn) | J33: 25000 | N33: diesel | O33: Operating Engineer - heavy equip. group (per WD) | P33: day/wk/4wk | Q33: 850 | R33: 2500 | S33: 5500 | V33: bare | Y33: A26 | Z33: read Oct 2026 | AA33: B | AJ33: D | AK33: D | AL33: Owned: USACE standby = 0.5 x DEPR + FCCM, max 40 hr/wk [USACE-EP]; with only an all-in rate use Caltrans delay factor x rate, max 8 hr/day & 40 hr/wk [CALT-2627]: HCECL factor 0.17 (book) / 0.16 (Sep 2026 interim). Rental: accrues by calendar period (no idle discount). FEMA: not eligible unless intermittent use [FEMA-PG]. | AM33: lowboy-legal | AN33: 25000 | AP33: N | AQ33: =IFERROR(IF(AND(INDEX(Mob_Demob!$D$6:$D$14,MATCH(AM33,Mob_Demob!$A$6:$A$14,0))="",INDEX(Mob_Demob!$G$6:$G$14,MATCH(AM33,Mob_Demob!$A$6:$A$14,0))=""),"",ROUND(MAX(N(INDEX(Mob_Demob!$G$6:$G$14,MATCH(AM33,Mob_Demob!$A$6:$A$14,0))),N(INDEX(Mob_Demob!$D$6:$D$14,MATCH(AM33,Mob_Demob!$A$6:$A$14,0)))*Settings!$B$6)+IF(AP33="Y",N(INDEX(Mob_Demob!$I$6:$I$14,MATCH(AM33,Mob_Demob!$A$6:$A$14,0)))*Settings!$B$19,0)+N(INDEX(Mob_Demob!$L$6:$L$14,MATCH(AM33,Mob_Demob!$A$6:$A$14,0)))*N(INDEX(Mob_Demob!$K$6:$K$14,MATCH(AM33,Mob_Demob!$A$6:$A$14,0)))*Settings!$B$6+N(INDEX(Mob_Demob!$M$6:$M$14,MATCH(AM33,Mob_Demob!$A$6:$A$14,0)))*N(INDEX(Mob_Demob!$N$6:$N$14,MATCH(AM33,Mob_Demob!$A$6:$A$14,0))),0)),"") -> 550 | AR33: =IF(AQ33="","",ROUND(AQ33*Settings!$B$18,0)) -> 550 | AS33: EW-TRENCH-5,EW-STRUCT,EW-BACKFILL | AT33: Rent: Ahearn only. | AU33: Needs fuel gal/hr; Needs rate (owned)
A34: EX-WHEEL-20T | B34: Earthwork | C34: Hydraulic excavator | D34: Wheeled excavator | E34: Wheeled 40,000-55,000 lb | F34: Operating weight | G34: 43980 | H34: lb | I34: Cat M314-M322 (36,990-54,770 lb, 134-174 hp; 18.6-23 mph travel); Ahearn 40-45K lb | J34: 43980 | K34: 174 | N34: diesel | O34: Operating Engineer - heavy equip. group (per WD) | P34: day/wk/4wk | Q34: 1050 | R34: 3500 | S34: 7500 | V34: bare | Y34: A26 | Z34: read Oct 2026 | AA34: B | AE34: =ROUND(K34*Settings!$B$11*Settings!$B$13,2) -> 2.96 | AF34: =ROUND(K34*Settings!$B$11*Settings!$B$14,2) -> 3.89 | AG34: =ROUND(K34*Settings!$B$11*Settings!$B$15,2) -> 5.07 | AH34: Derived (C): Net_HP x 0.0486 diesel gal/bhp-hr x load factor 0.35/0.46/0.60 [USACE-EP] | AJ34: D | AK34: D | AL34: Owned: USACE standby = 0.5 x DEPR + FCCM, max 40 hr/wk [USACE-EP]; with only an all-in rate use Caltrans delay factor x rate, max 8 hr/day & 40 hr/wk [CALT-2627]: HCECL factor 0.17 (book) / 0.16 (Sep 2026 interim). Rental: accrues by calendar period (no idle discount). FEMA: not eligible unless intermittent use [FEMA-PG]. | AM34: lowboy-legal | AN34: 43980 | AP34: N | AQ34: =IFERROR(IF(AND(INDEX(Mob_Demob!$D$6:$D$14,MATCH(AM34,Mob_Demob!$A$6:$A$14,0))="",INDEX(Mob_Demob!$G$6:$G$14,MATCH(AM34,Mob_Demob!$A$6:$A$14,0))=""),"",ROUND(MAX(N(INDEX(Mob_Demob!$G$6:$G$14,MATCH(AM34,Mob_Demob!$A$6:$A$14,0))),N(INDEX(Mob_Demob!$D$6:$D$14,MATCH(AM34,Mob_Demob!$A$6:$A$14,0)))*Settings!$B$6)+IF(AP34="Y",N(INDEX(Mob_Demob!$I$6:$I$14,MATCH(AM34,Mob_Demob!$A$6:$A$14,0)))*Settings!$B$19,0)+N(INDEX(Mob_Demob!$L$6:$L$14,MATCH(AM34,Mob_Demob!$A$6:$A$14,0)))*N(INDEX(Mob_Demob!$K$6:$K$14,MATCH(AM34,Mob_Demob!$A$6:$A$14,0)))*Settings!$B$6+N(INDEX(Mob_Demob!$M$6:$M$14,MATCH(AM34,Mob_Demob!$A$6:$A$14,0)))*N(INDEX(Mob_Demob!$N$6:$N$14,MATCH(AM34,Mob_Demob!$A$6:$A$14,0))),0)),"") -> 550 | AR34: =IF(AQ34="","",ROUND(AQ34*Settings!$B$18,0)) -> 550 | AS34: EW-TRENCH-5,EW-TRENCH-10,EW-STRUCT,EW-BACKFILL,EW-TRENCH-15 | AT34: Representative Cat M318 (174 hp, 43,980 lb). Can road short distances at 18.6-23 mph. Rent: Ahearn 40-45K lb only. Fuel gal/hr derived (C): Net_HP x USACE fuel factor x load factor (Settings B11-B15). | AU34: Needs rate (owned)
A35: EX-LR-40T | B35: Earthwork | C35: Hydraulic excavator | D35: Long-reach (LRE) | E35: Long-reach ~43 t (42.8 ft dig) | F35: Max dig depth | G35: 42.8 | H35: ft | I35: Cat 340 LRE | J35: 96500 | N35: diesel | O35: Operating Engineer - heavy equip. group (per WD) | P35: day/wk/4wk | V35: bare | AA35: D | AJ35: D | AK35: D | AL35: Owned: USACE standby = 0.5 x DEPR + FCCM, max 40 hr/wk [USACE-EP]; with only an all-in rate use Caltrans delay factor x rate, max 8 hr/day & 40 hr/wk [CALT-2627]: HCECL factor 0.17 (book) / 0.16 (Sep 2026 interim). Rental: accrues by calendar period (no idle discount). FEMA: not eligible unless intermittent use [FEMA-PG]. | AM35: lowboy-permitted | AN35: 96500 | AP35: Y | AQ35: =IFERROR(IF(AND(INDEX(Mob_Demob!$D$6:$D$14,MATCH(AM35,Mob_Demob!$A$6:$A$14,0))="",INDEX(Mob_Demob!$G$6:$G$14,MATCH(AM35,Mob_Demob!$A$6:$A$14,0))=""),"",ROUND(MAX(N(INDEX(Mob_Demob!$G$6:$G$14,MATCH(AM35,Mob_Demob!$A$6:$A$14,0))),N(INDEX(Mob_Demob!$D$6:$D$14,MATCH(AM35,Mob_Demob!$A$6:$A$14,0)))*Settings!$B$6)+IF(AP35="Y",N(INDEX(Mob_Demob!$I$6:$I$14,MATCH(AM35,Mob_Demob!$A$6:$A$14,0)))*Settings!$B$19,0)+N(INDEX(Mob_Demob!$L$6:$L$14,MATCH(AM35,Mob_Demob!$A$6:$A$14,0)))*N(INDEX(Mob_Demob!$K$6:$K$14,MATCH(AM35,Mob_Demob!$A$6:$A$14,0)))*Settings!$B$6+N(INDEX(Mob_Demob!$M$6:$M$14,MATCH(AM35,Mob_Demob!$A$6:$A$14,0)))*N(INDEX(Mob_Demob!$N$6:$N$14,MATCH(AM35,Mob_Demob!$A$6:$A$14,0))),0)),"") -> 1800 | AR35: =IF(AQ35="","",ROUND(AQ35*Settings!$B$18,0)) -> 1800 | AS35: EW-MASS | AT35: Specs Ziegler. | AU35: Needs rate; Needs fuel gal/hr; Needs rate (rental); Needs rate (owned)
A36: EX-LR-55T | B36: Earthwork | C36: Hydraulic excavator | D36: Long-reach (LRE) | E36: Long-reach ~58 t (42.8 ft dig) | F36: Max dig depth | G36: 42.8 | H36: ft | I36: Cat 352 LRE | J36: 128100 | N36: diesel | O36: Operating Engineer - heavy equip. group (per WD) | P36: day/wk/4wk | V36: bare | AA36: D | AJ36: D | AK36: D | AL36: Owned: USACE standby = 0.5 x DEPR + FCCM, max 40 hr/wk [USACE-EP]; with only an all-in rate use Caltrans delay factor x rate, max 8 hr/day & 40 hr/wk [CALT-2627]: HCECL factor 0.17 (book) / 0.16 (Sep 2026 interim). Rental: accrues by calendar period (no idle discount). FEMA: not eligible unless intermittent use [FEMA-PG]. | AM36: multi-axle-heavy | AN36: 128100 | AP36: Y | AQ36: =IFERROR(IF(AND(INDEX(Mob_Demob!$D$6:$D$14,MATCH(AM36,Mob_Demob!$A$6:$A$14,0))="",INDEX(Mob_Demob!$G$6:$G$14,MATCH(AM36,Mob_Demob!$A$6:$A$14,0))=""),"",ROUND(MAX(N(INDEX(Mob_Demob!$G$6:$G$14,MATCH(AM36,Mob_Demob!$A$6:$A$14,0))),N(INDEX(Mob_Demob!$D$6:$D$14,MATCH(AM36,Mob_Demob!$A$6:$A$14,0)))*Settings!$B$6)+IF(AP36="Y",N(INDEX(Mob_Demob!$I$6:$I$14,MATCH(AM36,Mob_Demob!$A$6:$A$14,0)))*Settings!$B$19,0)+N(INDEX(Mob_Demob!$L$6:$L$14,MATCH(AM36,Mob_Demob!$A$6:$A$14,0)))*N(INDEX(Mob_Demob!$K$6:$K$14,MATCH(AM36,Mob_Demob!$A$6:$A$14,0)))*Settings!$B$6+N(INDEX(Mob_Demob!$M$6:$M$14,MATCH(AM36,Mob_Demob!$A$6:$A$14,0)))*N(INDEX(Mob_Demob!$N$6:$N$14,MATCH(AM36,Mob_Demob!$A$6:$A$14,0))),0)),"") -> 1913 | AR36: =IF(AQ36="","",ROUND(AQ36*Settings!$B$18,0)) -> 1913 | AS36: EW-MASS | AT36: Specs Ziegler. | AU36: Needs rate; Needs fuel gal/hr; Needs rate (rental); Needs rate (owned)
A37: EX-SHOVEL-95T | B37: Earthwork | C37: Hydraulic excavator | D37: Front shovel | E37: Front shovel ~96 t | F37: Operating weight | G37: 212300 | H37: lb | I37: Cat 395 Front Shovel | J37: 212300 | N37: diesel | O37: Operating Engineer - heavy equip. group (per WD) | P37: day/wk/4wk | V37: bare | AA37: D | AJ37: D | AK37: D | AL37: Owned: USACE standby = 0.5 x DEPR + FCCM, max 40 hr/wk [USACE-EP]; with only an all-in rate use Caltrans delay factor x rate, max 8 hr/day & 40 hr/wk [CALT-2627]: HCECL factor 0.17 (book) / 0.16 (Sep 2026 interim). Rental: accrues by calendar period (no idle discount). FEMA: not eligible unless intermittent use [FEMA-PG]. | AM37: multi-axle-heavy | AN37: 212300 | AP37: Y | AQ37: =IFERROR(IF(AND(INDEX(Mob_Demob!$D$6:$D$14,MATCH(AM37,Mob_Demob!$A$6:$A$14,0))="",INDEX(Mob_Demob!$G$6:$G$14,MATCH(AM37,Mob_Demob!$A$6:$A$14,0))=""),"",ROUND(MAX(N(INDEX(Mob_Demob!$G$6:$G$14,MATCH(AM37,Mob_Demob!$A$6:$A$14,0))),N(INDEX(Mob_Demob!$D$6:$D$14,MATCH(AM37,Mob_Demob!$A$6:$A$14,0)))*Settings!$B$6)+IF(AP37="Y",N(INDEX(Mob_Demob!$I$6:$I$14,MATCH(AM37,Mob_Demob!$A$6:$A$14,0)))*Settings!$B$19,0)+N(INDEX(Mob_Demob!$L$6:$L$14,MATCH(AM37,Mob_Demob!$A$6:$A$14,0)))*N(INDEX(Mob_Demob!$K$6:$K$14,MATCH(AM37,Mob_Demob!$A$6:$A$14,0)))*Settings!$B$6+N(INDEX(Mob_Demob!$M$6:$M$14,MATCH(AM37,Mob_Demob!$A$6:$A$14,0)))*N(INDEX(Mob_Demob!$N$6:$N$14,MATCH(AM37,Mob_Demob!$A$6:$A$14,0))),0)),"") -> 1913 | AR37: =IF(AQ37="","",ROUND(AQ37*Settings!$B$18,0)) -> 1913 | AS37: EW-CUTLOAD | AU37: Needs rate; Needs fuel gal/hr; Needs rate (rental); Needs rate (owned)
A38: EX-GRADALL-XL3100 | B38: Earthwork | C38: Hydraulic excavator | D38: Truck-mounted (Gradall) | E38: Gradall XL3100 III (0.57 CY) | F38: Bucket | G38: 0.57 | H38: CY | I38: Gradall XL3100 III | K38: 184 | L38: 0.57 CY bucket | N38: diesel | O38: Operating Engineer - heavy equip. group (per WD) | P38: day/wk/4wk | V38: bare | AA38: D | AB38: 8287 | AC38: 215.34 | AD38: FEMA 2025 | AE38: =ROUND(K38*Settings!$B$11*Settings!$B$13,2) -> 3.13 | AF38: =ROUND(K38*Settings!$B$11*Settings!$B$14,2) -> 4.11 | AG38: =ROUND(K38*Settings!$B$11*Settings!$B$15,2) -> 5.37 | AH38: Derived (C): Net_HP x 0.0486 diesel gal/bhp-hr x load factor 0.35/0.46/0.60 [USACE-EP] | AI38: =IF(OR(AC38="",AF38="",Settings!$B$5=""),"",ROUND(AC38-AF38*Settings!$B$5,2)) -> 200.3 | AJ38: B | AK38: C | AL38: Owned: USACE standby = 0.5 x DEPR + FCCM, max 40 hr/wk [USACE-EP]; with only an all-in rate use Caltrans delay factor x rate, max 8 hr/day & 40 hr/wk [CALT-2627]: HCETD factor 0.12. Rental: accrues by calendar period (no idle discount). FEMA: not eligible unless intermittent use [FEMA-PG]. | AM38: self-propelled | AP38: N | AQ38: =IFERROR(IF(AND(INDEX(Mob_Demob!$D$6:$D$14,MATCH(AM38,Mob_Demob!$A$6:$A$14,0))="",INDEX(Mob_Demob!$G$6:$G$14,MATCH(AM38,Mob_Demob!$A$6:$A$14,0))=""),"",ROUND(MAX(N(INDEX(Mob_Demob!$G$6:$G$14,MATCH(AM38,Mob_Demob!$A$6:$A$14,0))),N(INDEX(Mob_Demob!$D$6:$D$14,MATCH(AM38,Mob_Demob!$A$6:$A$14,0)))*Settings!$B$6)+IF(AP38="Y",N(INDEX(Mob_Demob!$I$6:$I$14,MATCH(AM38,Mob_Demob!$A$6:$A$14,0)))*Settings!$B$19,0)+N(INDEX(Mob_Demob!$L$6:$L$14,MATCH(AM38,Mob_Demob!$A$6:$A$14,0)))*N(INDEX(Mob_Demob!$K$6:$K$14,MATCH(AM38,Mob_Demob!$A$6:$A$14,0)))*Settings!$B$6+N(INDEX(Mob_Demob!$M$6:$M$14,MATCH(AM38,Mob_Demob!$A$6:$A$14,0)))*N(INDEX(Mob_Demob!$N$6:$N$14,MATCH(AM38,Mob_Demob!$A$6:$A$14,0))),0)),"") | AR38: =IF(AQ38="","",ROUND(AQ38*Settings!$B$18,0)) | AS38: EW-CUTLOAD,EW-TRENCH-5,EW-STRUCT | AT38: HP from taxonomy extract (owned_rates lists n/c). Travels on its own truck carrier. Fuel gal/hr derived (C): Net_HP x USACE fuel factor x load factor (Settings B11-B15). Ex-fuel (C) = FEMA incl-fuel rate - Fuel_gal_hr_med x diesel back-out price (Settings B5). | AU38: Needs rate (rental)
A39: EX-GRADALL-XL4100 | B39: Earthwork | C39: Hydraulic excavator | D39: Truck-mounted (Gradall) | E39: Gradall XL4100 III (0.62 CY) | F39: Bucket | G39: 0.62 | H39: CY | I39: Gradall XL4100 III | K39: 238 | L39: 0.62 CY bucket | N39: diesel | O39: Operating Engineer - heavy equip. group (per WD) | P39: day/wk/4wk | V39: bare | AA39: D | AB39: 8288 | AC39: 315.08 | AD39: FEMA 2025 | AE39: =ROUND(K39*Settings!$B$11*Settings!$B$13,2) -> 4.05 | AF39: =ROUND(K39*Settings!$B$11*Settings!$B$14,2) -> 5.32 | AG39: =ROUND(K39*Settings!$B$11*Settings!$B$15,2) -> 6.94 | AH39: Derived (C): Net_HP x 0.0486 diesel gal/bhp-hr x load factor 0.35/0.46/0.60 [USACE-EP] | AI39: =IF(OR(AC39="",AF39="",Settings!$B$5=""),"",ROUND(AC39-AF39*Settings!$B$5,2)) -> 295.61 | AJ39: B | AK39: C | AL39: Owned: USACE standby = 0.5 x DEPR + FCCM, max 40 hr/wk [USACE-EP]; with only an all-in rate use Caltrans delay factor x rate, max 8 hr/day & 40 hr/wk [CALT-2627]: HCETD factor 0.12. Rental: accrues by calendar period (no idle discount). FEMA: not eligible unless intermittent use [FEMA-PG]. | AM39: self-propelled | AP39: N | AQ39: =IFERROR(IF(AND(INDEX(Mob_Demob!$D$6:$D$14,MATCH(AM39,Mob_Demob!$A$6:$A$14,0))="",INDEX(Mob_Demob!$G$6:$G$14,MATCH(AM39,Mob_Demob!$A$6:$A$14,0))=""),"",ROUND(MAX(N(INDEX(Mob_Demob!$G$6:$G$14,MATCH(AM39,Mob_Demob!$A$6:$A$14,0))),N(INDEX(Mob_Demob!$D$6:$D$14,MATCH(AM39,Mob_Demob!$A$6:$A$14,0)))*Settings!$B$6)+IF(AP39="Y",N(INDEX(Mob_Demob!$I$6:$I$14,MATCH(AM39,Mob_Demob!$A$6:$A$14,0)))*Settings!$B$19,0)+N(INDEX(Mob_Demob!$L$6:$L$14,MATCH(AM39,Mob_Demob!$A$6:$A$14,0)))*N(INDEX(Mob_Demob!$K$6:$K$14,MATCH(AM39,Mob_Demob!$A$6:$A$14,0)))*Settings!$B$6+N(INDEX(Mob_Demob!$M$6:$M$14,MATCH(AM39,Mob_Demob!$A$6:$A$14,0)))*N(INDEX(Mob_Demob!$N$6:$N$14,MATCH(AM39,Mob_Demob!$A$6:$A$14,0))),0)),"") | AR39: =IF(AQ39="","",ROUND(AQ39*Settings!$B$18,0)) | AS39: EW-CUTLOAD,EW-TRENCH-5,EW-STRUCT | AT39: HP from taxonomy extract (owned_rates lists n/c). Travels on its own truck carrier. Fuel gal/hr derived (C): Net_HP x USACE fuel factor x load factor (Settings B11-B15). Ex-fuel (C) = FEMA incl-fuel rate - Fuel_gal_hr_med x diesel back-out price (Settings B5). | AU39: Needs rate (rental)
A40: EX-GRADALL-XL5100 | B40: Earthwork | C40: Hydraulic excavator | D40: Truck-mounted (Gradall) | E40: Gradall XL5100 (1.25 CY) | F40: Bucket | G40: 1.25 | H40: CY | I40: Gradall XL5100 | K40: 230 | L40: 1.25 CY bucket | N40: diesel | O40: Operating Engineer - heavy equip. group (per WD) | P40: day/wk/4wk | V40: bare | AA40: D | AB40: 8289 | AC40: 351.11 | AD40: FEMA 2025 | AE40: =ROUND(K40*Settings!$B$11*Settings!$B$13,2) -> 3.91 | AF40: =ROUND(K40*Settings!$B$11*Settings!$B$14,2) -> 5.14 | AG40: =ROUND(K40*Settings!$B$11*Settings!$B$15,2) -> 6.71 | AH40: Derived (C): Net_HP x 0.0486 diesel gal/bhp-hr x load factor 0.35/0.46/0.60 [USACE-EP] | AI40: =IF(OR(AC40="",AF40="",Settings!$B$5=""),"",ROUND(AC40-AF40*Settings!$B$5,2)) -> 332.3 | AJ40: B | AK40: C | AL40: Owned: USACE standby = 0.5 x DEPR + FCCM, max 40 hr/wk [USACE-EP]; with only an all-in rate use Caltrans delay factor x rate, max 8 hr/day & 40 hr/wk [CALT-2627]: HCETD factor 0.12. Rental: accrues by calendar period (no idle discount). FEMA: not eligible unless intermittent use [FEMA-PG]. | AM40: self-propelled | AP40: N | AQ40: =IFERROR(IF(AND(INDEX(Mob_Demob!$D$6:$D$14,MATCH(AM40,Mob_Demob!$A$6:$A$14,0))="",INDEX(Mob_Demob!$G$6:$G$14,MATCH(AM40,Mob_Demob!$A$6:$A$14,0))=""),"",ROUND(MAX(N(INDEX(Mob_Demob!$G$6:$G$14,MATCH(AM40,Mob_Demob!$A$6:$A$14,0))),N(INDEX(Mob_Demob!$D$6:$D$14,MATCH(AM40,Mob_Demob!$A$6:$A$14,0)))*Settings!$B$6)+IF(AP40="Y",N(INDEX(Mob_Demob!$I$6:$I$14,MATCH(AM40,Mob_Demob!$A$6:$A$14,0)))*Settings!$B$19,0)+N(INDEX(Mob_Demob!$L$6:$L$14,MATCH(AM40,Mob_Demob!$A$6:$A$14,0)))*N(INDEX(Mob_Demob!$K$6:$K$14,MATCH(AM40,Mob_Demob!$A$6:$A$14,0)))*Settings!$B$6+N(INDEX(Mob_Demob!$M$6:$M$14,MATCH(AM40,Mob_Demob!$A$6:$A$14,0)))*N(INDEX(Mob_Demob!$N$6:$N$14,MATCH(AM40,Mob_Demob!$A$6:$A$14,0))),0)),"") | AR40: =IF(AQ40="","",ROUND(AQ40*Settings!$B$18,0)) | AS40: EW-CUTLOAD,EW-TRENCH-5,EW-STRUCT | AT40: HP from taxonomy extract (owned_rates lists n/c). Travels on its own truck carrier. Fuel gal/hr derived (C): Net_HP x USACE fuel factor x load factor (Settings B11-B15). Ex-fuel (C) = FEMA incl-fuel rate - Fuel_gal_hr_med x diesel back-out price (Settings B5). | AU40: Needs rate (rental)
A41: EX-CLAM-10CY | B41: Earthwork | C41: Clamshell bucket (crane/cable) | D41: Cable clamshell | E41: Clamshell 1.0 CY | F41: Bucket | G41: 1.0 | H41: CY | L41: 1.0 CY | N41: none (attachment) | O41: None (non-operated item) | P41: day/wk/4wk | V41: bare | AA41: D | AB41: 8270 | AE41: 0 | AF41: 0 | AG41: 0 | AH41: No engine (towed / attachment / non-powered) | AJ41: D | AK41: D | AL41: Owned: USACE standby = 0.5 x DEPR + FCCM, max 40 hr/wk [USACE-EP]; with only an all-in rate use Caltrans delay factor x rate, max 8 hr/day & 40 hr/wk [CALT-2627]: no class factor captured, use 0.10-0.22 band (inference). Rental: accrues by calendar period. FEMA: not eligible unless intermittent use [FEMA-PG]. | AM41: flatbed | AP41: N | AQ41: =IFERROR(IF(AND(INDEX(Mob_Demob!$D$6:$D$14,MATCH(AM41,Mob_Demob!$A$6:$A$14,0))="",INDEX(Mob_Demob!$G$6:$G$14,MATCH(AM41,Mob_Demob!$A$6:$A$14,0))=""),"",ROUND(MAX(N(INDEX(Mob_Demob!$G$6:$G$14,MATCH(AM41,Mob_Demob!$A$6:$A$14,0))),N(INDEX(Mob_Demob!$D$6:$D$14,MATCH(AM41,Mob_Demob!$A$6:$A$14,0)))*Settings!$B$6)+IF(AP41="Y",N(INDEX(Mob_Demob!$I$6:$I$14,MATCH(AM41,Mob_Demob!$A$6:$A$14,0)))*Settings!$B$19,0)+N(INDEX(Mob_Demob!$L$6:$L$14,MATCH(AM41,Mob_Demob!$A$6:$A$14,0)))*N(INDEX(Mob_Demob!$K$6:$K$14,MATCH(AM41,Mob_Demob!$A$6:$A$14,0)))*Settings!$B$6+N(INDEX(Mob_Demob!$M$6:$M$14,MATCH(AM41,Mob_Demob!$A$6:$A$14,0)))*N(INDEX(Mob_Demob!$N$6:$N$14,MATCH(AM41,Mob_Demob!$A$6:$A$14,0))),0)),"") -> 400 | AR41: =IF(AQ41="","",ROUND(AQ41*Settings!$B$18,0)) -> 400 | AT41: FEMA 8270: Code listed in taxonomy; rate not captured in owned-rate notes. | AU41: Needs rate; Needs rate (rental); Needs rate (owned; FEMA code exists)
A42: EX-CLAM-3-4CY | B42: Earthwork | C42: Clamshell bucket (crane/cable) | D42: Cable clamshell | E42: Clamshell 3-4 CY | F42: Bucket | G42: 3-4 | H42: CY | L42: 3-4 CY | N42: none (attachment) | O42: None (non-operated item) | P42: day/wk/4wk | V42: bare | AA42: D | AB42: 8271 | AE42: 0 | AF42: 0 | AG42: 0 | AH42: No engine (towed / attachment / non-powered) | AJ42: D | AK42: D | AL42: Owned: USACE standby = 0.5 x DEPR + FCCM, max 40 hr/wk [USACE-EP]; with only an all-in rate use Caltrans delay factor x rate, max 8 hr/day & 40 hr/wk [CALT-2627]: no class factor captured, use 0.10-0.22 band (inference). Rental: accrues by calendar period. FEMA: not eligible unless intermittent use [FEMA-PG]. | AM42: flatbed | AP42: N | AQ42: =IFERROR(IF(AND(INDEX(Mob_Demob!$D$6:$D$14,MATCH(AM42,Mob_Demob!$A$6:$A$14,0))="",INDEX(Mob_Demob!$G$6:$G$14,MATCH(AM42,Mob_Demob!$A$6:$A$14,0))=""),"",ROUND(MAX(N(INDEX(Mob_Demob!$G$6:$G$14,MATCH(AM42,Mob_Demob!$A$6:$A$14,0))),N(INDEX(Mob_Demob!$D$6:$D$14,MATCH(AM42,Mob_Demob!$A$6:$A$14,0)))*Settings!$B$6)+IF(AP42="Y",N(INDEX(Mob_Demob!$I$6:$I$14,MATCH(AM42,Mob_Demob!$A$6:$A$14,0)))*Settings!$B$19,0)+N(INDEX(Mob_Demob!$L$6:$L$14,MATCH(AM42,Mob_Demob!$A$6:$A$14,0)))*N(INDEX(Mob_Demob!$K$6:$K$14,MATCH(AM42,Mob_Demob!$A$6:$A$14,0)))*Settings!$B$6+N(INDEX(Mob_Demob!$M$6:$M$14,MATCH(AM42,Mob_Demob!$A$6:$A$14,0)))*N(INDEX(Mob_Demob!$N$6:$N$14,MATCH(AM42,Mob_Demob!$A$6:$A$14,0))),0)),"") -> 400 | AR42: =IF(AQ42="","",ROUND(AQ42*Settings!$B$18,0)) -> 400 | AT42: FEMA 8271: Code listed in taxonomy; rate not captured in owned-rate notes. | AU42: Needs rate; Needs rate (rental); Needs rate (owned; FEMA code exists)
A43: EX-CLAM-5CY | B43: Earthwork | C43: Clamshell bucket (crane/cable) | D43: Cable clamshell | E43: Clamshell 5 CY | F43: Bucket | G43: 5 | H43: CY | L43: 5 CY | N43: none (attachment) | O43: None (non-operated item) | P43: day/wk/4wk | V43: bare | AA43: D | AB43: 8272 | AE43: 0 | AF43: 0 | AG43: 0 | AH43: No engine (towed / attachment / non-powered) | AJ43: D | AK43: D | AL43: Owned: USACE standby = 0.5 x DEPR + FCCM, max 40 hr/wk [USACE-EP]; with only an all-in rate use Caltrans delay factor x rate, max 8 hr/day & 40 hr/wk [CALT-2627]: no class factor captured, use 0.10-0.22 band (inference). Rental: accrues by calendar period. FEMA: not eligible unless intermittent use [FEMA-PG]. | AM43: flatbed | AP43: N | AQ43: =IFERROR(IF(AND(INDEX(Mob_Demob!$D$6:$D$14,MATCH(AM43,Mob_Demob!$A$6:$A$14,0))="",INDEX(Mob_Demob!$G$6:$G$14,MATCH(AM43,Mob_Demob!$A$6:$A$14,0))=""),"",ROUND(MAX(N(INDEX(Mob_Demob!$G$6:$G$14,MATCH(AM43,Mob_Demob!$A$6:$A$14,0))),N(INDEX(Mob_Demob!$D$6:$D$14,MATCH(AM43,Mob_Demob!$A$6:$A$14,0)))*Settings!$B$6)+IF(AP43="Y",N(INDEX(Mob_Demob!$I$6:$I$14,MATCH(AM43,Mob_Demob!$A$6:$A$14,0)))*Settings!$B$19,0)+N(INDEX(Mob_Demob!$L$6:$L$14,MATCH(AM43,Mob_Demob!$A$6:$A$14,0)))*N(INDEX(Mob_Demob!$K$6:$K$14,MATCH(AM43,Mob_Demob!$A$6:$A$14,0)))*Settings!$B$6+N(INDEX(Mob_Demob!$M$6:$M$14,MATCH(AM43,Mob_Demob!$A$6:$A$14,0)))*N(INDEX(Mob_Demob!$N$6:$N$14,MATCH(AM43,Mob_Demob!$A$6:$A$14,0))),0)),"") -> 400 | AR43: =IF(AQ43="","",ROUND(AQ43*Settings!$B$18,0)) -> 400 | AT43: FEMA 8272: Code listed in taxonomy; rate not captured in owned-rate notes. | AU43: Needs rate; Needs rate (rental); Needs rate (owned; FEMA code exists)
A44: EX-CLAM-75CY | B44: Earthwork | C44: Clamshell bucket (crane/cable) | D44: Cable clamshell | E44: Clamshell 7.5 CY | F44: Bucket | G44: 7.5 | H44: CY | L44: 7.5 CY | N44: none (attachment) | O44: None (non-operated item) | P44: day/wk/4wk | V44: bare | AA44: D | AB44: 8273 | AE44: 0 | AF44: 0 | AG44: 0 | AH44: No engine (towed / attachment / non-powered) | AJ44: D | AK44: D | AL44: Owned: USACE standby = 0.5 x DEPR + FCCM, max 40 hr/wk [USACE-EP]; with only an all-in rate use Caltrans delay factor x rate, max 8 hr/day & 40 hr/wk [CALT-2627]: no class factor captured, use 0.10-0.22 band (inference). Rental: accrues by calendar period. FEMA: not eligible unless intermittent use [FEMA-PG]. | AM44: flatbed | AP44: N | AQ44: =IFERROR(IF(AND(INDEX(Mob_Demob!$D$6:$D$14,MATCH(AM44,Mob_Demob!$A$6:$A$14,0))="",INDEX(Mob_Demob!$G$6:$G$14,MATCH(AM44,Mob_Demob!$A$6:$A$14,0))=""),"",ROUND(MAX(N(INDEX(Mob_Demob!$G$6:$G$14,MATCH(AM44,Mob_Demob!$A$6:$A$14,0))),N(INDEX(Mob_Demob!$D$6:$D$14,MATCH(AM44,Mob_Demob!$A$6:$A$14,0)))*Settings!$B$6)+IF(AP44="Y",N(INDEX(Mob_Demob!$I$6:$I$14,MATCH(AM44,Mob_Demob!$A$6:$A$14,0)))*Settings!$B$19,0)+N(INDEX(Mob_Demob!$L$6:$L$14,MATCH(AM44,Mob_Demob!$A$6:$A$14,0)))*N(INDEX(Mob_Demob!$K$6:$K$14,MATCH(AM44,Mob_Demob!$A$6:$A$14,0)))*Settings!$B$6+N(INDEX(Mob_Demob!$M$6:$M$14,MATCH(AM44,Mob_Demob!$A$6:$A$14,0)))*N(INDEX(Mob_Demob!$N$6:$N$14,MATCH(AM44,Mob_Demob!$A$6:$A$14,0))),0)),"") -> 400 | AR44: =IF(AQ44="","",ROUND(AQ44*Settings!$B$18,0)) -> 400 | AT44: FEMA 8273: Code listed in taxonomy; rate not captured in owned-rate notes. | AU44: Needs rate; Needs rate (rental); Needs rate (owned; FEMA code exists)
A45: EX-DRAG-2CY | B45: Earthwork | C45: Dragline bucket (crane/cable) | D45: Cable dragline | E45: Dragline 2 CY | F45: Bucket | G45: 2 | H45: CY | L45: 2 CY | N45: none (attachment) | O45: None (non-operated item) | P45: day/wk/4wk | V45: bare | AA45: D | AB45: 8275 | AE45: 0 | AF45: 0 | AG45: 0 | AH45: No engine (towed / attachment / non-powered) | AJ45: D | AK45: D | AL45: Owned: USACE standby = 0.5 x DEPR + FCCM, max 40 hr/wk [USACE-EP]; with only an all-in rate use Caltrans delay factor x rate, max 8 hr/day & 40 hr/wk [CALT-2627]: no class factor captured, use 0.10-0.22 band (inference). Rental: accrues by calendar period. FEMA: not eligible unless intermittent use [FEMA-PG]. | AM45: flatbed | AP45: N | AQ45: =IFERROR(IF(AND(INDEX(Mob_Demob!$D$6:$D$14,MATCH(AM45,Mob_Demob!$A$6:$A$14,0))="",INDEX(Mob_Demob!$G$6:$G$14,MATCH(AM45,Mob_Demob!$A$6:$A$14,0))=""),"",ROUND(MAX(N(INDEX(Mob_Demob!$G$6:$G$14,MATCH(AM45,Mob_Demob!$A$6:$A$14,0))),N(INDEX(Mob_Demob!$D$6:$D$14,MATCH(AM45,Mob_Demob!$A$6:$A$14,0)))*Settings!$B$6)+IF(AP45="Y",N(INDEX(Mob_Demob!$I$6:$I$14,MATCH(AM45,Mob_Demob!$A$6:$A$14,0)))*Settings!$B$19,0)+N(INDEX(Mob_Demob!$L$6:$L$14,MATCH(AM45,Mob_Demob!$A$6:$A$14,0)))*N(INDEX(Mob_Demob!$K$6:$K$14,MATCH(AM45,Mob_Demob!$A$6:$A$14,0)))*Settings!$B$6+N(INDEX(Mob_Demob!$M$6:$M$14,MATCH(AM45,Mob_Demob!$A$6:$A$14,0)))*N(INDEX(Mob_Demob!$N$6:$N$14,MATCH(AM45,Mob_Demob!$A$6:$A$14,0))),0)),"") -> 400 | AR45: =IF(AQ45="","",ROUND(AQ45*Settings!$B$18,0)) -> 400 | AT45: FEMA 8275: Code listed in taxonomy; rate not captured in owned-rate notes. | AU45: Needs rate; Needs rate (rental); Needs rate (owned; FEMA code exists)
A46: EX-DRAG-5CY | B46: Earthwork | C46: Dragline bucket (crane/cable) | D46: Cable dragline | E46: Dragline 5 CY | F46: Bucket | G46: 5 | H46: CY | L46: 5 CY | N46: none (attachment) | O46: None (non-operated item) | P46: day/wk/4wk | V46: bare | AA46: D | AB46: 8276 | AE46: 0 | AF46: 0 | AG46: 0 | AH46: No engine (towed / attachment / non-powered) | AJ46: D | AK46: D | AL46: Owned: USACE standby = 0.5 x DEPR + FCCM, max 40 hr/wk [USACE-EP]; with only an all-in rate use Caltrans delay factor x rate, max 8 hr/day & 40 hr/wk [CALT-2627]: no class factor captured, use 0.10-0.22 band (inference). Rental: accrues by calendar period. FEMA: not eligible unless intermittent use [FEMA-PG]. | AM46: flatbed | AP46: N | AQ46: =IFERROR(IF(AND(INDEX(Mob_Demob!$D$6:$D$14,MATCH(AM46,Mob_Demob!$A$6:$A$14,0))="",INDEX(Mob_Demob!$G$6:$G$14,MATCH(AM46,Mob_Demob!$A$6:$A$14,0))=""),"",ROUND(MAX(N(INDEX(Mob_Demob!$G$6:$G$14,MATCH(AM46,Mob_Demob!$A$6:$A$14,0))),N(INDEX(Mob_Demob!$D$6:$D$14,MATCH(AM46,Mob_Demob!$A$6:$A$14,0)))*Settings!$B$6)+IF(AP46="Y",N(INDEX(Mob_Demob!$I$6:$I$14,MATCH(AM46,Mob_Demob!$A$6:$A$14,0)))*Settings!$B$19,0)+N(INDEX(Mob_Demob!$L$6:$L$14,MATCH(AM46,Mob_Demob!$A$6:$A$14,0)))*N(INDEX(Mob_Demob!$K$6:$K$14,MATCH(AM46,Mob_Demob!$A$6:$A$14,0)))*Settings!$B$6+N(INDEX(Mob_Demob!$M$6:$M$14,MATCH(AM46,Mob_Demob!$A$6:$A$14,0)))*N(INDEX(Mob_Demob!$N$6:$N$14,MATCH(AM46,Mob_Demob!$A$6:$A$14,0))),0)),"") -> 400 | AR46: =IF(AQ46="","",ROUND(AQ46*Settings!$B$18,0)) -> 400 | AT46: FEMA 8276: Code listed in taxonomy; rate not captured in owned-rate notes. | AU46: Needs rate; Needs rate (rental); Needs rate (owned; FEMA code exists)
A47: EX-DRAG-10CY | B47: Earthwork | C47: Dragline bucket (crane/cable) | D47: Cable dragline | E47: Dragline 10 CY | F47: Bucket | G47: 10 | H47: CY | L47: 10 CY | N47: none (attachment) | O47: None (non-operated item) | P47: day/wk/4wk | V47: bare | AA47: D | AB47: 8277 | AE47: 0 | AF47: 0 | AG47: 0 | AH47: No engine (towed / attachment / non-powered) | AJ47: D | AK47: D | AL47: Owned: USACE standby = 0.5 x DEPR + FCCM, max 40 hr/wk [USACE-EP]; with only an all-in rate use Caltrans delay factor x rate, max 8 hr/day & 40 hr/wk [CALT-2627]: no class factor captured, use 0.10-0.22 band (inference). Rental: accrues by calendar period. FEMA: not eligible unless intermittent use [FEMA-PG]. | AM47: flatbed | AP47: N | AQ47: =IFERROR(IF(AND(INDEX(Mob_Demob!$D$6:$D$14,MATCH(AM47,Mob_Demob!$A$6:$A$14,0))="",INDEX(Mob_Demob!$G$6:$G$14,MATCH(AM47,Mob_Demob!$A$6:$A$14,0))=""),"",ROUND(MAX(N(INDEX(Mob_Demob!$G$6:$G$14,MATCH(AM47,Mob_Demob!$A$6:$A$14,0))),N(INDEX(Mob_Demob!$D$6:$D$14,MATCH(AM47,Mob_Demob!$A$6:$A$14,0)))*Settings!$B$6)+IF(AP47="Y",N(INDEX(Mob_Demob!$I$6:$I$14,MATCH(AM47,Mob_Demob!$A$6:$A$14,0)))*Settings!$B$19,0)+N(INDEX(Mob_Demob!$L$6:$L$14,MATCH(AM47,Mob_Demob!$A$6:$A$14,0)))*N(INDEX(Mob_Demob!$K$6:$K$14,MATCH(AM47,Mob_Demob!$A$6:$A$14,0)))*Settings!$B$6+N(INDEX(Mob_Demob!$M$6:$M$14,MATCH(AM47,Mob_Demob!$A$6:$A$14,0)))*N(INDEX(Mob_Demob!$N$6:$N$14,MATCH(AM47,Mob_Demob!$A$6:$A$14,0))),0)),"") -> 400 | AR47: =IF(AQ47="","",ROUND(AQ47*Settings!$B$18,0)) -> 400 | AT47: FEMA 8277: Code listed in taxonomy; rate not captured in owned-rate notes. | AU47: Needs rate; Needs rate (rental); Needs rate (owned; FEMA code exists)
A48: EX-DRAG-14CY | B48: Earthwork | C48: Dragline bucket (crane/cable) | D48: Cable dragline | E48: Dragline 14 CY | F48: Bucket | G48: 14 | H48: CY | L48: 14 CY | N48: none (attachment) | O48: None (non-operated item) | P48: day/wk/4wk | V48: bare | AA48: D | AB48: 8278 | AE48: 0 | AF48: 0 | AG48: 0 | AH48: No engine (towed / attachment / non-powered) | AJ48: D | AK48: D | AL48: Owned: USACE standby = 0.5 x DEPR + FCCM, max 40 hr/wk [USACE-EP]; with only an all-in rate use Caltrans delay factor x rate, max 8 hr/day & 40 hr/wk [CALT-2627]: no class factor captured, use 0.10-0.22 band (inference). Rental: accrues by calendar period. FEMA: not eligible unless intermittent use [FEMA-PG]. | AM48: flatbed | AP48: N | AQ48: =IFERROR(IF(AND(INDEX(Mob_Demob!$D$6:$D$14,MATCH(AM48,Mob_Demob!$A$6:$A$14,0))="",INDEX(Mob_Demob!$G$6:$G$14,MATCH(AM48,Mob_Demob!$A$6:$A$14,0))=""),"",ROUND(MAX(N(INDEX(Mob_Demob!$G$6:$G$14,MATCH(AM48,Mob_Demob!$A$6:$A$14,0))),N(INDEX(Mob_Demob!$D$6:$D$14,MATCH(AM48,Mob_Demob!$A$6:$A$14,0)))*Settings!$B$6)+IF(AP48="Y",N(INDEX(Mob_Demob!$I$6:$I$14,MATCH(AM48,Mob_Demob!$A$6:$A$14,0)))*Settings!$B$19,0)+N(INDEX(Mob_Demob!$L$6:$L$14,MATCH(AM48,Mob_Demob!$A$6:$A$14,0)))*N(INDEX(Mob_Demob!$K$6:$K$14,MATCH(AM48,Mob_Demob!$A$6:$A$14,0)))*Settings!$B$6+N(INDEX(Mob_Demob!$M$6:$M$14,MATCH(AM48,Mob_Demob!$A$6:$A$14,0)))*N(INDEX(Mob_Demob!$N$6:$N$14,MATCH(AM48,Mob_Demob!$A$6:$A$14,0))),0)),"") -> 400 | AR48: =IF(AQ48="","",ROUND(AQ48*Settings!$B$18,0)) -> 400 | AT48: FEMA 8278: Code listed in taxonomy; rate not captured in owned-rate notes. | AU48: Needs rate; Needs rate (rental); Needs rate (owned; FEMA code exists)
A49: BH-415 | B49: Earthwork | C49: Backhoe loader | D49: Center-pivot, compact | E49: Cat 415 class (69 hp) | F49: Net HP | G49: 69 | H49: hp | I49: Cat 415 IL (69 hp, 17,637 lb) | J49: 17637 | K49: 69 | N49: diesel | O49: Operating Engineer - light/compact group (per WD) | P49: day/wk/4wk | Q49: 491 | R49: 1424 | S49: 4129 | V49: bare | Y49: W25 | Z49: 2025 | AA49: B | AE49: =ROUND(K49*Settings!$B$11*Settings!$B$13,2) -> 1.17 | AF49: =ROUND(K49*Settings!$B$11*Settings!$B$14,2) -> 1.54 | AG49: =ROUND(K49*Settings!$B$11*Settings!$B$15,2) -> 2.01 | AH49: Derived (C): Net_HP x 0.0486 diesel gal/bhp-hr x load factor 0.35/0.46/0.60 [USACE-EP] | AJ49: D | AK49: D | AL49: Owned: USACE standby = 0.5 x DEPR + FCCM, max 40 hr/wk [USACE-EP]; with only an all-in rate use Caltrans delay factor x rate, max 8 hr/day & 40 hr/wk [CALT-2627]: LDRRT factor 0.11 (book) / 0.10 (interim). Rental: accrues by calendar period (no idle discount). FEMA: not eligible unless intermittent use [FEMA-PG]. | AM49: tilt-trailer | AN49: 17637 | AP49: N | AQ49: =IFERROR(IF(AND(INDEX(Mob_Demob!$D$6:$D$14,MATCH(AM49,Mob_Demob!$A$6:$A$14,0))="",INDEX(Mob_Demob!$G$6:$G$14,MATCH(AM49,Mob_Demob!$A$6:$A$14,0))=""),"",ROUND(MAX(N(INDEX(Mob_Demob!$G$6:$G$14,MATCH(AM49,Mob_Demob!$A$6:$A$14,0))),N(INDEX(Mob_Demob!$D$6:$D$14,MATCH(AM49,Mob_Demob!$A$6:$A$14,0)))*Settings!$B$6)+IF(AP49="Y",N(INDEX(Mob_Demob!$I$6:$I$14,MATCH(AM49,Mob_Demob!$A$6:$A$14,0)))*Settings!$B$19,0)+N(INDEX(Mob_Demob!$L$6:$L$14,MATCH(AM49,Mob_Demob!$A$6:$A$14,0)))*N(INDEX(Mob_Demob!$K$6:$K$14,MATCH(AM49,Mob_Demob!$A$6:$A$14,0)))*Settings!$B$6+N(INDEX(Mob_Demob!$M$6:$M$14,MATCH(AM49,Mob_Demob!$A$6:$A$14,0)))*N(INDEX(Mob_Demob!$N$6:$N$14,MATCH(AM49,Mob_Demob!$A$6:$A$14,0))),0)),"") -> 500 | AR49: =IF(AQ49="","",ROUND(AQ49*Settings!$B$18,0)) -> 500 | AS49: EW-TRENCH-5,EW-BACKFILL,EW-LOAD-TRK | AT49: Rent: Wheeler only. Fuel gal/hr derived (C): Net_HP x USACE fuel factor x load factor (Settings B11-B15). | AU49: Non-monotonic vs BH-STD-14FT - source data; Needs rate (owned)
A50: BH-STD-14FT | B50: Earthwork | C50: Backhoe loader | D50: Center-pivot, standard | E50: Standard 14-15 ft dig (90-103 hp) | F50: Max dig depth | G50: 14 | H50: ft | I50: Cat 416/420/420 XE (24,251 lb, 92-103 hp); Case 580SN; 90-99 hp class | J50: 24251 | K50: 103 | L50: 0.87 CY loader bucket (Case 580 per FEMA 8401); Bucket 1.25 yd3 typ (Cat 420 loader MP bucket 1.25 yd3) | N50: diesel | O50: Operating Engineer - light/compact group (per WD) | P50: day/wk/4wk | Q50: 500 | R50: 1250 | S50: 3735 | T50: 2750 | U50: 5209 | V50: bare | Y50: W25;B25;A26 | Z50: 2025-2026 | AA50: A | AB50: 8572 | AC50: 110.03 | AD50: FEMA 2025 | AE50: 1.16 | AF50: 1.46 | AG50: 1.77 | AH50: Cat VisionLink Dec 2022, model 420-07 [CATFUEL22] | AI50: =IF(OR(AC50="",AF50="",Settings!$B$5=""),"",ROUND(AC50-AF50*Settings!$B$5,2)) -> 104.69 | AJ50: B | AK50: C | AL50: Owned: USACE standby = 0.5 x DEPR + FCCM, max 40 hr/wk [USACE-EP]; with only an all-in rate use Caltrans delay factor x rate, max 8 hr/day & 40 hr/wk [CALT-2627]: LDRRT factor 0.11 (book) / 0.10 (interim). Rental: accrues by calendar period (no idle discount). FEMA: not eligible unless intermittent use [FEMA-PG]. | AM50: lowboy-legal | AN50: 24251 | AP50: N | AQ50: =IFERROR(IF(AND(INDEX(Mob_Demob!$D$6:$D$14,MATCH(AM50,Mob_Demob!$A$6:$A$14,0))="",INDEX(Mob_Demob!$G$6:$G$14,MATCH(AM50,Mob_Demob!$A$6:$A$14,0))=""),"",ROUND(MAX(N(INDEX(Mob_Demob!$G$6:$G$14,MATCH(AM50,Mob_Demob!$A$6:$A$14,0))),N(INDEX(Mob_Demob!$D$6:$D$14,MATCH(AM50,Mob_Demob!$A$6:$A$14,0)))*Settings!$B$6)+IF(AP50="Y",N(INDEX(Mob_Demob!$I$6:$I$14,MATCH(AM50,Mob_Demob!$A$6:$A$14,0)))*Settings!$B$19,0)+N(INDEX(Mob_Demob!$L$6:$L$14,MATCH(AM50,Mob_Demob!$A$6:$A$14,0)))*N(INDEX(Mob_Demob!$K$6:$K$14,MATCH(AM50,Mob_Demob!$A$6:$A$14,0)))*Settings!$B$6+N(INDEX(Mob_Demob!$M$6:$M$14,MATCH(AM50,Mob_Demob!$A$6:$A$14,0)))*N(INDEX(Mob_Demob!$N$6:$N$14,MATCH(AM50,Mob_Demob!$A$6:$A$14,0))),0)),"") -> 550 | AR50: =IF(AQ50="","",ROUND(AQ50*Settings!$B$18,0)) -> 550 | AS50: EW-TRENCH-5,EW-STRUCT,EW-BACKFILL,EW-LOAD-TRK,UT-PIPE-WATER | AT50: Weight is max operating weight (Ziegler). Cat 420: 91 hp net, loader MP bucket 1.25 yd3, 14 ft std dig; travel F 3.7/5.8/12/25 mph [CAT-420]. Hoe bucket capacity not published (trench/structural rows stay D). Rent: Median of 3 sources (W 420 619/1796/5209; B Case 580SN 415/1245/3735; A 90-99 hp 500/1250/2750). Ex-fuel (C) = FEMA incl-fuel rate - Fuel_gal_hr_med x diesel back-out price (Settings B5).
A51: BH-CASE580-80HP | B51: Earthwork | C51: Backhoe loader | D51: Center-pivot, standard (FEMA 8401) | E51: Case 580 Super L (80 hp, 0.87 CY) | F51: Net HP | G51: 80 | H51: hp | I51: Case 580 Super L | K51: 80 | L51: 0.87 CY; Bucket 0.87 yd3 typ (Case 580 Super L 0.87 CY (FEMA 8401)) | N51: diesel | O51: Operating Engineer - light/compact group (per WD) | P51: day/wk/4wk | V51: bare | AA51: D | AB51: 8401 | AC51: 92.56 | AD51: FEMA 2025 | AE51: =ROUND(K51*Settings!$B$11*Settings!$B$13,2) -> 1.36 | AF51: =ROUND(K51*Settings!$B$11*Settings!$B$14,2) -> 1.79 | AG51: =ROUND(K51*Settings!$B$11*Settings!$B$15,2) -> 2.33 | AH51: Derived (C): Net_HP x 0.0486 diesel gal/bhp-hr x load factor 0.35/0.46/0.60 [USACE-EP] | AI51: =IF(OR(AC51="",AF51="",Settings!$B$5=""),"",ROUND(AC51-AF51*Settings!$B$5,2)) -> 86.01 | AJ51: B | AK51: C | AL51: Owned: USACE standby = 0.5 x DEPR + FCCM, max 40 hr/wk [USACE-EP]; with only an all-in rate use Caltrans delay factor x rate, max 8 hr/day & 40 hr/wk [CALT-2627]: LDRRT factor 0.11 (book) / 0.10 (interim). Rental: accrues by calendar period (no idle discount). FEMA: not eligible unless intermittent use [FEMA-PG]. | AM51: lowboy-legal | AP51: maybe | AQ51: =IFERROR(IF(AND(INDEX(Mob_Demob!$D$6:$D$14,MATCH(AM51,Mob_Demob!$A$6:$A$14,0))="",INDEX(Mob_Demob!$G$6:$G$14,MATCH(AM51,Mob_Demob!$A$6:$A$14,0))=""),"",ROUND(MAX(N(INDEX(Mob_Demob!$G$6:$G$14,MATCH(AM51,Mob_Demob!$A$6:$A$14,0))),N(INDEX(Mob_Demob!$D$6:$D$14,MATCH(AM51,Mob_Demob!$A$6:$A$14,0)))*Settings!$B$6)+IF(AP51="Y",N(INDEX(Mob_Demob!$I$6:$I$14,MATCH(AM51,Mob_Demob!$A$6:$A$14,0)))*Settings!$B$19,0)+N(INDEX(Mob_Demob!$L$6:$L$14,MATCH(AM51,Mob_Demob!$A$6:$A$14,0)))*N(INDEX(Mob_Demob!$K$6:$K$14,MATCH(AM51,Mob_Demob!$A$6:$A$14,0)))*Settings!$B$6+N(INDEX(Mob_Demob!$M$6:$M$14,MATCH(AM51,Mob_Demob!$A$6:$A$14,0)))*N(INDEX(Mob_Demob!$N$6:$N$14,MATCH(AM51,Mob_Demob!$A$6:$A$14,0))),0)),"") -> 550 | AR51: =IF(AQ51="","",ROUND(AQ51*Settings!$B$18,0)) -> 550 | AS51: EW-TRENCH-5,EW-BACKFILL | AT51: Owned-rate row only; for rental use BH-STD-14FT. Fuel gal/hr derived (C): Net_HP x USACE fuel factor x load factor (Settings B11-B15). Ex-fuel (C) = FEMA incl-fuel rate - Fuel_gal_hr_med x diesel back-out price (Settings B5). | AU51: Non-monotonic vs BH-430 - source data; Needs rate (rental)
A52: BH-430 | B52: Earthwork | C52: Backhoe loader | D52: Center-pivot, extended | E52: Cat 430 class (107 hp, 15.1 ft dig) | F52: Max dig depth | G52: 15.1 | H52: ft | I52: Cat 430 | J52: 24251 | K52: 107 | N52: diesel | O52: Operating Engineer - light/compact group (per WD) | P52: day/wk/4wk | Q52: 684 | R52: 1982 | S52: 5749 | V52: bare | Y52: W25 | Z52: 2025 | AA52: B | AE52: 1.18 | AF52: 1.5 | AG52: 1.81 | AH52: Cat VisionLink Dec 2022, model 430-07 [CATFUEL22] | AJ52: D | AK52: D | AL52: Owned: USACE standby = 0.5 x DEPR + FCCM, max 40 hr/wk [USACE-EP]; with only an all-in rate use Caltrans delay factor x rate, max 8 hr/day & 40 hr/wk [CALT-2627]: LDRRT factor 0.11 (book) / 0.10 (interim). Rental: accrues by calendar period (no idle discount). FEMA: not eligible unless intermittent use [FEMA-PG]. | AM52: lowboy-legal | AN52: 24251 | AP52: N | AQ52: =IFERROR(IF(AND(INDEX(Mob_Demob!$D$6:$D$14,MATCH(AM52,Mob_Demob!$A$6:$A$14,0))="",INDEX(Mob_Demob!$G$6:$G$14,MATCH(AM52,Mob_Demob!$A$6:$A$14,0))=""),"",ROUND(MAX(N(INDEX(Mob_Demob!$G$6:$G$14,MATCH(AM52,Mob_Demob!$A$6:$A$14,0))),N(INDEX(Mob_Demob!$D$6:$D$14,MATCH(AM52,Mob_Demob!$A$6:$A$14,0)))*Settings!$B$6)+IF(AP52="Y",N(INDEX(Mob_Demob!$I$6:$I$14,MATCH(AM52,Mob_Demob!$A$6:$A$14,0)))*Settings!$B$19,0)+N(INDEX(Mob_Demob!$L$6:$L$14,MATCH(AM52,Mob_Demob!$A$6:$A$14,0)))*N(INDEX(Mob_Demob!$K$6:$K$14,MATCH(AM52,Mob_Demob!$A$6:$A$14,0)))*Settings!$B$6+N(INDEX(Mob_Demob!$M$6:$M$14,MATCH(AM52,Mob_Demob!$A$6:$A$14,0)))*N(INDEX(Mob_Demob!$N$6:$N$14,MATCH(AM52,Mob_Demob!$A$6:$A$14,0))),0)),"") -> 550 | AR52: =IF(AQ52="","",ROUND(AQ52*Settings!$B$18,0)) -> 550 | AS52: EW-TRENCH-5,EW-BACKFILL,EW-LOAD-TRK | AT52: Rent: Wheeler only. | AU52: Needs rate (owned)
A53: BH-440 | B53: Earthwork | C53: Backhoe loader | D53: Center-pivot, large | E53: Cat 440 class (104 hp, 29,321 lb) | F53: Net HP | G53: 104 | H53: hp | I53: Cat 440 | J53: 29321 | K53: 104 | N53: diesel | O53: Operating Engineer - light/compact group (per WD) | P53: day/wk/4wk | Q53: 927 | R53: 2688 | S53: 7796 | V53: bare | Y53: W25 | Z53: 2025 | AA53: B | AE53: 1.44 | AF53: 1.79 | AG53: 2.15 | AH53: Cat VisionLink Dec 2022, model 440-07 [CATFUEL22] | AJ53: D | AK53: D | AL53: Owned: USACE standby = 0.5 x DEPR + FCCM, max 40 hr/wk [USACE-EP]; with only an all-in rate use Caltrans delay factor x rate, max 8 hr/day & 40 hr/wk [CALT-2627]: LDRRT factor 0.11 (book) / 0.10 (interim). Rental: accrues by calendar period (no idle discount). FEMA: not eligible unless intermittent use [FEMA-PG]. | AM53: lowboy-legal | AN53: 29321 | AP53: N | AQ53: =IFERROR(IF(AND(INDEX(Mob_Demob!$D$6:$D$14,MATCH(AM53,Mob_Demob!$A$6:$A$14,0))="",INDEX(Mob_Demob!$G$6:$G$14,MATCH(AM53,Mob_Demob!$A$6:$A$14,0))=""),"",ROUND(MAX(N(INDEX(Mob_Demob!$G$6:$G$14,MATCH(AM53,Mob_Demob!$A$6:$A$14,0))),N(INDEX(Mob_Demob!$D$6:$D$14,MATCH(AM53,Mob_Demob!$A$6:$A$14,0)))*Settings!$B$6)+IF(AP53="Y",N(INDEX(Mob_Demob!$I$6:$I$14,MATCH(AM53,Mob_Demob!$A$6:$A$14,0)))*Settings!$B$19,0)+N(INDEX(Mob_Demob!$L$6:$L$14,MATCH(AM53,Mob_Demob!$A$6:$A$14,0)))*N(INDEX(Mob_Demob!$K$6:$K$14,MATCH(AM53,Mob_Demob!$A$6:$A$14,0)))*Settings!$B$6+N(INDEX(Mob_Demob!$M$6:$M$14,MATCH(AM53,Mob_Demob!$A$6:$A$14,0)))*N(INDEX(Mob_Demob!$N$6:$N$14,MATCH(AM53,Mob_Demob!$A$6:$A$14,0))),0)),"") -> 550 | AR53: =IF(AQ53="","",ROUND(AQ53*Settings!$B$18,0)) -> 550 | AS53: EW-TRENCH-5,EW-TRENCH-10,EW-BACKFILL,EW-LOAD-TRK | AT53: Rent: Wheeler only. | AU53: Needs rate (owned)
A54: BH-450 | B54: Earthwork | C54: Backhoe loader | D54: Center-pivot, large | E54: Cat 450 class (131 hp, 17 ft dig) | F54: Max dig depth | G54: 17 | H54: ft | I54: Cat 450 | J54: 29321 | K54: 131 | N54: diesel | O54: Operating Engineer - light/compact group (per WD) | P54: day/wk/4wk | V54: bare | AA54: D | AB54: 8573 | AE54: 1.47 | AF54: 1.83 | AG54: 2.2 | AH54: Cat VisionLink Dec 2022, model 450-07 [CATFUEL22] | AJ54: D | AK54: D | AL54: Owned: USACE standby = 0.5 x DEPR + FCCM, max 40 hr/wk [USACE-EP]; with only an all-in rate use Caltrans delay factor x rate, max 8 hr/day & 40 hr/wk [CALT-2627]: LDRRT factor 0.11 (book) / 0.10 (interim). Rental: accrues by calendar period (no idle discount). FEMA: not eligible unless intermittent use [FEMA-PG]. | AM54: lowboy-legal | AN54: 29321 | AP54: N | AQ54: =IFERROR(IF(AND(INDEX(Mob_Demob!$D$6:$D$14,MATCH(AM54,Mob_Demob!$A$6:$A$14,0))="",INDEX(Mob_Demob!$G$6:$G$14,MATCH(AM54,Mob_Demob!$A$6:$A$14,0))=""),"",ROUND(MAX(N(INDEX(Mob_Demob!$G$6:$G$14,MATCH(AM54,Mob_Demob!$A$6:$A$14,0))),N(INDEX(Mob_Demob!$D$6:$D$14,MATCH(AM54,Mob_Demob!$A$6:$A$14,0)))*Settings!$B$6)+IF(AP54="Y",N(INDEX(Mob_Demob!$I$6:$I$14,MATCH(AM54,Mob_Demob!$A$6:$A$14,0)))*Settings!$B$19,0)+N(INDEX(Mob_Demob!$L$6:$L$14,MATCH(AM54,Mob_Demob!$A$6:$A$14,0)))*N(INDEX(Mob_Demob!$K$6:$K$14,MATCH(AM54,Mob_Demob!$A$6:$A$14,0)))*Settings!$B$6+N(INDEX(Mob_Demob!$M$6:$M$14,MATCH(AM54,Mob_Demob!$A$6:$A$14,0)))*N(INDEX(Mob_Demob!$N$6:$N$14,MATCH(AM54,Mob_Demob!$A$6:$A$14,0))),0)),"") -> 550 | AR54: =IF(AQ54="","",ROUND(AQ54*Settings!$B$18,0)) -> 550 | AS54: EW-TRENCH-5,EW-TRENCH-10,EW-BACKFILL,EW-LOAD-TRK | AT54: FEMA 8573: FEMA rate not reliably extracted. | AU54: Needs rate; Needs rate (rental); Needs rate (owned; FEMA code exists)
A55: BH-SIDESHIFT | B55: Earthwork | C55: Backhoe loader | D55: Side-shift | E55: Side-shift 70-92 hp | F55: Net HP | G55: 92 | H55: hp | I55: Cat 428 (70 hp), 432 (92 hp), 434 (92 hp; 25,353 lb) | J55: 25353 | K55: 92 | N55: diesel | O55: Operating Engineer - light/compact group (per WD) | P55: day/wk/4wk | V55: bare | AA55: D | AE55: =ROUND(K55*Settings!$B$11*Settings!$B$13,2) -> 1.56 | AF55: =ROUND(K55*Settings!$B$11*Settings!$B$14,2) -> 2.06 | AG55: =ROUND(K55*Settings!$B$11*Settings!$B$15,2) -> 2.68 | AH55: Derived (C): Net_HP x 0.0486 diesel gal/bhp-hr x load factor 0.35/0.46/0.60 [USACE-EP] | AJ55: D | AK55: D | AL55: Owned: USACE standby = 0.5 x DEPR + FCCM, max 40 hr/wk [USACE-EP]; with only an all-in rate use Caltrans delay factor x rate, max 8 hr/day & 40 hr/wk [CALT-2627]: LDRRT factor 0.11 (book) / 0.10 (interim). Rental: accrues by calendar period (no idle discount). FEMA: not eligible unless intermittent use [FEMA-PG]. | AM55: lowboy-legal | AN55: 25353 | AP55: N | AQ55: =IFERROR(IF(AND(INDEX(Mob_Demob!$D$6:$D$14,MATCH(AM55,Mob_Demob!$A$6:$A$14,0))="",INDEX(Mob_Demob!$G$6:$G$14,MATCH(AM55,Mob_Demob!$A$6:$A$14,0))=""),"",ROUND(MAX(N(INDEX(Mob_Demob!$G$6:$G$14,MATCH(AM55,Mob_Demob!$A$6:$A$14,0))),N(INDEX(Mob_Demob!$D$6:$D$14,MATCH(AM55,Mob_Demob!$A$6:$A$14,0)))*Settings!$B$6)+IF(AP55="Y",N(INDEX(Mob_Demob!$I$6:$I$14,MATCH(AM55,Mob_Demob!$A$6:$A$14,0)))*Settings!$B$19,0)+N(INDEX(Mob_Demob!$L$6:$L$14,MATCH(AM55,Mob_Demob!$A$6:$A$14,0)))*N(INDEX(Mob_Demob!$K$6:$K$14,MATCH(AM55,Mob_Demob!$A$6:$A$14,0)))*Settings!$B$6+N(INDEX(Mob_Demob!$M$6:$M$14,MATCH(AM55,Mob_Demob!$A$6:$A$14,0)))*N(INDEX(Mob_Demob!$N$6:$N$14,MATCH(AM55,Mob_Demob!$A$6:$A$14,0))),0)),"") -> 550 | AR55: =IF(AQ55="","",ROUND(AQ55*Settings!$B$18,0)) -> 550 | AS55: EW-TRENCH-5,EW-BACKFILL | AT55: Representative 434. Fuel gal/hr derived (C): Net_HP x USACE fuel factor x load factor (Settings B11-B15). | AU55: Needs rate; Needs rate (rental); Needs rate (owned)
A56: WL-MINI-07Y | B56: Earthwork | C56: Wheel loader | D56: Compact (mini) | E56: 0.5-0.7 CY (~38 hp) | F56: Bucket | G56: 0.7 | H56: CY | I56: Gehl 280 | K56: 38 | L56: 0.5-0.7 CY; Bucket 0.6 yd3 typ (midpoint of 0.5-0.7 CY (Gehl 280, taxonomy)) | N56: diesel | O56: Operating Engineer - light/compact group (per WD) | P56: day/wk/4wk | V56: bare | AA56: D | AB56: 8390 | AC56: 42.33 | AD56: FEMA 2025 | AE56: =ROUND(K56*Settings!$B$11*Settings!$B$13,2) -> 0.65 | AF56: =ROUND(K56*Settings!$B$11*Settings!$B$14,2) -> 0.85 | AG56: =ROUND(K56*Settings!$B$11*Settings!$B$15,2) -> 1.11 | AH56: Derived (C): Net_HP x 0.0486 diesel gal/bhp-hr x load factor 0.35/0.46/0.60 [USACE-EP] | AI56: =IF(OR(AC56="",AF56="",Settings!$B$5=""),"",ROUND(AC56-AF56*Settings!$B$5,2)) -> 39.22 | AJ56: B | AK56: C | AL56: Owned: USACE standby = 0.5 x DEPR + FCCM, max 40 hr/wk [USACE-EP]; with only an all-in rate use Caltrans delay factor x rate, max 8 hr/day & 40 hr/wk [CALT-2627]: LDRRT factor 0.11 (book) / 0.10 (interim). Rental: accrues by calendar period (no idle discount). FEMA: not eligible unless intermittent use [FEMA-PG]. | AM56: tilt-trailer | AP56: N | AQ56: =IFERROR(IF(AND(INDEX(Mob_Demob!$D$6:$D$14,MATCH(AM56,Mob_Demob!$A$6:$A$14,0))="",INDEX(Mob_Demob!$G$6:$G$14,MATCH(AM56,Mob_Demob!$A$6:$A$14,0))=""),"",ROUND(MAX(N(INDEX(Mob_Demob!$G$6:$G$14,MATCH(AM56,Mob_Demob!$A$6:$A$14,0))),N(INDEX(Mob_Demob!$D$6:$D$14,MATCH(AM56,Mob_Demob!$A$6:$A$14,0)))*Settings!$B$6)+IF(AP56="Y",N(INDEX(Mob_Demob!$I$6:$I$14,MATCH(AM56,Mob_Demob!$A$6:$A$14,0)))*Settings!$B$19,0)+N(INDEX(Mob_Demob!$L$6:$L$14,MATCH(AM56,Mob_Demob!$A$6:$A$14,0)))*N(INDEX(Mob_Demob!$K$6:$K$14,MATCH(AM56,Mob_Demob!$A$6:$A$14,0)))*Settings!$B$6+N(INDEX(Mob_Demob!$M$6:$M$14,MATCH(AM56,Mob_Demob!$A$6:$A$14,0)))*N(INDEX(Mob_Demob!$N$6:$N$14,MATCH(AM56,Mob_Demob!$A$6:$A$14,0))),0)),"") -> 500 | AR56: =IF(AQ56="","",ROUND(AQ56*Settings!$B$18,0)) -> 500 | AS56: EW-LOAD-TRK,EW-STOCKPILE,EW-BACKFILL | AT56: Fuel gal/hr derived (C): Net_HP x USACE fuel factor x load factor (Settings B11-B15). Ex-fuel (C) = FEMA incl-fuel rate - Fuel_gal_hr_med x diesel back-out price (Settings B5). | AU56: Needs rate (rental)
A57: WL-COMPACT-1Y | B57: Earthwork | C57: Wheel loader | D57: Compact | E57: ~1-1.25 yd (~68-75 hp) | F57: Bucket | G57: 1 | H57: CY | I57: Cat 903/906/907/908 (74.7 hp, 12,628-14,617 lb, 1.0-2.0 yd); Bobcat L85; Kubota R630 | J57: 12628 | K57: 74.7 | L57: 1.0-1.25 CY; Bucket 1.125 yd3 typ (midpoint of 1.0-1.25 yd rental class (Cat 906 GP 1.0-1.7; Deere 244 P 1.0-1.4)) | N57: diesel | O57: Operating Engineer - light/compact group (per WD) | P57: day/wk/4wk | Q57: 400 | R57: 1200 | S57: 3240 | T57: 3000 | U57: 5209 | V57: bare | Y57: W25;B25;A26 | Z57: 2025-2026 | AA57: A | AB57: 8391 | AC57: 58.08 | AD57: FEMA 2025 | AE57: 0.57 | AF57: 0.75 | AG57: 0.92 | AH57: Cat VisionLink Dec 2022, model 906M [CATFUEL22] | AI57: =IF(OR(AC57="",AF57="",Settings!$B$5=""),"",ROUND(AC57-AF57*Settings!$B$5,2)) -> 55.34 | AJ57: B | AK57: C | AL57: Owned: USACE standby = 0.5 x DEPR + FCCM, max 40 hr/wk [USACE-EP]; with only an all-in rate use Caltrans delay factor x rate, max 8 hr/day & 40 hr/wk [CALT-2627]: LDRRT factor 0.11 (book) / 0.10 (interim). Rental: accrues by calendar period (no idle discount). FEMA: not eligible unless intermittent use [FEMA-PG]. | AM57: tilt-trailer | AN57: 12628 | AP57: N | AQ57: =IFERROR(IF(AND(INDEX(Mob_Demob!$D$6:$D$14,MATCH(AM57,Mob_Demob!$A$6:$A$14,0))="",INDEX(Mob_Demob!$G$6:$G$14,MATCH(AM57,Mob_Demob!$A$6:$A$14,0))=""),"",ROUND(MAX(N(INDEX(Mob_Demob!$G$6:$G$14,MATCH(AM57,Mob_Demob!$A$6:$A$14,0))),N(INDEX(Mob_Demob!$D$6:$D$14,MATCH(AM57,Mob_Demob!$A$6:$A$14,0)))*Settings!$B$6)+IF(AP57="Y",N(INDEX(Mob_Demob!$I$6:$I$14,MATCH(AM57,Mob_Demob!$A$6:$A$14,0)))*Settings!$B$19,0)+N(INDEX(Mob_Demob!$L$6:$L$14,MATCH(AM57,Mob_Demob!$A$6:$A$14,0)))*N(INDEX(Mob_Demob!$K$6:$K$14,MATCH(AM57,Mob_Demob!$A$6:$A$14,0)))*Settings!$B$6+N(INDEX(Mob_Demob!$M$6:$M$14,MATCH(AM57,Mob_Demob!$A$6:$A$14,0)))*N(INDEX(Mob_Demob!$N$6:$N$14,MATCH(AM57,Mob_Demob!$A$6:$A$14,0))),0)),"") -> 500 | AR57: =IF(AQ57="","",ROUND(AQ57*Settings!$B$18,0)) -> 500 | AS57: EW-LOAD-TRK,EW-STOCKPILE,EW-BACKFILL | AT57: Rent: Median of 3 sources (W 906 619/1796/5209; B 360/1080/3240; A 400/1200/3000). FEMA: FEMA 8391 Bobcat L85 (68 hp) mapped to this class by HP. Ex-fuel (C) = FEMA incl-fuel rate - Fuel_gal_hr_med x diesel back-out price (Settings B5).
A58: WL-COMPACT-2Y | B58: Earthwork | C58: Wheel loader | D58: Compact | E58: 2-2.5 yd (~110 hp) | F58: Bucket | G58: 2.25 | H58: CY | I58: Cat 910/914 (110 hp, 18,102-19,103 lb, 1.7-4.6 yd); Komatsu WA200 (2.5 yd); Develon DL200 | J58: 18102 | K58: 110 | L58: 2.0-2.5 CY; Bucket 2.25 yd3 typ (midpoint of 2.0-2.5 yd rental class (Deere 344 P 2.0-2.6)) | N58: diesel | O58: Operating Engineer - light/compact group (per WD) | P58: day/wk/4wk | Q58: 675 | R58: 1925 | S58: 4900 | T58: 4230 | U58: 6956 | V58: bare | Y58: W25;B25;C25;R25 | Z58: 2025-2026 | AA58: A | AB58: 8392 | AC58: 83.4 | AD58: FEMA 2025 | AE58: 0.96 | AF58: 1.16 | AG58: 1.36 | AH58: Cat VisionLink Dec 2022, model 910-14 [CATFUEL22] | AI58: =IF(OR(AC58="",AF58="",Settings!$B$5=""),"",ROUND(AC58-AF58*Settings!$B$5,2)) -> 79.15 | AJ58: B | AK58: C | AL58: Owned: USACE standby = 0.5 x DEPR + FCCM, max 40 hr/wk [USACE-EP]; with only an all-in rate use Caltrans delay factor x rate, max 8 hr/day & 40 hr/wk [CALT-2627]: LDRRT factor 0.11 (book) / 0.10 (interim). Rental: accrues by calendar period (no idle discount). FEMA: not eligible unless intermittent use [FEMA-PG]. | AM58: tilt-trailer | AN58: 18102 | AP58: N | AQ58: =IFERROR(IF(AND(INDEX(Mob_Demob!$D$6:$D$14,MATCH(AM58,Mob_Demob!$A$6:$A$14,0))="",INDEX(Mob_Demob!$G$6:$G$14,MATCH(AM58,Mob_Demob!$A$6:$A$14,0))=""),"",ROUND(MAX(N(INDEX(Mob_Demob!$G$6:$G$14,MATCH(AM58,Mob_Demob!$A$6:$A$14,0))),N(INDEX(Mob_Demob!$D$6:$D$14,MATCH(AM58,Mob_Demob!$A$6:$A$14,0)))*Settings!$B$6)+IF(AP58="Y",N(INDEX(Mob_Demob!$I$6:$I$14,MATCH(AM58,Mob_Demob!$A$6:$A$14,0)))*Settings!$B$19,0)+N(INDEX(Mob_Demob!$L$6:$L$14,MATCH(AM58,Mob_Demob!$A$6:$A$14,0)))*N(INDEX(Mob_Demob!$K$6:$K$14,MATCH(AM58,Mob_Demob!$A$6:$A$14,0)))*Settings!$B$6+N(INDEX(Mob_Demob!$M$6:$M$14,MATCH(AM58,Mob_Demob!$A$6:$A$14,0)))*N(INDEX(Mob_Demob!$N$6:$N$14,MATCH(AM58,Mob_Demob!$A$6:$A$14,0))),0)),"") -> 500 | AR58: =IF(AQ58="","",ROUND(AQ58*Settings!$B$18,0)) -> 500 | AS58: EW-LOAD-TRK,EW-STOCKPILE,EW-BACKFILL | AT58: Rent: Median of 4 sources (W 914 827/2399/6956; B 470/1410/4230; C 750/1850/4600; R 600/2000/5200). Ex-fuel (C) = FEMA incl-fuel rate - Fuel_gal_hr_med x diesel back-out price (Settings B5).
A59: WL-SMALL-3Y | B59: Earthwork | C59: Wheel loader | D59: Small | E59: 3-3.2 yd (~170 hp) | F59: Bucket | G59: 3 | H59: CY | I59: Cat 926 (170 hp, 27,972 lb, 3.0 yd), 930 (31,124 lb, 3.2 yd); Komatsu WA270 | J59: 27972 | K59: 170 | L59: 3.0-3.2 CY; Bucket 3.1 yd3 typ (midpoint of 3.0-3.2 yd rental class) | N59: diesel | O59: Operating Engineer - heavy equip. group (per WD) | P59: day/wk/4wk | Q59: 825 | R59: 2050 | S59: 5500 | T59: 5100 | U59: 8211 | V59: bare | Y59: W25;C25;A26 | Z59: 2025-2026 | AA59: A | AB59: 8393 | AC59: 116.74 | AD59: FEMA 2025 | AE59: 1.72 | AF59: 2.11 | AG59: 2.51 | AH59: Cat VisionLink Dec 2022, model 926M [CATFUEL22] | AI59: =IF(OR(AC59="",AF59="",Settings!$B$5=""),"",ROUND(AC59-AF59*Settings!$B$5,2)) -> 109.02 | AJ59: B | AK59: C | AL59: Owned: USACE standby = 0.5 x DEPR + FCCM, max 40 hr/wk [USACE-EP]; with only an all-in rate use Caltrans delay factor x rate, max 8 hr/day & 40 hr/wk [CALT-2627]: LDRRT factor 0.11 (book) / 0.10 (interim). Rental: accrues by calendar period (no idle discount). FEMA: not eligible unless intermittent use [FEMA-PG]. | AM59: lowboy-legal | AN59: 27972 | AP59: N | AQ59: =IFERROR(IF(AND(INDEX(Mob_Demob!$D$6:$D$14,MATCH(AM59,Mob_Demob!$A$6:$A$14,0))="",INDEX(Mob_Demob!$G$6:$G$14,MATCH(AM59,Mob_Demob!$A$6:$A$14,0))=""),"",ROUND(MAX(N(INDEX(Mob_Demob!$G$6:$G$14,MATCH(AM59,Mob_Demob!$A$6:$A$14,0))),N(INDEX(Mob_Demob!$D$6:$D$14,MATCH(AM59,Mob_Demob!$A$6:$A$14,0)))*Settings!$B$6)+IF(AP59="Y",N(INDEX(Mob_Demob!$I$6:$I$14,MATCH(AM59,Mob_Demob!$A$6:$A$14,0)))*Settings!$B$19,0)+N(INDEX(Mob_Demob!$L$6:$L$14,MATCH(AM59,Mob_Demob!$A$6:$A$14,0)))*N(INDEX(Mob_Demob!$K$6:$K$14,MATCH(AM59,Mob_Demob!$A$6:$A$14,0)))*Settings!$B$6+N(INDEX(Mob_Demob!$M$6:$M$14,MATCH(AM59,Mob_Demob!$A$6:$A$14,0)))*N(INDEX(Mob_Demob!$N$6:$N$14,MATCH(AM59,Mob_Demob!$A$6:$A$14,0))),0)),"") -> 550 | AR59: =IF(AQ59="","",ROUND(AQ59*Settings!$B$18,0)) -> 550 | AS59: EW-LOAD-TRK,EW-STOCKPILE,EW-BACKFILL | AT59: Rounded half-up (Excel rule) in revision; may differ by 1 from the notes table, which used banker's rounding. Rent: Median of 3 sources (W 926/930 avg 976/2831/8210; C 825/2050/5100; A 550/2000/5500). Ex-fuel (C) = FEMA incl-fuel rate - Fuel_gal_hr_med x diesel back-out price (Settings B5).
A60: WL-SMALL-4Y | B60: Earthwork | C60: Wheel loader | D60: Small | E60: 3.5-4.25 yd (~190-232 hp) | F60: Bucket | G60: 3.8 | H60: CY | I60: Cat 938 (191 hp, 35,528 lb, 3.8 yd); Komatsu WA320 (3.5)/WA380 (4.25); Deere 644K (4.2 CY) | J60: 35528 | K60: 191 | L60: 3.5-4.25 CY; Bucket 3.875 yd3 typ (midpoint of 3.5-4.25 yd rental class) | N60: diesel | O60: Operating Engineer - heavy equip. group (per WD) | P60: day/wk/4wk | Q60: 1088 | R60: 2700 | S60: 7000 | T60: 5700 | U60: 9884 | V60: bare | Y60: W25;C25;A26 | Z60: 2025-2026 | AA60: A | AB60: 8394 | AC60: 116.87 | AD60: FEMA 2025 | AE60: 1.9 | AF60: 2.36 | AG60: 2.82 | AH60: Cat VisionLink Dec 2022, model 938M [CATFUEL22] | AI60: =IF(OR(AC60="",AF60="",Settings!$B$5=""),"",ROUND(AC60-AF60*Settings!$B$5,2)) -> 108.23 | AJ60: B | AK60: C | AL60: Owned: USACE standby = 0.5 x DEPR + FCCM, max 40 hr/wk [USACE-EP]; with only an all-in rate use Caltrans delay factor x rate, max 8 hr/day & 40 hr/wk [CALT-2627]: LDRRT factor 0.11 (book) / 0.10 (interim). Rental: accrues by calendar period (no idle discount). FEMA: not eligible unless intermittent use [FEMA-PG]. | AM60: lowboy-legal | AN60: 35528 | AP60: N | AQ60: =IFERROR(IF(AND(INDEX(Mob_Demob!$D$6:$D$14,MATCH(AM60,Mob_Demob!$A$6:$A$14,0))="",INDEX(Mob_Demob!$G$6:$G$14,MATCH(AM60,Mob_Demob!$A$6:$A$14,0))=""),"",ROUND(MAX(N(INDEX(Mob_Demob!$G$6:$G$14,MATCH(AM60,Mob_Demob!$A$6:$A$14,0))),N(INDEX(Mob_Demob!$D$6:$D$14,MATCH(AM60,Mob_Demob!$A$6:$A$14,0)))*Settings!$B$6)+IF(AP60="Y",N(INDEX(Mob_Demob!$I$6:$I$14,MATCH(AM60,Mob_Demob!$A$6:$A$14,0)))*Settings!$B$19,0)+N(INDEX(Mob_Demob!$L$6:$L$14,MATCH(AM60,Mob_Demob!$A$6:$A$14,0)))*N(INDEX(Mob_Demob!$K$6:$K$14,MATCH(AM60,Mob_Demob!$A$6:$A$14,0)))*Settings!$B$6+N(INDEX(Mob_Demob!$M$6:$M$14,MATCH(AM60,Mob_Demob!$A$6:$A$14,0)))*N(INDEX(Mob_Demob!$N$6:$N$14,MATCH(AM60,Mob_Demob!$A$6:$A$14,0))),0)),"") -> 550 | AR60: =IF(AQ60="","",ROUND(AQ60*Settings!$B$18,0)) -> 550 | AS60: EW-LOAD-TRK,EW-STOCKPILE,EW-BACKFILL | AT60: Rent: Median of 3 sources (W 938 1175/3408/9884; C WA320/380 avg 1088/2700/6700; A 850/2500/7000). FEMA: FEMA 8394 Deere 644K (4.2 CY, 232 hp) mapped to this class by bucket. Ex-fuel (C) = FEMA incl-fuel rate - Fuel_gal_hr_med x diesel back-out price (Settings B5).
A61: WL-MED-45Y | B61: Earthwork | C61: Wheel loader | D61: Medium | E61: 4.5 yd (~225-250 hp) | F61: Bucket | G61: 4.5 | H61: CY | I61: Cat 950 GC (225 hp, 3.75-5.75 yd), 950 (249 hp, 42,461 lb) | J61: 42461 | K61: 249 | L61: 4.5 CY; Bucket 4.5 yd3 typ (4.5 yd (Wheeler Cat 950 rental line; cat.com 950 rated 4.1)) | N61: diesel | O61: Operating Engineer - heavy equip. group (per WD) | P61: day/wk/4wk | Q61: 1473 | R61: 4272 | S61: 12387 | V61: bare | Y61: W25 | Z61: 2025 | AA61: B | AB61: 8396 | AC61: 139.8 | AD61: FEMA 2025 | AE61: 2.38 | AF61: 3.02 | AG61: 3.66 | AH61: Cat VisionLink Dec 2022, model 950M [CATFUEL22] | AI61: =IF(OR(AC61="",AF61="",Settings!$B$5=""),"",ROUND(AC61-AF61*Settings!$B$5,2)) -> 128.75 | AJ61: B | AK61: C | AL61: Owned: USACE standby = 0.5 x DEPR + FCCM, max 40 hr/wk [USACE-EP]; with only an all-in rate use Caltrans delay factor x rate, max 8 hr/day & 40 hr/wk [CALT-2627]: LDRRT factor 0.11 (book) / 0.10 (interim). Rental: accrues by calendar period (no idle discount). FEMA: not eligible unless intermittent use [FEMA-PG]. | AM61: lowboy-legal | AN61: 42461 | AP61: N | AQ61: =IFERROR(IF(AND(INDEX(Mob_Demob!$D$6:$D$14,MATCH(AM61,Mob_Demob!$A$6:$A$14,0))="",INDEX(Mob_Demob!$G$6:$G$14,MATCH(AM61,Mob_Demob!$A$6:$A$14,0))=""),"",ROUND(MAX(N(INDEX(Mob_Demob!$G$6:$G$14,MATCH(AM61,Mob_Demob!$A$6:$A$14,0))),N(INDEX(Mob_Demob!$D$6:$D$14,MATCH(AM61,Mob_Demob!$A$6:$A$14,0)))*Settings!$B$6)+IF(AP61="Y",N(INDEX(Mob_Demob!$I$6:$I$14,MATCH(AM61,Mob_Demob!$A$6:$A$14,0)))*Settings!$B$19,0)+N(INDEX(Mob_Demob!$L$6:$L$14,MATCH(AM61,Mob_Demob!$A$6:$A$14,0)))*N(INDEX(Mob_Demob!$K$6:$K$14,MATCH(AM61,Mob_Demob!$A$6:$A$14,0)))*Settings!$B$6+N(INDEX(Mob_Demob!$M$6:$M$14,MATCH(AM61,Mob_Demob!$A$6:$A$14,0)))*N(INDEX(Mob_Demob!$N$6:$N$14,MATCH(AM61,Mob_Demob!$A$6:$A$14,0))),0)),"") -> 550 | AR61: =IF(AQ61="","",ROUND(AQ61*Settings!$B$18,0)) -> 550 | AS61: EW-LOAD-TRK,EW-STOCKPILE,EW-BACKFILL | AT61: Rent: Wheeler 950 (4.5 yd) only. Ex-fuel (C) = FEMA incl-fuel rate - Fuel_gal_hr_med x diesel back-out price (Settings B5).
A62: WL-MED-5Y | B62: Earthwork | C62: Wheel loader | D62: Medium | E62: 5-5.25 yd (~255-321 hp) | F62: Bucket | G62: 5.25 | H62: CY | I62: Cat 962/966 (321 hp, 51,124 lb, 5.25 yd); Case 921C (5 CY, 255 hp) | J62: 51124 | K62: 321 | L62: 5.0-5.25 CY; Bucket 5.25 yd3 typ (5.25 yd (Cat 966 rental line)) | N62: diesel | O62: Operating Engineer - heavy equip. group (per WD) | P62: day/wk/4wk | Q62: 2085 | R62: 6046 | S62: 17533 | V62: bare | Y62: W25 | Z62: 2025 | AA62: B | AB62: 8395 | AC62: 163.2 | AD62: FEMA 2025 | AE62: 3.08 | AF62: 3.88 | AG62: 4.69 | AH62: Cat VisionLink Dec 2022, model 966M [CATFUEL22] | AI62: =IF(OR(AC62="",AF62="",Settings!$B$5=""),"",ROUND(AC62-AF62*Settings!$B$5,2)) -> 149 | AJ62: B | AK62: C | AL62: Owned: USACE standby = 0.5 x DEPR + FCCM, max 40 hr/wk [USACE-EP]; with only an all-in rate use Caltrans delay factor x rate, max 8 hr/day & 40 hr/wk [CALT-2627]: LDRRT factor 0.11 (book) / 0.10 (interim). Rental: accrues by calendar period (no idle discount). FEMA: not eligible unless intermittent use [FEMA-PG]. | AM62: lowboy-legal | AN62: 51124 | AP62: maybe | AQ62: =IFERROR(IF(AND(INDEX(Mob_Demob!$D$6:$D$14,MATCH(AM62,Mob_Demob!$A$6:$A$14,0))="",INDEX(Mob_Demob!$G$6:$G$14,MATCH(AM62,Mob_Demob!$A$6:$A$14,0))=""),"",ROUND(MAX(N(INDEX(Mob_Demob!$G$6:$G$14,MATCH(AM62,Mob_Demob!$A$6:$A$14,0))),N(INDEX(Mob_Demob!$D$6:$D$14,MATCH(AM62,Mob_Demob!$A$6:$A$14,0)))*Settings!$B$6)+IF(AP62="Y",N(INDEX(Mob_Demob!$I$6:$I$14,MATCH(AM62,Mob_Demob!$A$6:$A$14,0)))*Settings!$B$19,0)+N(INDEX(Mob_Demob!$L$6:$L$14,MATCH(AM62,Mob_Demob!$A$6:$A$14,0)))*N(INDEX(Mob_Demob!$K$6:$K$14,MATCH(AM62,Mob_Demob!$A$6:$A$14,0)))*Settings!$B$6+N(INDEX(Mob_Demob!$M$6:$M$14,MATCH(AM62,Mob_Demob!$A$6:$A$14,0)))*N(INDEX(Mob_Demob!$N$6:$N$14,MATCH(AM62,Mob_Demob!$A$6:$A$14,0))),0)),"") -> 550 | AR62: =IF(AQ62="","",ROUND(AQ62*Settings!$B$18,0)) -> 550 | AS62: EW-LOAD-TRK,EW-STOCKPILE,EW-BACKFILL | AT62: Rent: Wheeler 966 (5.25 yd) only. FEMA: FEMA 8395 is a Case 921C (5 CY); fuel row is Cat 966M - different makes in one class. Ex-fuel (C) = FEMA incl-fuel rate - Fuel_gal_hr_med x diesel back-out price (Settings B5).
A63: WL-MED-972 | B63: Earthwork | C63: Wheel loader | D63: Medium | E63: Cat 972 class (~339 hp) | F63: Net HP | G63: 339 | H63: hp | I63: Cat 972 (339 hp, 54,858 lb) | J63: 54858 | K63: 339 | N63: diesel | O63: Operating Engineer - heavy equip. group (per WD) | P63: day/wk/4wk | Q63: 2236 | R63: 6484 | S63: 18803 | V63: bare | Y63: W25 | Z63: 2025 | AA63: B | AB63: 8397 | AC63: 188.93 | AD63: FEMA 2025 | AE63: 3.3 | AF63: 4.18 | AG63: 5.06 | AH63: Cat VisionLink Dec 2022, model 972M [CATFUEL22] | AI63: =IF(OR(AC63="",AF63="",Settings!$B$5=""),"",ROUND(AC63-AF63*Settings!$B$5,2)) -> 173.63 | AJ63: B | AK63: C | AL63: Owned: USACE standby = 0.5 x DEPR + FCCM, max 40 hr/wk [USACE-EP]; with only an all-in rate use Caltrans delay factor x rate, max 8 hr/day & 40 hr/wk [CALT-2627]: LDRRT factor 0.11 (book) / 0.10 (interim). Rental: accrues by calendar period (no idle discount). FEMA: not eligible unless intermittent use [FEMA-PG]. | AM63: lowboy-legal | AN63: 54858 | AP63: maybe | AQ63: =IFERROR(IF(AND(INDEX(Mob_Demob!$D$6:$D$14,MATCH(AM63,Mob_Demob!$A$6:$A$14,0))="",INDEX(Mob_Demob!$G$6:$G$14,MATCH(AM63,Mob_Demob!$A$6:$A$14,0))=""),"",ROUND(MAX(N(INDEX(Mob_Demob!$G$6:$G$14,MATCH(AM63,Mob_Demob!$A$6:$A$14,0))),N(INDEX(Mob_Demob!$D$6:$D$14,MATCH(AM63,Mob_Demob!$A$6:$A$14,0)))*Settings!$B$6)+IF(AP63="Y",N(INDEX(Mob_Demob!$I$6:$I$14,MATCH(AM63,Mob_Demob!$A$6:$A$14,0)))*Settings!$B$19,0)+N(INDEX(Mob_Demob!$L$6:$L$14,MATCH(AM63,Mob_Demob!$A$6:$A$14,0)))*N(INDEX(Mob_Demob!$K$6:$K$14,MATCH(AM63,Mob_Demob!$A$6:$A$14,0)))*Settings!$B$6+N(INDEX(Mob_Demob!$M$6:$M$14,MATCH(AM63,Mob_Demob!$A$6:$A$14,0)))*N(INDEX(Mob_Demob!$N$6:$N$14,MATCH(AM63,Mob_Demob!$A$6:$A$14,0))),0)),"") -> 550 | AR63: =IF(AQ63="","",ROUND(AQ63*Settings!$B$18,0)) -> 550 | AS63: EW-LOAD-TRK,EW-STOCKPILE,EW-BACKFILL | AT63: Rent: Wheeler only. Ex-fuel (C) = FEMA incl-fuel rate - Fuel_gal_hr_med x diesel back-out price (Settings B5).
A64: WL-MED-980 | B64: Earthwork | C64: Wheel loader | D64: Medium | E64: Cat 980 class (~420 hp, 5.75-7.5 yd) | F64: Net HP | G64: 420 | H64: hp | I64: Cat 980 / 980 GC | J64: 65610 | K64: 393 | L64: 5.75-7.5 CY (980 GC); Bucket 6.625 yd3 typ (midpoint of Cat 980 GC 5.75-7.5 yd3) | N64: diesel | O64: Operating Engineer - heavy equip. group (per WD) | P64: day/wk/4wk | Q64: 2719 | R64: 7886 | S64: 22869 | V64: bare | Y64: W25 | Z64: 2025 | AA64: B | AC64: =ROUND(AC63+(AC67-AC63)*(K64-K63)/(K67-K63),2) -> 223.06 | AD64: FEMA 2025 (interpolated) | AE64: 4.07 | AF64: 5.19 | AG64: 6.32 | AH64: Cat VisionLink Dec 2022, model 980M [CATFUEL22] | AI64: =IF(OR(AC64="",AF64="",Settings!$B$5=""),"",ROUND(AC64-AF64*Settings!$B$5,2)) -> 204.06 | AJ64: C | AK64: C | AL64: Owned: USACE standby = 0.5 x DEPR + FCCM, max 40 hr/wk [USACE-EP]; with only an all-in rate use Caltrans delay factor x rate, max 8 hr/day & 40 hr/wk [CALT-2627]: LDRRT factor 0.11 (book) / 0.10 (interim). Rental: accrues by calendar period (no idle discount). FEMA: not eligible unless intermittent use [FEMA-PG]. | AM64: lowboy-legal | AN64: 65610 | AP64: maybe | AQ64: =IFERROR(IF(AND(INDEX(Mob_Demob!$D$6:$D$14,MATCH(AM64,Mob_Demob!$A$6:$A$14,0))="",INDEX(Mob_Demob!$G$6:$G$14,MATCH(AM64,Mob_Demob!$A$6:$A$14,0))=""),"",ROUND(MAX(N(INDEX(Mob_Demob!$G$6:$G$14,MATCH(AM64,Mob_Demob!$A$6:$A$14,0))),N(INDEX(Mob_Demob!$D$6:$D$14,MATCH(AM64,Mob_Demob!$A$6:$A$14,0)))*Settings!$B$6)+IF(AP64="Y",N(INDEX(Mob_Demob!$I$6:$I$14,MATCH(AM64,Mob_Demob!$A$6:$A$14,0)))*Settings!$B$19,0)+N(INDEX(Mob_Demob!$L$6:$L$14,MATCH(AM64,Mob_Demob!$A$6:$A$14,0)))*N(INDEX(Mob_Demob!$K$6:$K$14,MATCH(AM64,Mob_Demob!$A$6:$A$14,0)))*Settings!$B$6+N(INDEX(Mob_Demob!$M$6:$M$14,MATCH(AM64,Mob_Demob!$A$6:$A$14,0)))*N(INDEX(Mob_Demob!$N$6:$N$14,MATCH(AM64,Mob_Demob!$A$6:$A$14,0))),0)),"") -> 550 | AR64: =IF(AQ64="","",ROUND(AQ64*Settings!$B$18,0)) -> 550 | AS64: EW-LOAD-TRK,EW-STOCKPILE,EW-BACKFILL | AT64: 980 GC: 393 hp, 65,610 lb; F 4.1/7.9/14/24.7 mph [CAT-WL-PG]. Rent: Wheeler only. Owned_rate_hr_incl_fuel interpolated (C) between WL-MED-972 and WL-LARGE-988 by Net HP (FEMA 2025 endpoints). Ex-fuel (C) = FEMA incl-fuel rate - Fuel_gal_hr_med x diesel back-out price (Settings B5).
A65: WL-MED-982 | B65: Earthwork | C65: Wheel loader | D65: Medium | E65: Cat 982 class (~432 hp) | F65: Net HP | G65: 432 | H65: hp | I65: Cat 982 | J65: 78264 | K65: 432 | N65: diesel | O65: Operating Engineer - heavy equip. group (per WD) | P65: day/wk/4wk | V65: bare | AA65: D | AC65: =ROUND(AC63+(AC67-AC63)*(K65-K63)/(K67-K63),2) -> 247.71 | AD65: FEMA 2025 (interpolated) | AE65: 4.49 | AF65: 5.77 | AG65: 7.04 | AH65: Cat VisionLink Dec 2022, model 982M [CATFUEL22] | AI65: =IF(OR(AC65="",AF65="",Settings!$B$5=""),"",ROUND(AC65-AF65*Settings!$B$5,2)) -> 226.59 | AJ65: C | AK65: C | AL65: Owned: USACE standby = 0.5 x DEPR + FCCM, max 40 hr/wk [USACE-EP]; with only an all-in rate use Caltrans delay factor x rate, max 8 hr/day & 40 hr/wk [CALT-2627]: LDRRT factor 0.11 (book) / 0.10 (interim). Rental: accrues by calendar period (no idle discount). FEMA: not eligible unless intermittent use [FEMA-PG]. | AM65: lowboy-permitted | AN65: 78264 | AP65: Y | AQ65: =IFERROR(IF(AND(INDEX(Mob_Demob!$D$6:$D$14,MATCH(AM65,Mob_Demob!$A$6:$A$14,0))="",INDEX(Mob_Demob!$G$6:$G$14,MATCH(AM65,Mob_Demob!$A$6:$A$14,0))=""),"",ROUND(MAX(N(INDEX(Mob_Demob!$G$6:$G$14,MATCH(AM65,Mob_Demob!$A$6:$A$14,0))),N(INDEX(Mob_Demob!$D$6:$D$14,MATCH(AM65,Mob_Demob!$A$6:$A$14,0)))*Settings!$B$6)+IF(AP65="Y",N(INDEX(Mob_Demob!$I$6:$I$14,MATCH(AM65,Mob_Demob!$A$6:$A$14,0)))*Settings!$B$19,0)+N(INDEX(Mob_Demob!$L$6:$L$14,MATCH(AM65,Mob_Demob!$A$6:$A$14,0)))*N(INDEX(Mob_Demob!$K$6:$K$14,MATCH(AM65,Mob_Demob!$A$6:$A$14,0)))*Settings!$B$6+N(INDEX(Mob_Demob!$M$6:$M$14,MATCH(AM65,Mob_Demob!$A$6:$A$14,0)))*N(INDEX(Mob_Demob!$N$6:$N$14,MATCH(AM65,Mob_Demob!$A$6:$A$14,0))),0)),"") -> 1800 | AR65: =IF(AQ65="","",ROUND(AQ65*Settings!$B$18,0)) -> 1800 | AS65: EW-LOAD-TRK,EW-STOCKPILE | AT65: Owned_rate_hr_incl_fuel interpolated (C) between WL-MED-972 and WL-LARGE-988 by Net HP (FEMA 2025 endpoints). Ex-fuel (C) = FEMA incl-fuel rate - Fuel_gal_hr_med x diesel back-out price (Settings B5). | AU65: Needs rate (rental)
A66: WL-LARGE-986 | B66: Earthwork | C66: Wheel loader | D66: Large | E66: Cat 986 class (~449 hp, 6.5-13.5 yd) | F66: Net HP | G66: 449 | H66: hp | I66: Cat 986 | J66: 97785 | K66: 449 | L66: 6.5-13.5 CY | N66: diesel | O66: Operating Engineer - heavy equip. group (per WD) | P66: day/wk/4wk | V66: bare | AA66: D | AC66: =ROUND(AC63+(AC67-AC63)*(K66-K63)/(K67-K63),2) -> 258.45 | AD66: FEMA 2025 (interpolated) | AE66: =ROUND(K66*Settings!$B$11*Settings!$B$13,2) -> 7.64 | AF66: =ROUND(K66*Settings!$B$11*Settings!$B$14,2) -> 10.04 | AG66: =ROUND(K66*Settings!$B$11*Settings!$B$15,2) -> 13.09 | AH66: Derived (C): Net_HP x 0.0486 diesel gal/bhp-hr x load factor 0.35/0.46/0.60 [USACE-EP] | AI66: =IF(OR(AC66="",AF66="",Settings!$B$5=""),"",ROUND(AC66-AF66*Settings!$B$5,2)) -> 221.7 | AJ66: C | AK66: C | AL66: Owned: USACE standby = 0.5 x DEPR + FCCM, max 40 hr/wk [USACE-EP]; with only an all-in rate use Caltrans delay factor x rate, max 8 hr/day & 40 hr/wk [CALT-2627]: LDRRT factor 0.11 (book) / 0.10 (interim). Rental: accrues by calendar period (no idle discount). FEMA: not eligible unless intermittent use [FEMA-PG]. | AM66: lowboy-permitted | AN66: 97785 | AP66: Y | AQ66: =IFERROR(IF(AND(INDEX(Mob_Demob!$D$6:$D$14,MATCH(AM66,Mob_Demob!$A$6:$A$14,0))="",INDEX(Mob_Demob!$G$6:$G$14,MATCH(AM66,Mob_Demob!$A$6:$A$14,0))=""),"",ROUND(MAX(N(INDEX(Mob_Demob!$G$6:$G$14,MATCH(AM66,Mob_Demob!$A$6:$A$14,0))),N(INDEX(Mob_Demob!$D$6:$D$14,MATCH(AM66,Mob_Demob!$A$6:$A$14,0)))*Settings!$B$6)+IF(AP66="Y",N(INDEX(Mob_Demob!$I$6:$I$14,MATCH(AM66,Mob_Demob!$A$6:$A$14,0)))*Settings!$B$19,0)+N(INDEX(Mob_Demob!$L$6:$L$14,MATCH(AM66,Mob_Demob!$A$6:$A$14,0)))*N(INDEX(Mob_Demob!$K$6:$K$14,MATCH(AM66,Mob_Demob!$A$6:$A$14,0)))*Settings!$B$6+N(INDEX(Mob_Demob!$M$6:$M$14,MATCH(AM66,Mob_Demob!$A$6:$A$14,0)))*N(INDEX(Mob_Demob!$N$6:$N$14,MATCH(AM66,Mob_Demob!$A$6:$A$14,0))),0)),"") -> 1800 | AR66: =IF(AQ66="","",ROUND(AQ66*Settings!$B$18,0)) -> 1800 | AS66: EW-LOAD-TRK,EW-STOCKPILE | AT66: Owned_rate_hr_incl_fuel interpolated (C) between WL-MED-972 and WL-LARGE-988 by Net HP (FEMA 2025 endpoints). Fuel gal/hr derived (C): Net_HP x USACE fuel factor x load factor (Settings B11-B15). Ex-fuel (C) = FEMA incl-fuel rate - Fuel_gal_hr_med x diesel back-out price (Settings B5). | AU66: Non-monotonic vs WL-LARGE-988 - source data; Needs rate (rental)
A67: WL-LARGE-988 | B67: Earthwork | C67: Wheel loader | D67: Large | E67: Cat 988 class (~580 hp, 6.2-17 yd) | F67: Net HP | G67: 580 | H67: hp | I67: Cat 988 | J67: 112574 | K67: 580 | L67: 6.2-17 CY | N67: diesel | O67: Operating Engineer - heavy equip. group (per WD) | P67: day/wk/4wk | V67: bare | AA67: D | AB67: 8398 | AC67: 341.25 | AD67: FEMA 2025 | AE67: 6.76 | AF67: 8.62 | AG67: 10.48 | AH67: Cat VisionLink Dec 2022, model 988K [CATFUEL22] | AI67: =IF(OR(AC67="",AF67="",Settings!$B$5=""),"",ROUND(AC67-AF67*Settings!$B$5,2)) -> 309.7 | AJ67: B | AK67: C | AL67: Owned: USACE standby = 0.5 x DEPR + FCCM, max 40 hr/wk [USACE-EP]; with only an all-in rate use Caltrans delay factor x rate, max 8 hr/day & 40 hr/wk [CALT-2627]: LDRRT factor 0.11 (book) / 0.10 (interim). Rental: accrues by calendar period (no idle discount). FEMA: not eligible unless intermittent use [FEMA-PG]. | AM67: multi-axle-heavy | AN67: 112574 | AP67: Y | AQ67: =IFERROR(IF(AND(INDEX(Mob_Demob!$D$6:$D$14,MATCH(AM67,Mob_Demob!$A$6:$A$14,0))="",INDEX(Mob_Demob!$G$6:$G$14,MATCH(AM67,Mob_Demob!$A$6:$A$14,0))=""),"",ROUND(MAX(N(INDEX(Mob_Demob!$G$6:$G$14,MATCH(AM67,Mob_Demob!$A$6:$A$14,0))),N(INDEX(Mob_Demob!$D$6:$D$14,MATCH(AM67,Mob_Demob!$A$6:$A$14,0)))*Settings!$B$6)+IF(AP67="Y",N(INDEX(Mob_Demob!$I$6:$I$14,MATCH(AM67,Mob_Demob!$A$6:$A$14,0)))*Settings!$B$19,0)+N(INDEX(Mob_Demob!$L$6:$L$14,MATCH(AM67,Mob_Demob!$A$6:$A$14,0)))*N(INDEX(Mob_Demob!$K$6:$K$14,MATCH(AM67,Mob_Demob!$A$6:$A$14,0)))*Settings!$B$6+N(INDEX(Mob_Demob!$M$6:$M$14,MATCH(AM67,Mob_Demob!$A$6:$A$14,0)))*N(INDEX(Mob_Demob!$N$6:$N$14,MATCH(AM67,Mob_Demob!$A$6:$A$14,0))),0)),"") -> 1913 | AR67: =IF(AQ67="","",ROUND(AQ67*Settings!$B$18,0)) -> 1913 | AS67: EW-LOAD-TRK,EW-STOCKPILE | AT67: Cat 988: 6.2-17 yd3 (17 = light material); rated payload 12.5 t face / 16 t loose; production left D (bucket range too wide for a typical) [CAT-WL-PG]. Ex-fuel (C) = FEMA incl-fuel rate - Fuel_gal_hr_med x diesel back-out price (Settings B5). | AU67: Needs rate (rental)
A68: WL-LARGE-990 | B68: Earthwork | C68: Wheel loader | D68: Large (quarry/mining) | E68: Cat 990 class (~786 hp) | F68: Net HP | G68: 786 | H68: hp | I68: Cat 990 | J68: 178517 | K68: 786 | N68: diesel | O68: Operating Engineer - heavy equip. group (per WD) | P68: day/wk/4wk | V68: bare | AA68: D | AE68: =ROUND(K68*Settings!$B$11*Settings!$B$13,2) -> 13.37 | AF68: =ROUND(K68*Settings!$B$11*Settings!$B$14,2) -> 17.57 | AG68: =ROUND(K68*Settings!$B$11*Settings!$B$15,2) -> 22.92 | AH68: Derived (C): Net_HP x 0.0486 diesel gal/bhp-hr x load factor 0.35/0.46/0.60 [USACE-EP] | AJ68: D | AK68: D | AL68: Owned: USACE standby = 0.5 x DEPR + FCCM, max 40 hr/wk [USACE-EP]; with only an all-in rate use Caltrans delay factor x rate, max 8 hr/day & 40 hr/wk [CALT-2627]: LDRRT factor 0.11 (book) / 0.10 (interim). Rental: accrues by calendar period (no idle discount). FEMA: not eligible unless intermittent use [FEMA-PG]. | AM68: multi-axle-heavy | AN68: 178517 | AP68: Y | AQ68: =IFERROR(IF(AND(INDEX(Mob_Demob!$D$6:$D$14,MATCH(AM68,Mob_Demob!$A$6:$A$14,0))="",INDEX(Mob_Demob!$G$6:$G$14,MATCH(AM68,Mob_Demob!$A$6:$A$14,0))=""),"",ROUND(MAX(N(INDEX(Mob_Demob!$G$6:$G$14,MATCH(AM68,Mob_Demob!$A$6:$A$14,0))),N(INDEX(Mob_Demob!$D$6:$D$14,MATCH(AM68,Mob_Demob!$A$6:$A$14,0)))*Settings!$B$6)+IF(AP68="Y",N(INDEX(Mob_Demob!$I$6:$I$14,MATCH(AM68,Mob_Demob!$A$6:$A$14,0)))*Settings!$B$19,0)+N(INDEX(Mob_Demob!$L$6:$L$14,MATCH(AM68,Mob_Demob!$A$6:$A$14,0)))*N(INDEX(Mob_Demob!$K$6:$K$14,MATCH(AM68,Mob_Demob!$A$6:$A$14,0)))*Settings!$B$6+N(INDEX(Mob_Demob!$M$6:$M$14,MATCH(AM68,Mob_Demob!$A$6:$A$14,0)))*N(INDEX(Mob_Demob!$N$6:$N$14,MATCH(AM68,Mob_Demob!$A$6:$A$14,0))),0)),"") -> 1913 | AR68: =IF(AQ68="","",ROUND(AQ68*Settings!$B$18,0)) -> 1913 | AS68: EW-LOAD-TRK | AT68: No FEMA row above 580 hp; not extrapolated. Cat 993/995 (mining) omitted. Fuel gal/hr derived (C): Net_HP x USACE fuel factor x load factor (Settings B11-B15). | AU68: Needs rate; Needs rate (rental); Needs rate (owned)
A69: WL-LARGE-992 | B69: Earthwork | C69: Wheel loader | D69: Large (quarry/mining) | E69: Cat 992 class (~814 hp) | F69: Net HP | G69: 814 | H69: hp | I69: Cat 992 | J69: 233430 | K69: 814 | L69: 15-32 CY | N69: diesel | O69: Operating Engineer - heavy equip. group (per WD) | P69: day/wk/4wk | V69: bare | AA69: D | AE69: =ROUND(K69*Settings!$B$11*Settings!$B$13,2) -> 13.85 | AF69: =ROUND(K69*Settings!$B$11*Settings!$B$14,2) -> 18.2 | AG69: =ROUND(K69*Settings!$B$11*Settings!$B$15,2) -> 23.74 | AH69: Derived (C): Net_HP x 0.0486 diesel gal/bhp-hr x load factor 0.35/0.46/0.60 [USACE-EP] | AJ69: D | AK69: D | AL69: Owned: USACE standby = 0.5 x DEPR + FCCM, max 40 hr/wk [USACE-EP]; with only an all-in rate use Caltrans delay factor x rate, max 8 hr/day & 40 hr/wk [CALT-2627]: LDRRT factor 0.11 (book) / 0.10 (interim). Rental: accrues by calendar period (no idle discount). FEMA: not eligible unless intermittent use [FEMA-PG]. | AM69: multi-axle-heavy | AN69: 233430 | AP69: Y | AQ69: =IFERROR(IF(AND(INDEX(Mob_Demob!$D$6:$D$14,MATCH(AM69,Mob_Demob!$A$6:$A$14,0))="",INDEX(Mob_Demob!$G$6:$G$14,MATCH(AM69,Mob_Demob!$A$6:$A$14,0))=""),"",ROUND(MAX(N(INDEX(Mob_Demob!$G$6:$G$14,MATCH(AM69,Mob_Demob!$A$6:$A$14,0))),N(INDEX(Mob_Demob!$D$6:$D$14,MATCH(AM69,Mob_Demob!$A$6:$A$14,0)))*Settings!$B$6)+IF(AP69="Y",N(INDEX(Mob_Demob!$I$6:$I$14,MATCH(AM69,Mob_Demob!$A$6:$A$14,0)))*Settings!$B$19,0)+N(INDEX(Mob_Demob!$L$6:$L$14,MATCH(AM69,Mob_Demob!$A$6:$A$14,0)))*N(INDEX(Mob_Demob!$K$6:$K$14,MATCH(AM69,Mob_Demob!$A$6:$A$14,0)))*Settings!$B$6+N(INDEX(Mob_Demob!$M$6:$M$14,MATCH(AM69,Mob_Demob!$A$6:$A$14,0)))*N(INDEX(Mob_Demob!$N$6:$N$14,MATCH(AM69,Mob_Demob!$A$6:$A$14,0))),0)),"") -> 1913 | AR69: =IF(AQ69="","",ROUND(AQ69*Settings!$B$18,0)) -> 1913 | AS69: EW-LOAD-TRK | AT69: No FEMA row above 580 hp; not extrapolated. Cat 993/995 (mining) omitted. Fuel gal/hr derived (C): Net_HP x USACE fuel factor x load factor (Settings B11-B15). | AU69: Needs rate; Needs rate (rental); Needs rate (owned)
A70: TL-CRAWL-963 | B70: Earthwork | C70: Track loader | D70: Crawler loader | E70: 3-3.2 CY (~178 hp) | F70: Bucket | G70: 3 | H70: CY | I70: Cat 963C | K70: 178 | L70: 3-3.2 CY; Bucket 3.1 yd3 typ (midpoint of Cat 963 3-3.2 CY) | N70: diesel | O70: Operating Engineer - heavy equip. group (per WD) | P70: day/wk/4wk | V70: bare | AA70: D | AB70: 8383 | AC70: 197.79 | AD70: FEMA 2025 | AE70: =ROUND(K70*Settings!$B$11*Settings!$B$13,2) -> 3.03 | AF70: =ROUND(K70*Settings!$B$11*Settings!$B$14,2) -> 3.98 | AG70: =ROUND(K70*Settings!$B$11*Settings!$B$15,2) -> 5.19 | AH70: Derived (C): Net_HP x 0.0486 diesel gal/bhp-hr x load factor 0.35/0.46/0.60 [USACE-EP] | AI70: =IF(OR(AC70="",AF70="",Settings!$B$5=""),"",ROUND(AC70-AF70*Settings!$B$5,2)) -> 183.22 | AJ70: B | AK70: C | AL70: Owned: USACE standby = 0.5 x DEPR + FCCM, max 40 hr/wk [USACE-EP]; with only an all-in rate use Caltrans delay factor x rate, max 8 hr/day & 40 hr/wk [CALT-2627]: LDRCL factor 0.11. Rental: accrues by calendar period (no idle discount). FEMA: not eligible unless intermittent use [FEMA-PG]. | AM70: lowboy-legal | AP70: maybe | AQ70: =IFERROR(IF(AND(INDEX(Mob_Demob!$D$6:$D$14,MATCH(AM70,Mob_Demob!$A$6:$A$14,0))="",INDEX(Mob_Demob!$G$6:$G$14,MATCH(AM70,Mob_Demob!$A$6:$A$14,0))=""),"",ROUND(MAX(N(INDEX(Mob_Demob!$G$6:$G$14,MATCH(AM70,Mob_Demob!$A$6:$A$14,0))),N(INDEX(Mob_Demob!$D$6:$D$14,MATCH(AM70,Mob_Demob!$A$6:$A$14,0)))*Settings!$B$6)+IF(AP70="Y",N(INDEX(Mob_Demob!$I$6:$I$14,MATCH(AM70,Mob_Demob!$A$6:$A$14,0)))*Settings!$B$19,0)+N(INDEX(Mob_Demob!$L$6:$L$14,MATCH(AM70,Mob_Demob!$A$6:$A$14,0)))*N(INDEX(Mob_Demob!$K$6:$K$14,MATCH(AM70,Mob_Demob!$A$6:$A$14,0)))*Settings!$B$6+N(INDEX(Mob_Demob!$M$6:$M$14,MATCH(AM70,Mob_Demob!$A$6:$A$14,0)))*N(INDEX(Mob_Demob!$N$6:$N$14,MATCH(AM70,Mob_Demob!$A$6:$A$14,0))),0)),"") -> 550 | AR70: =IF(AQ70="","",ROUND(AQ70*Settings!$B$18,0)) -> 550 | AS70: EW-LOAD-TRK,EW-BACKFILL | AT70: HP from taxonomy (FEMA cap 178). Fuel gal/hr derived (C): Net_HP x USACE fuel factor x load factor (Settings B11-B15). Ex-fuel (C) = FEMA incl-fuel rate - Fuel_gal_hr_med x diesel back-out price (Settings B5). | AU70: Needs rate (rental)
A71: TL-CRAWL-973 | B71: Earthwork | C71: Track loader | D71: Crawler loader | E71: 4-4.19 CY (~238 hp) | F71: Bucket | G71: 4 | H71: CY | I71: Cat 973C | K71: 238 | L71: 4-4.19 CY; Bucket 4.095 yd3 typ (midpoint of Cat 973 4-4.19 CY) | N71: diesel | O71: Operating Engineer - heavy equip. group (per WD) | P71: day/wk/4wk | V71: bare | AA71: D | AB71: 8384 | AC71: 254.71 | AD71: FEMA 2025 | AE71: =ROUND(K71*Settings!$B$11*Settings!$B$13,2) -> 4.05 | AF71: =ROUND(K71*Settings!$B$11*Settings!$B$14,2) -> 5.32 | AG71: =ROUND(K71*Settings!$B$11*Settings!$B$15,2) -> 6.94 | AH71: Derived (C): Net_HP x 0.0486 diesel gal/bhp-hr x load factor 0.35/0.46/0.60 [USACE-EP] | AI71: =IF(OR(AC71="",AF71="",Settings!$B$5=""),"",ROUND(AC71-AF71*Settings!$B$5,2)) -> 235.24 | AJ71: B | AK71: C | AL71: Owned: USACE standby = 0.5 x DEPR + FCCM, max 40 hr/wk [USACE-EP]; with only an all-in rate use Caltrans delay factor x rate, max 8 hr/day & 40 hr/wk [CALT-2627]: LDRCL factor 0.11. Rental: accrues by calendar period (no idle discount). FEMA: not eligible unless intermittent use [FEMA-PG]. | AM71: lowboy-permitted | AP71: Y | AQ71: =IFERROR(IF(AND(INDEX(Mob_Demob!$D$6:$D$14,MATCH(AM71,Mob_Demob!$A$6:$A$14,0))="",INDEX(Mob_Demob!$G$6:$G$14,MATCH(AM71,Mob_Demob!$A$6:$A$14,0))=""),"",ROUND(MAX(N(INDEX(Mob_Demob!$G$6:$G$14,MATCH(AM71,Mob_Demob!$A$6:$A$14,0))),N(INDEX(Mob_Demob!$D$6:$D$14,MATCH(AM71,Mob_Demob!$A$6:$A$14,0)))*Settings!$B$6)+IF(AP71="Y",N(INDEX(Mob_Demob!$I$6:$I$14,MATCH(AM71,Mob_Demob!$A$6:$A$14,0)))*Settings!$B$19,0)+N(INDEX(Mob_Demob!$L$6:$L$14,MATCH(AM71,Mob_Demob!$A$6:$A$14,0)))*N(INDEX(Mob_Demob!$K$6:$K$14,MATCH(AM71,Mob_Demob!$A$6:$A$14,0)))*Settings!$B$6+N(INDEX(Mob_Demob!$M$6:$M$14,MATCH(AM71,Mob_Demob!$A$6:$A$14,0)))*N(INDEX(Mob_Demob!$N$6:$N$14,MATCH(AM71,Mob_Demob!$A$6:$A$14,0))),0)),"") -> 1800 | AR71: =IF(AQ71="","",ROUND(AQ71*Settings!$B$18,0)) -> 1800 | AS71: EW-LOAD-TRK,EW-BACKFILL | AT71: Weight not in notes; transport assumed permitted (verify). Fuel gal/hr derived (C): Net_HP x USACE fuel factor x load factor (Settings B11-B15). Ex-fuel (C) = FEMA incl-fuel rate - Fuel_gal_hr_med x diesel back-out price (Settings B5). | AU71: Needs rate (rental)
A72: SS-WHEEL-MICRO | B72: Earthwork | C72: Skid steer / CTL | D72: Wheeled skid steer, micro | E72: ROC 700-1,099 lb (~24 hp) | F72: Rated operating capacity | G72: 900 | H72: lb | I72: Bobcat S70 | K72: 24 | L72: ROC 700-1,099 lb | N72: diesel | O72: Operating Engineer - light/compact group (per WD) | P72: day/wk/4wk | Q72: 230 | R72: 690 | S72: 2070 | V72: bare | Y72: B25 | Z72: Mar 2025 | AA72: B | AB72: 8540 | AC72: 31.67 | AD72: FEMA 2025 | AE72: =ROUND(K72*Settings!$B$11*Settings!$B$13,2) -> 0.41 | AF72: =ROUND(K72*Settings!$B$11*Settings!$B$14,2) -> 0.54 | AG72: =ROUND(K72*Settings!$B$11*Settings!$B$15,2) -> 0.7 | AH72: Derived (C): Net_HP x 0.0486 diesel gal/bhp-hr x load factor 0.35/0.46/0.60 [USACE-EP] | AI72: =IF(OR(AC72="",AF72="",Settings!$B$5=""),"",ROUND(AC72-AF72*Settings!$B$5,2)) -> 29.69 | AJ72: B | AK72: C | AL72: Owned: USACE standby = 0.5 x DEPR + FCCM, max 40 hr/wk [USACE-EP]; with only an all-in rate use Caltrans delay factor x rate, max 8 hr/day & 40 hr/wk [CALT-2627]: no class factor captured, use 0.10-0.22 band (inference). Rental: accrues by calendar period. FEMA: not eligible unless intermittent use [FEMA-PG]. | AM72: tilt-trailer | AP72: N | AQ72: =IFERROR(IF(AND(INDEX(Mob_Demob!$D$6:$D$14,MATCH(AM72,Mob_Demob!$A$6:$A$14,0))="",INDEX(Mob_Demob!$G$6:$G$14,MATCH(AM72,Mob_Demob!$A$6:$A$14,0))=""),"",ROUND(MAX(N(INDEX(Mob_Demob!$G$6:$G$14,MATCH(AM72,Mob_Demob!$A$6:$A$14,0))),N(INDEX(Mob_Demob!$D$6:$D$14,MATCH(AM72,Mob_Demob!$A$6:$A$14,0)))*Settings!$B$6)+IF(AP72="Y",N(INDEX(Mob_Demob!$I$6:$I$14,MATCH(AM72,Mob_Demob!$A$6:$A$14,0)))*Settings!$B$19,0)+N(INDEX(Mob_Demob!$L$6:$L$14,MATCH(AM72,Mob_Demob!$A$6:$A$14,0)))*N(INDEX(Mob_Demob!$K$6:$K$14,MATCH(AM72,Mob_Demob!$A$6:$A$14,0)))*Settings!$B$6+N(INDEX(Mob_Demob!$M$6:$M$14,MATCH(AM72,Mob_Demob!$A$6:$A$14,0)))*N(INDEX(Mob_Demob!$N$6:$N$14,MATCH(AM72,Mob_Demob!$A$6:$A$14,0))),0)),"") -> 500 | AR72: =IF(AQ72="","",ROUND(AQ72*Settings!$B$18,0)) -> 500 | AS72: EW-LOAD-TRK,EW-BACKFILL,EW-SPREAD-SSL | AT72: Rent: Burris only. Fuel gal/hr derived (C): Net_HP x USACE fuel factor x load factor (Settings B11-B15). Ex-fuel (C) = FEMA incl-fuel rate - Fuel_gal_hr_med x diesel back-out price (Settings B5).
A73: SS-WHEEL-SMALL | B73: Earthwork | C73: Skid steer / CTL | D73: Wheeled skid steer, small frame | E73: ROC <1,750 lb | F73: Rated operating capacity | G73: 1500 | H73: lb | I73: Cat 226D; Bobcat S450 (1,370 lb), S530 (1,750 lb); ~5,000-6,000 lb, ~50 hp | J73: 5500 | K73: 50 | L73: ROC 1,370-1,749 lb | N73: diesel | O73: Operating Engineer - light/compact group (per WD) | P73: day/wk/4wk | Q73: 230 | R73: 743 | S73: 2038 | T73: 1875 | U73: 3462 | V73: bare | Y73: W25;B25;R25;N25 | Z73: 2025-2026 | AA73: A | AF73: 2.46 | AH73: Cat Dec 2022 single value, 226D3-249D3 group [CATFUEL22] | AJ73: D | AK73: D | AL73: Owned: USACE standby = 0.5 x DEPR + FCCM, max 40 hr/wk [USACE-EP]; with only an all-in rate use Caltrans delay factor x rate, max 8 hr/day & 40 hr/wk [CALT-2627]: no class factor captured, use 0.10-0.22 band (inference). Rental: accrues by calendar period. FEMA: not eligible unless intermittent use [FEMA-PG]. | AM73: tilt-trailer | AN73: 5500 | AP73: N | AQ73: =IFERROR(IF(AND(INDEX(Mob_Demob!$D$6:$D$14,MATCH(AM73,Mob_Demob!$A$6:$A$14,0))="",INDEX(Mob_Demob!$G$6:$G$14,MATCH(AM73,Mob_Demob!$A$6:$A$14,0))=""),"",ROUND(MAX(N(INDEX(Mob_Demob!$G$6:$G$14,MATCH(AM73,Mob_Demob!$A$6:$A$14,0))),N(INDEX(Mob_Demob!$D$6:$D$14,MATCH(AM73,Mob_Demob!$A$6:$A$14,0)))*Settings!$B$6)+IF(AP73="Y",N(INDEX(Mob_Demob!$I$6:$I$14,MATCH(AM73,Mob_Demob!$A$6:$A$14,0)))*Settings!$B$19,0)+N(INDEX(Mob_Demob!$L$6:$L$14,MATCH(AM73,Mob_Demob!$A$6:$A$14,0)))*N(INDEX(Mob_Demob!$K$6:$K$14,MATCH(AM73,Mob_Demob!$A$6:$A$14,0)))*Settings!$B$6+N(INDEX(Mob_Demob!$M$6:$M$14,MATCH(AM73,Mob_Demob!$A$6:$A$14,0)))*N(INDEX(Mob_Demob!$N$6:$N$14,MATCH(AM73,Mob_Demob!$A$6:$A$14,0))),0)),"") -> 500 | AR73: =IF(AQ73="","",ROUND(AQ73*Settings!$B$18,0)) -> 500 | AS73: EW-LOAD-TRK,EW-BACKFILL,EW-SPREAD-SSL | AT73: Spec value 1,500 lb = mid of class; weight/HP are SkidSteers.com frame-class figures (5,000-6,000 lb, ~50 hp). Rounded half-up (Excel rule) in revision; may differ by 1 from the notes table, which used banker's rounding. Rent: Median of 4 sources (W 412/1194/3462; B 240/720/2160; R 185/675/1875; N 219/765/1915). | AU73: Needs rate (owned)
A74: SS-WHEEL-MED | B74: Earthwork | C74: Skid steer / CTL | D74: Wheeled skid steer, medium frame | E74: ROC 1,750-2,500 lb | F74: Rated operating capacity | G74: 2100 | H74: lb | I74: Bobcat S590/S64 (2,300), S595/S66 (2,400); Gehl SSV65; 6,000-7,000 lb, 50-70 hp | J74: 6500 | K74: 70 | L74: ROC 1,750-2,500 lb; Bucket 0.6 yd3 typ (62-68 in bucket 0.57-0.63 yd3 mapped to 1,750-2,200 lb ROC (notes mapping; midpoint)) | N74: diesel | O74: Operating Engineer - light/compact group (per WD) | P74: day/wk/4wk | Q74: 257 | R74: 838 | S74: 2310 | T74: 2250 | U74: 2500 | V74: bare | Y74: B25;R25;A26 | Z74: 2025-2026 | AA74: A | AF74: 2.62 | AH74: Cat Dec 2022 single value, 236D3-262D3 group [CATFUEL22] | AJ74: D | AK74: D | AL74: Owned: USACE standby = 0.5 x DEPR + FCCM, max 40 hr/wk [USACE-EP]; with only an all-in rate use Caltrans delay factor x rate, max 8 hr/day & 40 hr/wk [CALT-2627]: no class factor captured, use 0.10-0.22 band (inference). Rental: accrues by calendar period. FEMA: not eligible unless intermittent use [FEMA-PG]. | AM74: tilt-trailer | AN74: 6500 | AP74: N | AQ74: =IFERROR(IF(AND(INDEX(Mob_Demob!$D$6:$D$14,MATCH(AM74,Mob_Demob!$A$6:$A$14,0))="",INDEX(Mob_Demob!$G$6:$G$14,MATCH(AM74,Mob_Demob!$A$6:$A$14,0))=""),"",ROUND(MAX(N(INDEX(Mob_Demob!$G$6:$G$14,MATCH(AM74,Mob_Demob!$A$6:$A$14,0))),N(INDEX(Mob_Demob!$D$6:$D$14,MATCH(AM74,Mob_Demob!$A$6:$A$14,0)))*Settings!$B$6)+IF(AP74="Y",N(INDEX(Mob_Demob!$I$6:$I$14,MATCH(AM74,Mob_Demob!$A$6:$A$14,0)))*Settings!$B$19,0)+N(INDEX(Mob_Demob!$L$6:$L$14,MATCH(AM74,Mob_Demob!$A$6:$A$14,0)))*N(INDEX(Mob_Demob!$K$6:$K$14,MATCH(AM74,Mob_Demob!$A$6:$A$14,0)))*Settings!$B$6+N(INDEX(Mob_Demob!$M$6:$M$14,MATCH(AM74,Mob_Demob!$A$6:$A$14,0)))*N(INDEX(Mob_Demob!$N$6:$N$14,MATCH(AM74,Mob_Demob!$A$6:$A$14,0))),0)),"") -> 500 | AR74: =IF(AQ74="","",ROUND(AQ74*Settings!$B$18,0)) -> 500 | AS74: EW-LOAD-TRK,EW-BACKFILL,EW-SPREAD-SSL | AT74: Rent: Median of 3 sources (B 257/770/2310; R 225/838/2250; A 375/1200/2500). | AU74: Needs rate (owned)
A75: SS-WHEEL-LARGE | B75: Earthwork | C75: Skid steer / CTL | D75: Wheeled skid steer, large frame | E75: ROC 2,500-3,500 lb | F75: Rated operating capacity | G75: 3000 | H75: lb | I75: Cat 270 XE; Bobcat S650/S76 (2,900), S770 (3,350), S86 (3,400); Gehl SSV75; 7,000-10,000 lb, 70+ hp | J75: 8500 | K75: 74 | L75: ROC 2,500-3,500 lb; Bucket 0.69 yd3 typ (74 in bucket 0.69 yd3 mapped to 2,500-3,200 lb ROC (notes mapping)) | N75: diesel | O75: Operating Engineer - light/compact group (per WD) | P75: day/wk/4wk | Q75: 373 | R75: 1175 | S75: 2958 | T75: 2750 | U75: 6003 | V75: bare | Y75: W25;B25;R25;A26 | Z75: 2025-2026 | AA75: A | AB75: 8541 | AC75: 45.23 | AD75: FEMA 2025 | AF75: 3.3 | AH75: Cat Dec 2022 single value, 272D3/299D3 group [CATFUEL22] | AI75: =IF(OR(AC75="",AF75="",Settings!$B$5=""),"",ROUND(AC75-AF75*Settings!$B$5,2)) -> 33.15 | AJ75: B | AK75: C | AL75: Owned: USACE standby = 0.5 x DEPR + FCCM, max 40 hr/wk [USACE-EP]; with only an all-in rate use Caltrans delay factor x rate, max 8 hr/day & 40 hr/wk [CALT-2627]: no class factor captured, use 0.10-0.22 band (inference). Rental: accrues by calendar period. FEMA: not eligible unless intermittent use [FEMA-PG]. | AM75: tilt-trailer | AN75: 8500 | AP75: N | AQ75: =IFERROR(IF(AND(INDEX(Mob_Demob!$D$6:$D$14,MATCH(AM75,Mob_Demob!$A$6:$A$14,0))="",INDEX(Mob_Demob!$G$6:$G$14,MATCH(AM75,Mob_Demob!$A$6:$A$14,0))=""),"",ROUND(MAX(N(INDEX(Mob_Demob!$G$6:$G$14,MATCH(AM75,Mob_Demob!$A$6:$A$14,0))),N(INDEX(Mob_Demob!$D$6:$D$14,MATCH(AM75,Mob_Demob!$A$6:$A$14,0)))*Settings!$B$6)+IF(AP75="Y",N(INDEX(Mob_Demob!$I$6:$I$14,MATCH(AM75,Mob_Demob!$A$6:$A$14,0)))*Settings!$B$19,0)+N(INDEX(Mob_Demob!$L$6:$L$14,MATCH(AM75,Mob_Demob!$A$6:$A$14,0)))*N(INDEX(Mob_Demob!$K$6:$K$14,MATCH(AM75,Mob_Demob!$A$6:$A$14,0)))*Settings!$B$6+N(INDEX(Mob_Demob!$M$6:$M$14,MATCH(AM75,Mob_Demob!$A$6:$A$14,0)))*N(INDEX(Mob_Demob!$N$6:$N$14,MATCH(AM75,Mob_Demob!$A$6:$A$14,0))),0)),"") -> 500 | AR75: =IF(AQ75="","",ROUND(AQ75*Settings!$B$18,0)) -> 500 | AS75: EW-LOAD-TRK,EW-BACKFILL,EW-SPREAD-SSL | AT75: Rounded half-up (Excel rule) in revision; may differ by 1 from the notes table, which used banker's rounding. Rent: Median of 4 sources (W 714/2070/6003; B 350/1050/3150; R 273/1025/2767; A 395/1300/2750). FEMA: FEMA 8541 Bobcat S76 (~2,900 lb ROC, to 74 hp). Ex-fuel (C) = FEMA incl-fuel rate - Fuel_gal_hr_med x diesel back-out price (Settings B5).
A76: SS-WHEEL-XL | B76: Earthwork | C76: Skid steer / CTL | D76: Wheeled skid steer, large frame (high ROC) | E76: ROC 3,000-4,500 lb | F76: Rated operating capacity | G76: 3400 | H76: lb | I76: Bobcat S86 (3,400 lb ROC, to 105 hp) | K76: 105 | L76: ROC 3,000-4,499 lb | N76: diesel | O76: Operating Engineer - light/compact group (per WD) | P76: day/wk/4wk | Q76: 330 | R76: 1090 | S76: 3170 | T76: 3100 | U76: 3240 | V76: bare | Y76: B25;R25 | Z76: 2025-2026 | AA76: A | AB76: 8542 | AC76: 60.67 | AD76: FEMA 2025 | AF76: 3.3 | AH76: Cat Dec 2022 single value, 272D3/299D3 group [CATFUEL22] | AI76: =IF(OR(AC76="",AF76="",Settings!$B$5=""),"",ROUND(AC76-AF76*Settings!$B$5,2)) -> 48.59 | AJ76: B | AK76: C | AL76: Owned: USACE standby = 0.5 x DEPR + FCCM, max 40 hr/wk [USACE-EP]; with only an all-in rate use Caltrans delay factor x rate, max 8 hr/day & 40 hr/wk [CALT-2627]: no class factor captured, use 0.10-0.22 band (inference). Rental: accrues by calendar period. FEMA: not eligible unless intermittent use [FEMA-PG]. | AM76: tilt-trailer | AP76: N | AQ76: =IFERROR(IF(AND(INDEX(Mob_Demob!$D$6:$D$14,MATCH(AM76,Mob_Demob!$A$6:$A$14,0))="",INDEX(Mob_Demob!$G$6:$G$14,MATCH(AM76,Mob_Demob!$A$6:$A$14,0))=""),"",ROUND(MAX(N(INDEX(Mob_Demob!$G$6:$G$14,MATCH(AM76,Mob_Demob!$A$6:$A$14,0))),N(INDEX(Mob_Demob!$D$6:$D$14,MATCH(AM76,Mob_Demob!$A$6:$A$14,0)))*Settings!$B$6)+IF(AP76="Y",N(INDEX(Mob_Demob!$I$6:$I$14,MATCH(AM76,Mob_Demob!$A$6:$A$14,0)))*Settings!$B$19,0)+N(INDEX(Mob_Demob!$L$6:$L$14,MATCH(AM76,Mob_Demob!$A$6:$A$14,0)))*N(INDEX(Mob_Demob!$K$6:$K$14,MATCH(AM76,Mob_Demob!$A$6:$A$14,0)))*Settings!$B$6+N(INDEX(Mob_Demob!$M$6:$M$14,MATCH(AM76,Mob_Demob!$A$6:$A$14,0)))*N(INDEX(Mob_Demob!$N$6:$N$14,MATCH(AM76,Mob_Demob!$A$6:$A$14,0))),0)),"") -> 500 | AR76: =IF(AQ76="","",ROUND(AQ76*Settings!$B$18,0)) -> 500 | AS76: EW-LOAD-TRK,EW-BACKFILL,EW-SPREAD-SSL | AT76: Rent: Median (=mean) of 2 sources: B 3,000-4,499 lb 360/1080/3240; R S86 300/1100/3100. Overlaps SS-WHEEL-LARGE. Ex-fuel (C) = FEMA incl-fuel rate - Fuel_gal_hr_med x diesel back-out price (Settings B5).
A77: SS-MTL | B77: Earthwork | C77: Skid steer / CTL | D77: Mini track loader (stand-on) | E77: Mini track loader (~25 hp) | F77: Net HP | G77: 25 | H77: hp | I77: Bobcat MT100/MT120 | K77: 25 | N77: diesel | O77: Operating Engineer - light/compact group (per WD) | P77: day/wk/4wk | Q77: 250 | R77: 975 | S77: 2695 | V77: bare | Y77: R25 | Z77: Spring 2025 | AA77: B | AB77: 8380 | AC77: 36.92 | AD77: FEMA 2025 | AE77: =ROUND(K77*Settings!$B$11*Settings!$B$13,2) -> 0.43 | AF77: =ROUND(K77*Settings!$B$11*Settings!$B$14,2) -> 0.56 | AG77: =ROUND(K77*Settings!$B$11*Settings!$B$15,2) -> 0.73 | AH77: Derived (C): Net_HP x 0.0486 diesel gal/bhp-hr x load factor 0.35/0.46/0.60 [USACE-EP] | AI77: =IF(OR(AC77="",AF77="",Settings!$B$5=""),"",ROUND(AC77-AF77*Settings!$B$5,2)) -> 34.87 | AJ77: B | AK77: C | AL77: Owned: USACE standby = 0.5 x DEPR + FCCM, max 40 hr/wk [USACE-EP]; with only an all-in rate use Caltrans delay factor x rate, max 8 hr/day & 40 hr/wk [CALT-2627]: no class factor captured, use 0.10-0.22 band (inference). Rental: accrues by calendar period. FEMA: not eligible unless intermittent use [FEMA-PG]. | AM77: tilt-trailer | AP77: N | AQ77: =IFERROR(IF(AND(INDEX(Mob_Demob!$D$6:$D$14,MATCH(AM77,Mob_Demob!$A$6:$A$14,0))="",INDEX(Mob_Demob!$G$6:$G$14,MATCH(AM77,Mob_Demob!$A$6:$A$14,0))=""),"",ROUND(MAX(N(INDEX(Mob_Demob!$G$6:$G$14,MATCH(AM77,Mob_Demob!$A$6:$A$14,0))),N(INDEX(Mob_Demob!$D$6:$D$14,MATCH(AM77,Mob_Demob!$A$6:$A$14,0)))*Settings!$B$6)+IF(AP77="Y",N(INDEX(Mob_Demob!$I$6:$I$14,MATCH(AM77,Mob_Demob!$A$6:$A$14,0)))*Settings!$B$19,0)+N(INDEX(Mob_Demob!$L$6:$L$14,MATCH(AM77,Mob_Demob!$A$6:$A$14,0)))*N(INDEX(Mob_Demob!$K$6:$K$14,MATCH(AM77,Mob_Demob!$A$6:$A$14,0)))*Settings!$B$6+N(INDEX(Mob_Demob!$M$6:$M$14,MATCH(AM77,Mob_Demob!$A$6:$A$14,0)))*N(INDEX(Mob_Demob!$N$6:$N$14,MATCH(AM77,Mob_Demob!$A$6:$A$14,0))),0)),"") -> 500 | AR77: =IF(AQ77="","",ROUND(AQ77*Settings!$B$18,0)) -> 500 | AS77: EW-BACKFILL,EW-SPREAD-SSL | AT77: Rent: RTL MT100 only. Fuel gal/hr derived (C): Net_HP x USACE fuel factor x load factor (Settings B11-B15). Ex-fuel (C) = FEMA incl-fuel rate - Fuel_gal_hr_med x diesel back-out price (Settings B5).
A78: CTL-SMALL | B78: Earthwork | C78: Skid steer / CTL | D78: Compact track loader, small | E78: ROC <2,000 lb | F78: Rated operating capacity | G78: 1700 | H78: lb | I78: Cat 239; Bobcat T450 (1,500), T590 (1,900) | K78: 55 | L78: ROC <2,000 lb | N78: diesel | O78: Operating Engineer - light/compact group (per WD) | P78: day/wk/4wk | Q78: 372 | R78: 1288 | S78: 3198 | T78: 2795 | U78: 4542 | V78: bare | Y78: W25;R25;N25;A26 | Z78: 2025-2026 | AA78: A | AB78: 8381 | AC78: 41.49 | AD78: FEMA 2025 | AF78: 2.46 | AH78: Cat Dec 2022 single value, 226D3-249D3 group (incl. 239D3) [CATFUEL22] | AI78: =IF(OR(AC78="",AF78="",Settings!$B$5=""),"",ROUND(AC78-AF78*Settings!$B$5,2)) -> 32.49 | AJ78: B | AK78: C | AL78: Owned: USACE standby = 0.5 x DEPR + FCCM, max 40 hr/wk [USACE-EP]; with only an all-in rate use Caltrans delay factor x rate, max 8 hr/day & 40 hr/wk [CALT-2627]: no class factor captured, use 0.10-0.22 band (inference). Rental: accrues by calendar period. FEMA: not eligible unless intermittent use [FEMA-PG]. | AM78: tilt-trailer | AP78: N | AQ78: =IFERROR(IF(AND(INDEX(Mob_Demob!$D$6:$D$14,MATCH(AM78,Mob_Demob!$A$6:$A$14,0))="",INDEX(Mob_Demob!$G$6:$G$14,MATCH(AM78,Mob_Demob!$A$6:$A$14,0))=""),"",ROUND(MAX(N(INDEX(Mob_Demob!$G$6:$G$14,MATCH(AM78,Mob_Demob!$A$6:$A$14,0))),N(INDEX(Mob_Demob!$D$6:$D$14,MATCH(AM78,Mob_Demob!$A$6:$A$14,0)))*Settings!$B$6)+IF(AP78="Y",N(INDEX(Mob_Demob!$I$6:$I$14,MATCH(AM78,Mob_Demob!$A$6:$A$14,0)))*Settings!$B$19,0)+N(INDEX(Mob_Demob!$L$6:$L$14,MATCH(AM78,Mob_Demob!$A$6:$A$14,0)))*N(INDEX(Mob_Demob!$K$6:$K$14,MATCH(AM78,Mob_Demob!$A$6:$A$14,0)))*Settings!$B$6+N(INDEX(Mob_Demob!$M$6:$M$14,MATCH(AM78,Mob_Demob!$A$6:$A$14,0)))*N(INDEX(Mob_Demob!$N$6:$N$14,MATCH(AM78,Mob_Demob!$A$6:$A$14,0))),0)),"") -> 500 | AR78: =IF(AQ78="","",ROUND(AQ78*Settings!$B$18,0)) -> 500 | AS78: EW-LOAD-TRK,EW-BACKFILL,EW-SPREAD-SSL | AT78: Rent: Median of 4 sources (W 540/1566/4542; R 300/1325/3395; N 319/1115/2795; A 425/1250/3000). FEMA: FEMA 8381 Bobcat T450 (to 55 hp). Ex-fuel (C) = FEMA incl-fuel rate - Fuel_gal_hr_med x diesel back-out price (Settings B5).
A79: CTL-MED | B79: Earthwork | C79: Skid steer / CTL | D79: Compact track loader, medium | E79: ROC 2,000-3,000 lb | F79: Rated operating capacity | G79: 2500 | H79: lb | I79: Bobcat T550/T595/T650/T76; Takeuchi TL10; Kubota SVL65/75 | L79: ROC 2,000-3,000 lb; Bucket 0.69 yd3 typ (74 in bucket 0.69 yd3 mapped to 2,500-3,200 lb ROC (notes mapping)) | N79: diesel | O79: Operating Engineer - light/compact group (per WD) | P79: day/wk/4wk | Q79: 383 | R79: 1383 | S79: 3450 | T79: 3133 | U79: 4106 | V79: bare | Y79: B25;R25;N25;A26;C25 | Z79: 2025-2026 | AA79: A | AF79: 2.62 | AH79: Cat Dec 2022 single value, 259D3-289D3 group [CATFUEL22] | AJ79: D | AK79: D | AL79: Owned: USACE standby = 0.5 x DEPR + FCCM, max 40 hr/wk [USACE-EP]; with only an all-in rate use Caltrans delay factor x rate, max 8 hr/day & 40 hr/wk [CALT-2627]: no class factor captured, use 0.10-0.22 band (inference). Rental: accrues by calendar period. FEMA: not eligible unless intermittent use [FEMA-PG]. | AM79: tilt-trailer | AP79: N | AQ79: =IFERROR(IF(AND(INDEX(Mob_Demob!$D$6:$D$14,MATCH(AM79,Mob_Demob!$A$6:$A$14,0))="",INDEX(Mob_Demob!$G$6:$G$14,MATCH(AM79,Mob_Demob!$A$6:$A$14,0))=""),"",ROUND(MAX(N(INDEX(Mob_Demob!$G$6:$G$14,MATCH(AM79,Mob_Demob!$A$6:$A$14,0))),N(INDEX(Mob_Demob!$D$6:$D$14,MATCH(AM79,Mob_Demob!$A$6:$A$14,0)))*Settings!$B$6)+IF(AP79="Y",N(INDEX(Mob_Demob!$I$6:$I$14,MATCH(AM79,Mob_Demob!$A$6:$A$14,0)))*Settings!$B$19,0)+N(INDEX(Mob_Demob!$L$6:$L$14,MATCH(AM79,Mob_Demob!$A$6:$A$14,0)))*N(INDEX(Mob_Demob!$K$6:$K$14,MATCH(AM79,Mob_Demob!$A$6:$A$14,0)))*Settings!$B$6+N(INDEX(Mob_Demob!$M$6:$M$14,MATCH(AM79,Mob_Demob!$A$6:$A$14,0)))*N(INDEX(Mob_Demob!$N$6:$N$14,MATCH(AM79,Mob_Demob!$A$6:$A$14,0))),0)),"") -> 500 | AR79: =IF(AQ79="","",ROUND(AQ79*Settings!$B$18,0)) -> 500 | AS79: EW-LOAD-TRK,EW-BACKFILL,EW-SPREAD-SSL | AT79: Rounded half-up (Excel rule) in revision; may differ by 1 from the notes table, which used banker's rounding. Rent: Median of 5 sources (B 382/1148/3442; R 369/1450/4106; N 365/1250/3450; A 450/1383/3133; C 575/1400/3500). | AU79: Needs rate (owned)
A80: CTL-LARGE | B80: Earthwork | C80: Skid steer / CTL | D80: Compact track loader, large | E80: ROC >3,000 lb | F80: Rated operating capacity | G80: 3500 | H80: lb | I80: Cat 285 XE; Bobcat T770/T86 (3,800); Takeuchi TL12; Kubota SVL97 | K80: 105 | L80: ROC >3,000 lb; Bucket 0.74 yd3 typ (80 in bucket 0.74 yd3 mapped to 3,500 lb+ ROC (notes mapping)) | N80: diesel | O80: Operating Engineer - light/compact group (per WD) | P80: day/wk/4wk | Q80: 500 | R80: 1700 | S80: 4200 | T80: 3950 | U80: 10185 | V80: bare | Y80: W25;B25;R25;A26;C25 | Z80: 2025-2026 | AA80: A | AB80: 8382 | AC80: 62.38 | AD80: FEMA 2025 | AF80: 3.3 | AH80: Cat Dec 2022 single value, 299D3 group [CATFUEL22] | AI80: =IF(OR(AC80="",AF80="",Settings!$B$5=""),"",ROUND(AC80-AF80*Settings!$B$5,2)) -> 50.3 | AJ80: B | AK80: C | AL80: Owned: USACE standby = 0.5 x DEPR + FCCM, max 40 hr/wk [USACE-EP]; with only an all-in rate use Caltrans delay factor x rate, max 8 hr/day & 40 hr/wk [CALT-2627]: no class factor captured, use 0.10-0.22 band (inference). Rental: accrues by calendar period. FEMA: not eligible unless intermittent use [FEMA-PG]. | AM80: tilt-trailer | AP80: N | AQ80: =IFERROR(IF(AND(INDEX(Mob_Demob!$D$6:$D$14,MATCH(AM80,Mob_Demob!$A$6:$A$14,0))="",INDEX(Mob_Demob!$G$6:$G$14,MATCH(AM80,Mob_Demob!$A$6:$A$14,0))=""),"",ROUND(MAX(N(INDEX(Mob_Demob!$G$6:$G$14,MATCH(AM80,Mob_Demob!$A$6:$A$14,0))),N(INDEX(Mob_Demob!$D$6:$D$14,MATCH(AM80,Mob_Demob!$A$6:$A$14,0)))*Settings!$B$6)+IF(AP80="Y",N(INDEX(Mob_Demob!$I$6:$I$14,MATCH(AM80,Mob_Demob!$A$6:$A$14,0)))*Settings!$B$19,0)+N(INDEX(Mob_Demob!$L$6:$L$14,MATCH(AM80,Mob_Demob!$A$6:$A$14,0)))*N(INDEX(Mob_Demob!$K$6:$K$14,MATCH(AM80,Mob_Demob!$A$6:$A$14,0)))*Settings!$B$6+N(INDEX(Mob_Demob!$M$6:$M$14,MATCH(AM80,Mob_Demob!$A$6:$A$14,0)))*N(INDEX(Mob_Demob!$N$6:$N$14,MATCH(AM80,Mob_Demob!$A$6:$A$14,0))),0)),"") -> 500 | AR80: =IF(AQ80="","",ROUND(AQ80*Settings!$B$18,0)) -> 500 | AS80: EW-LOAD-TRK,EW-BACKFILL,EW-SPREAD-SSL | AT80: Rent: Median of 5 sources (W 1211/3511/10185; B 448/1342/4028; R 475/1850/4748; A 500/1700/3950; C 700/1700/4200). FEMA: FEMA 8382 Bobcat T86 (to 105 hp). Ex-fuel (C) = FEMA incl-fuel rate - Fuel_gal_hr_med x diesel back-out price (Settings B5).
A81: SC-621-24 | B81: Earthwork | C81: Wheel tractor scraper | D81: Open bowl, single engine | E81: 24 yd3 bowl | F81: Bowl capacity (heaped) | G81: 24 | H81: yd3 | I81: Cat 621 | L81: 24 yd3 heaped; rated load 57,610 lb | N81: diesel | O81: Operating Engineer - heavy equip. group (per WD) | P81: day/wk/4wk | V81: bare | AA81: D | AB81: 8524 | AC81: 189.79 | AD81: FEMA 2025 | AE81: 5.14 | AF81: 6.56 | AG81: 7.97 | AH81: Cat VisionLink Dec 2022, model 621K [CATFUEL22] | AI81: =IF(OR(AC81="",AF81="",Settings!$B$5=""),"",ROUND(AC81-AF81*Settings!$B$5,2)) -> 165.78 | AJ81: B | AK81: C | AL81: Owned: USACE standby = 0.5 x DEPR + FCCM, max 40 hr/wk [USACE-EP]; with only an all-in rate use Caltrans delay factor x rate, max 8 hr/day & 40 hr/wk [CALT-2627]: no class factor captured, use 0.10-0.22 band (inference). Rental: accrues by calendar period. FEMA: not eligible unless intermittent use [FEMA-PG]. | AM81: lowboy-permitted | AP81: Y | AQ81: =IFERROR(IF(AND(INDEX(Mob_Demob!$D$6:$D$14,MATCH(AM81,Mob_Demob!$A$6:$A$14,0))="",INDEX(Mob_Demob!$G$6:$G$14,MATCH(AM81,Mob_Demob!$A$6:$A$14,0))=""),"",ROUND(MAX(N(INDEX(Mob_Demob!$G$6:$G$14,MATCH(AM81,Mob_Demob!$A$6:$A$14,0))),N(INDEX(Mob_Demob!$D$6:$D$14,MATCH(AM81,Mob_Demob!$A$6:$A$14,0)))*Settings!$B$6)+IF(AP81="Y",N(INDEX(Mob_Demob!$I$6:$I$14,MATCH(AM81,Mob_Demob!$A$6:$A$14,0)))*Settings!$B$19,0)+N(INDEX(Mob_Demob!$L$6:$L$14,MATCH(AM81,Mob_Demob!$A$6:$A$14,0)))*N(INDEX(Mob_Demob!$K$6:$K$14,MATCH(AM81,Mob_Demob!$A$6:$A$14,0)))*Settings!$B$6+N(INDEX(Mob_Demob!$M$6:$M$14,MATCH(AM81,Mob_Demob!$A$6:$A$14,0)))*N(INDEX(Mob_Demob!$N$6:$N$14,MATCH(AM81,Mob_Demob!$A$6:$A$14,0))),0)),"") -> 1800 | AR81: =IF(AQ81="","",ROUND(AQ81*Settings!$B$18,0)) -> 1800 | AS81: EW-SCR-1000,EW-SCR-2000,EW-SCR-3000 | AT81: No published scraper rental rates found. Weight not in notes; transport assumed permitted. Loaded top speed 33.5 mph; 407 hp [CAT-SCR-PG]. Ex-fuel (C) = FEMA incl-fuel rate - Fuel_gal_hr_med x diesel back-out price (Settings B5). | AU81: Needs rate (rental)
A82: SC-623-23 | B82: Earthwork | C82: Wheel tractor scraper | D82: Elevating | E82: 23 yd3 bowl | F82: Bowl capacity (heaped) | G82: 23 | H82: yd3 | I82: Cat 623 | L82: 23 yd3 heaped; rated load 55,200 lb | N82: diesel | O82: Operating Engineer - heavy equip. group (per WD) | P82: day/wk/4wk | V82: bare | AA82: D | AE82: 5.93 | AF82: 7.59 | AG82: 9.25 | AH82: Cat VisionLink Dec 2022, model 623K [CATFUEL22] | AJ82: D | AK82: D | AL82: Owned: USACE standby = 0.5 x DEPR + FCCM, max 40 hr/wk [USACE-EP]; with only an all-in rate use Caltrans delay factor x rate, max 8 hr/day & 40 hr/wk [CALT-2627]: no class factor captured, use 0.10-0.22 band (inference). Rental: accrues by calendar period. FEMA: not eligible unless intermittent use [FEMA-PG]. | AM82: lowboy-permitted | AP82: Y | AQ82: =IFERROR(IF(AND(INDEX(Mob_Demob!$D$6:$D$14,MATCH(AM82,Mob_Demob!$A$6:$A$14,0))="",INDEX(Mob_Demob!$G$6:$G$14,MATCH(AM82,Mob_Demob!$A$6:$A$14,0))=""),"",ROUND(MAX(N(INDEX(Mob_Demob!$G$6:$G$14,MATCH(AM82,Mob_Demob!$A$6:$A$14,0))),N(INDEX(Mob_Demob!$D$6:$D$14,MATCH(AM82,Mob_Demob!$A$6:$A$14,0)))*Settings!$B$6)+IF(AP82="Y",N(INDEX(Mob_Demob!$I$6:$I$14,MATCH(AM82,Mob_Demob!$A$6:$A$14,0)))*Settings!$B$19,0)+N(INDEX(Mob_Demob!$L$6:$L$14,MATCH(AM82,Mob_Demob!$A$6:$A$14,0)))*N(INDEX(Mob_Demob!$K$6:$K$14,MATCH(AM82,Mob_Demob!$A$6:$A$14,0)))*Settings!$B$6+N(INDEX(Mob_Demob!$M$6:$M$14,MATCH(AM82,Mob_Demob!$A$6:$A$14,0)))*N(INDEX(Mob_Demob!$N$6:$N$14,MATCH(AM82,Mob_Demob!$A$6:$A$14,0))),0)),"") -> 1800 | AR82: =IF(AQ82="","",ROUND(AQ82*Settings!$B$18,0)) -> 1800 | AS82: EW-SCR-1000,EW-SCR-2000,EW-SCR-3000 | AT82: No published scraper rental rates found. Weight not in notes; transport assumed permitted. | AU82: Needs rate; Needs rate (rental); Needs rate (owned)
A83: SC-627-24 | B83: Earthwork | C83: Wheel tractor scraper | D83: Open bowl, tandem-powered (push-pull) | E83: 24 yd3 bowl | F83: Bowl capacity (heaped) | G83: 24 | H83: yd3 | I83: Cat 627 | L83: 24 yd3 heaped; rated load not in specs | N83: diesel | O83: Operating Engineer - heavy equip. group (per WD) | P83: day/wk/4wk | V83: bare | AA83: D | AE83: 10.52 | AF83: 9.77 | AG83: 9.03 | AH83: Cat VisionLink Dec 2022, model 627K [CATFUEL22] | AJ83: D | AK83: D | AL83: Owned: USACE standby = 0.5 x DEPR + FCCM, max 40 hr/wk [USACE-EP]; with only an all-in rate use Caltrans delay factor x rate, max 8 hr/day & 40 hr/wk [CALT-2627]: no class factor captured, use 0.10-0.22 band (inference). Rental: accrues by calendar period. FEMA: not eligible unless intermittent use [FEMA-PG]. | AM83: lowboy-permitted | AP83: Y | AQ83: =IFERROR(IF(AND(INDEX(Mob_Demob!$D$6:$D$14,MATCH(AM83,Mob_Demob!$A$6:$A$14,0))="",INDEX(Mob_Demob!$G$6:$G$14,MATCH(AM83,Mob_Demob!$A$6:$A$14,0))=""),"",ROUND(MAX(N(INDEX(Mob_Demob!$G$6:$G$14,MATCH(AM83,Mob_Demob!$A$6:$A$14,0))),N(INDEX(Mob_Demob!$D$6:$D$14,MATCH(AM83,Mob_Demob!$A$6:$A$14,0)))*Settings!$B$6)+IF(AP83="Y",N(INDEX(Mob_Demob!$I$6:$I$14,MATCH(AM83,Mob_Demob!$A$6:$A$14,0)))*Settings!$B$19,0)+N(INDEX(Mob_Demob!$L$6:$L$14,MATCH(AM83,Mob_Demob!$A$6:$A$14,0)))*N(INDEX(Mob_Demob!$K$6:$K$14,MATCH(AM83,Mob_Demob!$A$6:$A$14,0)))*Settings!$B$6+N(INDEX(Mob_Demob!$M$6:$M$14,MATCH(AM83,Mob_Demob!$A$6:$A$14,0)))*N(INDEX(Mob_Demob!$N$6:$N$14,MATCH(AM83,Mob_Demob!$A$6:$A$14,0))),0)),"") -> 1800 | AR83: =IF(AQ83="","",ROUND(AQ83*Settings!$B$18,0)) -> 1800 | AS83: EW-SCR-1000,EW-SCR-2000,EW-SCR-3000 | AT83: No published scraper rental rates found. Cat VisionLink values run high->low (low 10.52 > high 9.03) as published. Weight not in notes; transport assumed permitted. | AU83: Needs rate; Fuel low/high inverted in source; Needs rate (rental); Needs rate (owned)
A84: SC-631-34 | B84: Earthwork | C84: Wheel tractor scraper | D84: Open bowl, single engine | E84: 34 yd3 bowl | F84: Bowl capacity (heaped) | G84: 34 | H84: yd3 | I84: Cat 631 | L84: 34 yd3 heaped; rated load 82,200 lb | N84: diesel | O84: Operating Engineer - heavy equip. group (per WD) | P84: day/wk/4wk | V84: bare | AA84: D | AB84: 8521 | AC84: 344.22 | AD84: FEMA 2025 | AE84: 6.99 | AF84: 9.06 | AG84: 11.13 | AH84: Cat VisionLink Dec 2022, model 631K [CATFUEL22] | AI84: =IF(OR(AC84="",AF84="",Settings!$B$5=""),"",ROUND(AC84-AF84*Settings!$B$5,2)) -> 311.06 | AJ84: B | AK84: C | AL84: Owned: USACE standby = 0.5 x DEPR + FCCM, max 40 hr/wk [USACE-EP]; with only an all-in rate use Caltrans delay factor x rate, max 8 hr/day & 40 hr/wk [CALT-2627]: no class factor captured, use 0.10-0.22 band (inference). Rental: accrues by calendar period. FEMA: not eligible unless intermittent use [FEMA-PG]. | AM84: lowboy-permitted | AP84: Y | AQ84: =IFERROR(IF(AND(INDEX(Mob_Demob!$D$6:$D$14,MATCH(AM84,Mob_Demob!$A$6:$A$14,0))="",INDEX(Mob_Demob!$G$6:$G$14,MATCH(AM84,Mob_Demob!$A$6:$A$14,0))=""),"",ROUND(MAX(N(INDEX(Mob_Demob!$G$6:$G$14,MATCH(AM84,Mob_Demob!$A$6:$A$14,0))),N(INDEX(Mob_Demob!$D$6:$D$14,MATCH(AM84,Mob_Demob!$A$6:$A$14,0)))*Settings!$B$6)+IF(AP84="Y",N(INDEX(Mob_Demob!$I$6:$I$14,MATCH(AM84,Mob_Demob!$A$6:$A$14,0)))*Settings!$B$19,0)+N(INDEX(Mob_Demob!$L$6:$L$14,MATCH(AM84,Mob_Demob!$A$6:$A$14,0)))*N(INDEX(Mob_Demob!$K$6:$K$14,MATCH(AM84,Mob_Demob!$A$6:$A$14,0)))*Settings!$B$6+N(INDEX(Mob_Demob!$M$6:$M$14,MATCH(AM84,Mob_Demob!$A$6:$A$14,0)))*N(INDEX(Mob_Demob!$N$6:$N$14,MATCH(AM84,Mob_Demob!$A$6:$A$14,0))),0)),"") -> 1800 | AR84: =IF(AQ84="","",ROUND(AQ84*Settings!$B$18,0)) -> 1800 | AS84: EW-SCR-1000,EW-SCR-2000,EW-SCR-3000 | AT84: No published scraper rental rates found. Weight not in notes; transport assumed permitted. Loaded top speed 34.7 mph; 570 hp [CAT-SCR-PG]. Ex-fuel (C) = FEMA incl-fuel rate - Fuel_gal_hr_med x diesel back-out price (Settings B5). | AU84: Needs rate (rental)
A85: SC-637-34 | B85: Earthwork | C85: Wheel tractor scraper | D85: Open bowl, tandem-powered | E85: 34 yd3 bowl | F85: Bowl capacity (heaped) | G85: 34 | H85: yd3 | I85: Cat 637 (coal bowl 50 yd) | L85: 34 yd3 heaped; rated load 82,200 lb | N85: diesel | O85: Operating Engineer - heavy equip. group (per WD) | P85: day/wk/4wk | V85: bare | AA85: D | AE85: 12.6 | AF85: 12.2 | AG85: 11.79 | AH85: Cat VisionLink Dec 2022, model 637K [CATFUEL22] | AJ85: D | AK85: D | AL85: Owned: USACE standby = 0.5 x DEPR + FCCM, max 40 hr/wk [USACE-EP]; with only an all-in rate use Caltrans delay factor x rate, max 8 hr/day & 40 hr/wk [CALT-2627]: no class factor captured, use 0.10-0.22 band (inference). Rental: accrues by calendar period. FEMA: not eligible unless intermittent use [FEMA-PG]. | AM85: lowboy-permitted | AP85: Y | AQ85: =IFERROR(IF(AND(INDEX(Mob_Demob!$D$6:$D$14,MATCH(AM85,Mob_Demob!$A$6:$A$14,0))="",INDEX(Mob_Demob!$G$6:$G$14,MATCH(AM85,Mob_Demob!$A$6:$A$14,0))=""),"",ROUND(MAX(N(INDEX(Mob_Demob!$G$6:$G$14,MATCH(AM85,Mob_Demob!$A$6:$A$14,0))),N(INDEX(Mob_Demob!$D$6:$D$14,MATCH(AM85,Mob_Demob!$A$6:$A$14,0)))*Settings!$B$6)+IF(AP85="Y",N(INDEX(Mob_Demob!$I$6:$I$14,MATCH(AM85,Mob_Demob!$A$6:$A$14,0)))*Settings!$B$19,0)+N(INDEX(Mob_Demob!$L$6:$L$14,MATCH(AM85,Mob_Demob!$A$6:$A$14,0)))*N(INDEX(Mob_Demob!$K$6:$K$14,MATCH(AM85,Mob_Demob!$A$6:$A$14,0)))*Settings!$B$6+N(INDEX(Mob_Demob!$M$6:$M$14,MATCH(AM85,Mob_Demob!$A$6:$A$14,0)))*N(INDEX(Mob_Demob!$N$6:$N$14,MATCH(AM85,Mob_Demob!$A$6:$A$14,0))),0)),"") -> 1800 | AR85: =IF(AQ85="","",ROUND(AQ85*Settings!$B$18,0)) -> 1800 | AS85: EW-SCR-1000,EW-SCR-2000,EW-SCR-3000 | AT85: No published scraper rental rates found. Fuel values inverted as published. Weight not in notes; transport assumed permitted. 637 Coal Bowl 50 yd3 variant not catalogued separately. | AU85: Needs rate; Fuel low/high inverted in source; Needs rate (rental); Needs rate (owned)
A86: SC-651-44 | B86: Earthwork | C86: Wheel tractor scraper | D86: Open bowl, single engine | E86: 44 yd3 bowl | F86: Bowl capacity (heaped) | G86: 44 | H86: yd3 | I86: Cat 651 | L86: 44 yd3 heaped; rated load not in specs | N86: diesel | O86: Operating Engineer - heavy equip. group (per WD) | P86: day/wk/4wk | V86: bare | AA86: D | AB86: 8522 | AC86: 545.78 | AD86: FEMA 2025 | AI86: =IF(OR(AC86="",AF86="",Settings!$B$5=""),"",ROUND(AC86-AF86*Settings!$B$5,2)) | AJ86: B | AK86: C | AL86: Owned: USACE standby = 0.5 x DEPR + FCCM, max 40 hr/wk [USACE-EP]; with only an all-in rate use Caltrans delay factor x rate, max 8 hr/day & 40 hr/wk [CALT-2627]: no class factor captured, use 0.10-0.22 band (inference). Rental: accrues by calendar period. FEMA: not eligible unless intermittent use [FEMA-PG]. | AM86: lowboy-permitted | AP86: Y | AQ86: =IFERROR(IF(AND(INDEX(Mob_Demob!$D$6:$D$14,MATCH(AM86,Mob_Demob!$A$6:$A$14,0))="",INDEX(Mob_Demob!$G$6:$G$14,MATCH(AM86,Mob_Demob!$A$6:$A$14,0))=""),"",ROUND(MAX(N(INDEX(Mob_Demob!$G$6:$G$14,MATCH(AM86,Mob_Demob!$A$6:$A$14,0))),N(INDEX(Mob_Demob!$D$6:$D$14,MATCH(AM86,Mob_Demob!$A$6:$A$14,0)))*Settings!$B$6)+IF(AP86="Y",N(INDEX(Mob_Demob!$I$6:$I$14,MATCH(AM86,Mob_Demob!$A$6:$A$14,0)))*Settings!$B$19,0)+N(INDEX(Mob_Demob!$L$6:$L$14,MATCH(AM86,Mob_Demob!$A$6:$A$14,0)))*N(INDEX(Mob_Demob!$K$6:$K$14,MATCH(AM86,Mob_Demob!$A$6:$A$14,0)))*Settings!$B$6+N(INDEX(Mob_Demob!$M$6:$M$14,MATCH(AM86,Mob_Demob!$A$6:$A$14,0)))*N(INDEX(Mob_Demob!$N$6:$N$14,MATCH(AM86,Mob_Demob!$A$6:$A$14,0))),0)),"") -> 1800 | AR86: =IF(AQ86="","",ROUND(AQ86*Settings!$B$18,0)) -> 1800 | AS86: EW-SCR-1000,EW-SCR-2000,EW-SCR-3000 | AT86: No published scraper rental rates found. No Cat fuel row for 651 and no HP captured. Weight not in notes; transport assumed permitted. Ex-fuel (C) = FEMA incl-fuel rate - Fuel_gal_hr_med x diesel back-out price (Settings B5). | AU86: Needs fuel gal/hr; Needs rate (rental)
A87: SC-657-44 | B87: Earthwork | C87: Wheel tractor scraper | D87: Open bowl, tandem-powered | E87: 44 yd3 bowl | F87: Bowl capacity (heaped) | G87: 44 | H87: yd3 | I87: Cat 657 | L87: 44 yd3 heaped; rated load 104,000 lb | N87: diesel | O87: Operating Engineer - heavy equip. group (per WD) | P87: day/wk/4wk | V87: bare | AA87: D | AE87: 15.65 | AF87: 13.87 | AG87: 12.08 | AH87: Cat VisionLink Dec 2022, model 657-07 [CATFUEL22] | AJ87: D | AK87: D | AL87: Owned: USACE standby = 0.5 x DEPR + FCCM, max 40 hr/wk [USACE-EP]; with only an all-in rate use Caltrans delay factor x rate, max 8 hr/day & 40 hr/wk [CALT-2627]: no class factor captured, use 0.10-0.22 band (inference). Rental: accrues by calendar period. FEMA: not eligible unless intermittent use [FEMA-PG]. | AM87: lowboy-permitted | AP87: Y | AQ87: =IFERROR(IF(AND(INDEX(Mob_Demob!$D$6:$D$14,MATCH(AM87,Mob_Demob!$A$6:$A$14,0))="",INDEX(Mob_Demob!$G$6:$G$14,MATCH(AM87,Mob_Demob!$A$6:$A$14,0))=""),"",ROUND(MAX(N(INDEX(Mob_Demob!$G$6:$G$14,MATCH(AM87,Mob_Demob!$A$6:$A$14,0))),N(INDEX(Mob_Demob!$D$6:$D$14,MATCH(AM87,Mob_Demob!$A$6:$A$14,0)))*Settings!$B$6)+IF(AP87="Y",N(INDEX(Mob_Demob!$I$6:$I$14,MATCH(AM87,Mob_Demob!$A$6:$A$14,0)))*Settings!$B$19,0)+N(INDEX(Mob_Demob!$L$6:$L$14,MATCH(AM87,Mob_Demob!$A$6:$A$14,0)))*N(INDEX(Mob_Demob!$K$6:$K$14,MATCH(AM87,Mob_Demob!$A$6:$A$14,0)))*Settings!$B$6+N(INDEX(Mob_Demob!$M$6:$M$14,MATCH(AM87,Mob_Demob!$A$6:$A$14,0)))*N(INDEX(Mob_Demob!$N$6:$N$14,MATCH(AM87,Mob_Demob!$A$6:$A$14,0))),0)),"") -> 1800 | AR87: =IF(AQ87="","",ROUND(AQ87*Settings!$B$18,0)) -> 1800 | AS87: EW-SCR-1000,EW-SCR-2000,EW-SCR-3000 | AT87: No published scraper rental rates found. Fuel values inverted as published. Weight not in notes; transport assumed permitted. Loaded top speed 33 mph; 637 + 479 hp [CAT-SCR-PG]. | AU87: Needs rate; Fuel low/high inverted in source; Needs rate (rental); Needs rate (owned)
A88: SC-PULL-4CY | B88: Earthwork | C88: Pull scraper (towed) | D88: Box / pull pan | E88: 4.1 CY, 84 in | F88: Bowl capacity | G88: 4.1 | H88: CY | I88: Rome 5C | L88: 4.1 CY | N88: none (towed) | O88: None (non-operated item) | P88: day/wk/4wk | V88: bare | AA88: D | AB88: 8269 | AC88: 18.41 | AD88: FEMA 2025 | AE88: 0 | AF88: 0 | AG88: 0 | AH88: No engine (towed / attachment / non-powered) | AI88: =IF(OR(AC88="",AF88="",Settings!$B$5=""),"",ROUND(AC88-AF88*Settings!$B$5,2)) -> 18.41 | AJ88: B | AK88: C | AL88: Owned: USACE standby = 0.5 x DEPR + FCCM, max 40 hr/wk [USACE-EP]; with only an all-in rate use Caltrans delay factor x rate, max 8 hr/day & 40 hr/wk [CALT-2627]: no class factor captured, use 0.10-0.22 band (inference). Rental: accrues by calendar period. FEMA: not eligible unless intermittent use [FEMA-PG]. | AM88: flatbed | AP88: N | AQ88: =IFERROR(IF(AND(INDEX(Mob_Demob!$D$6:$D$14,MATCH(AM88,Mob_Demob!$A$6:$A$14,0))="",INDEX(Mob_Demob!$G$6:$G$14,MATCH(AM88,Mob_Demob!$A$6:$A$14,0))=""),"",ROUND(MAX(N(INDEX(Mob_Demob!$G$6:$G$14,MATCH(AM88,Mob_Demob!$A$6:$A$14,0))),N(INDEX(Mob_Demob!$D$6:$D$14,MATCH(AM88,Mob_Demob!$A$6:$A$14,0)))*Settings!$B$6)+IF(AP88="Y",N(INDEX(Mob_Demob!$I$6:$I$14,MATCH(AM88,Mob_Demob!$A$6:$A$14,0)))*Settings!$B$19,0)+N(INDEX(Mob_Demob!$L$6:$L$14,MATCH(AM88,Mob_Demob!$A$6:$A$14,0)))*N(INDEX(Mob_Demob!$K$6:$K$14,MATCH(AM88,Mob_Demob!$A$6:$A$14,0)))*Settings!$B$6+N(INDEX(Mob_Demob!$M$6:$M$14,MATCH(AM88,Mob_Demob!$A$6:$A$14,0)))*N(INDEX(Mob_Demob!$N$6:$N$14,MATCH(AM88,Mob_Demob!$A$6:$A$14,0))),0)),"") -> 400 | AR88: =IF(AQ88="","",ROUND(AQ88*Settings!$B$18,0)) -> 400 | AT88: Towed by a tractor/dozer priced separately. Ex-fuel = incl-fuel rate (no liquid fuel to back out). | AU88: Needs rate (rental)
A89: GR-COMPACT | B89: Earthwork | C89: Motor grader | D89: Compact | E89: Compact grader | F89: Model | G89: CG65E | I89: Cat CG65E | N89: diesel | O89: Operating Engineer - heavy equip. group (per WD) | P89: day/wk/4wk | Q89: 1073 | R89: 3111 | S89: 9021 | V89: bare | Y89: W25 | Z89: 2025 | AA89: B | AJ89: D | AK89: D | AL89: Owned: USACE standby = 0.5 x DEPR + FCCM, max 40 hr/wk [USACE-EP]; with only an all-in rate use Caltrans delay factor x rate, max 8 hr/day & 40 hr/wk [CALT-2627]: GRADR factor 0.11 (book) / 0.10 (interim). Rental: accrues by calendar period (no idle discount). FEMA: not eligible unless intermittent use [FEMA-PG]. | AM89: lowboy-legal | AP89: maybe | AQ89: =IFERROR(IF(AND(INDEX(Mob_Demob!$D$6:$D$14,MATCH(AM89,Mob_Demob!$A$6:$A$14,0))="",INDEX(Mob_Demob!$G$6:$G$14,MATCH(AM89,Mob_Demob!$A$6:$A$14,0))=""),"",ROUND(MAX(N(INDEX(Mob_Demob!$G$6:$G$14,MATCH(AM89,Mob_Demob!$A$6:$A$14,0))),N(INDEX(Mob_Demob!$D$6:$D$14,MATCH(AM89,Mob_Demob!$A$6:$A$14,0)))*Settings!$B$6)+IF(AP89="Y",N(INDEX(Mob_Demob!$I$6:$I$14,MATCH(AM89,Mob_Demob!$A$6:$A$14,0)))*Settings!$B$19,0)+N(INDEX(Mob_Demob!$L$6:$L$14,MATCH(AM89,Mob_Demob!$A$6:$A$14,0)))*N(INDEX(Mob_Demob!$K$6:$K$14,MATCH(AM89,Mob_Demob!$A$6:$A$14,0)))*Settings!$B$6+N(INDEX(Mob_Demob!$M$6:$M$14,MATCH(AM89,Mob_Demob!$A$6:$A$14,0)))*N(INDEX(Mob_Demob!$N$6:$N$14,MATCH(AM89,Mob_Demob!$A$6:$A$14,0))),0)),"") -> 550 | AR89: =IF(AQ89="","",ROUND(AQ89*Settings!$B$18,0)) -> 550 | AS89: EW-FGRADE | AT89: Specs not in notes. Rent: Wheeler only. | AU89: Needs fuel gal/hr; Needs rate (owned)
A90: GR-12FT-120 | B90: Earthwork | C90: Motor grader | D90: 12 ft moldboard | E90: 12 ft (Cat 120) | F90: Moldboard length | G90: 12 | H90: ft | I90: Cat 120 (130 hp, 35,067 lb) | J90: 35067 | K90: 130 | L90: 12 ft moldboard | N90: diesel | O90: Operating Engineer - heavy equip. group (per WD) | P90: day/wk/4wk | V90: bare | AA90: D | AB90: 8331 | AC90: 131.96 | AD90: FEMA 2025 | AE90: 2.35 | AF90: 2.9 | AG90: 3.45 | AH90: Cat VisionLink Dec 2022, model 120-14 [CATFUEL22] | AI90: =IF(OR(AC90="",AF90="",Settings!$B$5=""),"",ROUND(AC90-AF90*Settings!$B$5,2)) -> 121.35 | AJ90: B | AK90: C | AL90: Owned: USACE standby = 0.5 x DEPR + FCCM, max 40 hr/wk [USACE-EP]; with only an all-in rate use Caltrans delay factor x rate, max 8 hr/day & 40 hr/wk [CALT-2627]: GRADR factor 0.11 (book) / 0.10 (interim). Rental: accrues by calendar period (no idle discount). FEMA: not eligible unless intermittent use [FEMA-PG]. | AM90: lowboy-legal | AN90: 35067 | AP90: N | AQ90: =IFERROR(IF(AND(INDEX(Mob_Demob!$D$6:$D$14,MATCH(AM90,Mob_Demob!$A$6:$A$14,0))="",INDEX(Mob_Demob!$G$6:$G$14,MATCH(AM90,Mob_Demob!$A$6:$A$14,0))=""),"",ROUND(MAX(N(INDEX(Mob_Demob!$G$6:$G$14,MATCH(AM90,Mob_Demob!$A$6:$A$14,0))),N(INDEX(Mob_Demob!$D$6:$D$14,MATCH(AM90,Mob_Demob!$A$6:$A$14,0)))*Settings!$B$6)+IF(AP90="Y",N(INDEX(Mob_Demob!$I$6:$I$14,MATCH(AM90,Mob_Demob!$A$6:$A$14,0)))*Settings!$B$19,0)+N(INDEX(Mob_Demob!$L$6:$L$14,MATCH(AM90,Mob_Demob!$A$6:$A$14,0)))*N(INDEX(Mob_Demob!$K$6:$K$14,MATCH(AM90,Mob_Demob!$A$6:$A$14,0)))*Settings!$B$6+N(INDEX(Mob_Demob!$M$6:$M$14,MATCH(AM90,Mob_Demob!$A$6:$A$14,0)))*N(INDEX(Mob_Demob!$N$6:$N$14,MATCH(AM90,Mob_Demob!$A$6:$A$14,0))),0)),"") -> 550 | AR90: =IF(AQ90="","",ROUND(AQ90*Settings!$B$18,0)) -> 550 | AS90: EW-FGRADE,EW-RGRADE-GR,EW-SPREAD-BASE | AT90: Ex-fuel (C) = FEMA incl-fuel rate - Fuel_gal_hr_med x diesel back-out price (Settings B5). | AU90: Needs rate (rental)
A91: GR-12FT-140 | B91: Earthwork | C91: Motor grader | D91: 12 ft moldboard | E91: 12 ft (Cat 140) | F91: Moldboard length | G91: 12 | H91: ft | I91: Cat 140/140 AWD (179 hp, 42,647 lb); 140 GC | J91: 42647 | K91: 179 | L91: 12 ft moldboard | N91: diesel | O91: Operating Engineer - heavy equip. group (per WD) | P91: day/wk/4wk | Q91: 1949 | R91: 5652 | S91: 16389 | V91: bare | Y91: W25 | Z91: 2025 | AA91: B | AB91: 8332 | AC91: 159.04 | AD91: FEMA 2025 | AE91: 2.83 | AF91: 3.53 | AG91: 4.24 | AH91: Cat VisionLink Dec 2022, model 140-15 [CATFUEL22] | AI91: =IF(OR(AC91="",AF91="",Settings!$B$5=""),"",ROUND(AC91-AF91*Settings!$B$5,2)) -> 146.12 | AJ91: B | AK91: C | AL91: Owned: USACE standby = 0.5 x DEPR + FCCM, max 40 hr/wk [USACE-EP]; with only an all-in rate use Caltrans delay factor x rate, max 8 hr/day & 40 hr/wk [CALT-2627]: GRADR factor 0.11 (book) / 0.10 (interim). Rental: accrues by calendar period (no idle discount). FEMA: not eligible unless intermittent use [FEMA-PG]. | AM91: lowboy-legal | AN91: 42647 | AP91: N | AQ91: =IFERROR(IF(AND(INDEX(Mob_Demob!$D$6:$D$14,MATCH(AM91,Mob_Demob!$A$6:$A$14,0))="",INDEX(Mob_Demob!$G$6:$G$14,MATCH(AM91,Mob_Demob!$A$6:$A$14,0))=""),"",ROUND(MAX(N(INDEX(Mob_Demob!$G$6:$G$14,MATCH(AM91,Mob_Demob!$A$6:$A$14,0))),N(INDEX(Mob_Demob!$D$6:$D$14,MATCH(AM91,Mob_Demob!$A$6:$A$14,0)))*Settings!$B$6)+IF(AP91="Y",N(INDEX(Mob_Demob!$I$6:$I$14,MATCH(AM91,Mob_Demob!$A$6:$A$14,0)))*Settings!$B$19,0)+N(INDEX(Mob_Demob!$L$6:$L$14,MATCH(AM91,Mob_Demob!$A$6:$A$14,0)))*N(INDEX(Mob_Demob!$K$6:$K$14,MATCH(AM91,Mob_Demob!$A$6:$A$14,0)))*Settings!$B$6+N(INDEX(Mob_Demob!$M$6:$M$14,MATCH(AM91,Mob_Demob!$A$6:$A$14,0)))*N(INDEX(Mob_Demob!$N$6:$N$14,MATCH(AM91,Mob_Demob!$A$6:$A$14,0))),0)),"") -> 550 | AR91: =IF(AQ91="","",ROUND(AQ91*Settings!$B$18,0)) -> 550 | AS91: EW-FGRADE,EW-RGRADE-GR,EW-SPREAD-BASE | AT91: Wheeler single-source dealer pricing; independents likely 20-35% lower (notes inference). Rent: Wheeler 140/150 line. Ex-fuel (C) = FEMA incl-fuel rate - Fuel_gal_hr_med x diesel back-out price (Settings B5).
